Workbook
Name Account: #REF!
Name Account: #REF!
Name Accountno: #REF!
Name Accountno: #REF!
Name Catcode: #REF!
Name Catcode: #REF!
Name CodeT1: #REF!
Name CodeT1: #REF!
Name CodeT2: #REF!
Name CodeT2: #REF!
Name CodeT3: #REF!
Name CodeT3: #REF!
Name FADesc: #REF!
Name FADesc: #REF!
Name Leaseterm: #REF!
Name Leaseterm: #REF!
Name lkpOrderID: '[1]OrderName Data'!$A$2:$A$5000
Name lkpOrderID: '[1]OrderName Data'!$A$2:$A$5000
Name TotFAInputAmt: 资产分摊表!$U$3
Name TotFAInvAmt: 资产分摊表!$K$3
Name vrDateEntryFormat: [1]Configuration!$C$8
Name vrDateEntryFormat: [1]Configuration!$C$8
Name vrDialogTitle: [1]Parameters!$C$19
Name vrDialogTitle: [1]Parameters!$C$19
Name vrPaymentType: [1]Configuration!$C$5
Name vrPaymentType: [1]Configuration!$C$5

Sheet FA
A1: 麦当劳(中国)工程预算书 - 投标报价 FA Tool (IN RMB) V20250409
A2: 注意： 该“投标报价 FA Tool”的格式不得进行改动 | G2: 总价（不含税） | H2: =G179 -> 603552.92 | J2: 总价（含增值税） | M2: =ROUND(H2*1.09,2) -> 657872.68
F3: 区域 | G3: ='预算书-初步'!J2 -> 中区 | J3: 麦当劳项目经理 | K3: ='预算书-初步'!O2 -> 高虹
F4: 市场/城市 | G4: ='预算书-初步'!J3 -> 上海 | J4: 餐厅类型 | K4: ='预算书-初步'!O3 -> 新店 | M4: ='预算书-初步'!P3 -> Instore
F5: 餐厅名称 | G5: ='预算书-初步'!J5 -> 浦东张江中科路地铁站餐厅 | J5: 招标方式 | K5: ='预算书-初步'!O4 -> 集中招标
F6: 面积 | G6: ='预算书-初步'!J7 -> 185 | J6: 中标单价选用 | K6: ='预算书-初步'!O5 -> 上海锦伟
F7: 座位数 | G7: ='预算书-初步'!J8 -> 40 | J7: 异地施工上浮系数 | K7: ='预算书-初步'!O6 -> 0
E8: FA TOOL
B9: ASSET CODE | C9: PMTCode | E9: LEVEL | F9: DESCRIPTION | G9: Total | H9: Main Store | I9: Remote Kiosk | J9: Attached Kiosk | K9: McCafe | L9: MDS | M9: Hot Kiosk | N9: Dessert bar
I10: 80 | J10: 70 | K10: 60 | L10: 90 | M10: 75
C12: 1001 | D12: A | E12: 1 | F12: LHI - REAL ESTATE COSTS (承租物业改造费用-地产费用) | G12: =G13 -> 0 | H12: =H13 -> 0 | I12: =I13 -> 0 | J12: =J13 -> 0 | K12: =K13 -> 0 | L12: =L13 -> 0 | M12: =M13 -> 0 | N12: =N13 -> 0
C13: 1002 | D13: 0 | E13: 2 | F13: Real Estate Costs | G13: =SUM(G14:G15,G19:G26) -> 0 | H13: =SUM(H14:H15,H19:H26) -> 0 | I13: =SUM(I14:I15,I19:I26) -> 0 | J13: =SUM(J14:J15,J19:J26) -> 0 | K13: =SUM(K14:K15,K19:K26) -> 0 | L13: =SUM(L14:L15,L19:L26) -> 0 | M13: =SUM(M14:M15,M19:M26) -> 0 | N13: =SUM(N14:N15,N19:N26) -> 0
A14: 5 | B14: 6001 | C14: 1003 | D14: 0.1 | E14: 3 | F14: Land 土地
A15: 6 | B15: 6002 | C15: 1004 | D15: 0.2 | E15: 3 | F15: Building 房产建筑 | G15: =SUM(G16:G18) -> 0 | H15: =SUM(H16:H18) -> 0 | I15: =SUM(I16:I18) -> 0 | J15: =SUM(J16:J18) -> 0 | K15: =SUM(K16:K18) -> 0 | L15: =SUM(L16:L18) -> 0 | M15: =SUM(M16:M18) -> 0 | N15: =SUM(N16:N18) -> 0
A16: 7 | C16: 1005 | D16: 1 | E16: 4 | F16: 基础 仅适用于DT | G16: =SUM(H16:N16) -> 0 | H16: =SUMIF('预算书-初步'!A13:A2600,7,'预算书-初步'!P13:P2600)+SUMIF(其他!B9:B1041,FA!C16,其他!E9:E1041) -> 0 | I16: =SUMIF(其他!B9:B1041,FA!C16,其他!G9:G1041) -> 0 | J16: =SUMIF(其他!B9:B1041,FA!C16,其他!I9:I1041) -> 0 | K16: =SUMIF(其他!B9:B1041,FA!C16,其他!K9:K1041) -> 0 | L16: =SUMIF(其他!B9:B1041,FA!C16,其他!M9:M1041) -> 0 | M16: =SUMIF('预算书-初步'!A13:A2600,"大甜7",'预算书-初步'!P13:P2600)+SUMIF(其他!B9:B1041,FA!C16,其他!O9:O1041) -> 0 | N16: =SUMIF(其他!B9:B65,FA!C16,其他!Q9:Q65) -> 0
A17: 8 | C17: 1006 | D17: 2 | E17: 4 | F17: 主体建筑(仅适用于DT) | G17: =SUM(H17:N17) -> 0 | H17: =SUMIF('预算书-初步'!A13:A2600,8,'预算书-初步'!P13:P2600)+SUMIF(其他!B9:B65,FA!C17,其他!E9:E65) -> 0 | I17: =SUMIF(其他!B9:B65,FA!C17,其他!G9:G65) -> 0 | J17: =SUMIF(其他!B9:B1041,FA!C17,其他!I9:I1041) -> 0 | K17: =SUMIF(其他!B9:B65,FA!C17,其他!K9:K65) -> 0 | L17: =SUMIF(其他!B9:B65,FA!C17,其他!M9:M65) -> 0 | M17: =SUMIF('预算书-初步'!A13:A2600,"大甜8",'预算书-初步'!P13:P2600)+SUMIF(其他!B9:B65,FA!C17,其他!O9:O65) -> 0 | N17: =SUMIF(其他!B9:B65,FA!C17,其他!Q9:Q65) -> 0
A18: 9 | C18: 1007 | D18: 3 | E18: 4 | F18: 外立面(仅适用于DT) | G18: =SUM(H18:N18) -> 0 | H18: =SUMIF('预算书-初步'!A13:A2600,9,'预算书-初步'!P13:P2600)+SUMIF(其他!B9:B65,FA!C18,其他!E9:E65) -> 0 | I18: =SUMIF(其他!B9:B65,FA!C18,其他!G9:G65) -> 0 | J18: =SUMIF(其他!B9:B65,FA!C18,其他!I9:I65) -> 0 | K18: =SUMIF(其他!B9:B65,FA!C18,其他!K9:K65) -> 0 | L18: =SUMIF(其他!B9:B65,FA!C18,其他!M9:M65) -> 0 | M18: =SUMIF('预算书-初步'!A13:A2600,"大甜9",'预算书-初步'!P13:P2600)+SUMIF(其他!B9:B65,FA!C18,其他!O9:O65) -> 0 | N18: =SUMIF(其他!B9:B65,FA!C18,其他!Q9:Q65) -> 0
A19: 10 | B19: 6003 | C19: 1008 | D19: 0.3 | E19: 3 | F19: Lease Right 房产使用权 | G19: =SUM(H19:N19) -> 0
A20: 11 | B20: 6004 | C20: 1009 | D20: 0.4 | E20: 3 | F20: Key Money 启动费 | G20: =SUM(H20:N20) -> 0
A21: 12 | B21: 6005 | C21: 1010 | D21: 0.5 | E21: 3 | F21: Landlord Compensation 业主补偿金 | G21: =SUM(H21:N21) -> 0
A22: 13 | B22: 6006 | C22: 1011 | D22: 0.6 | E22: 3 | F22: PO Rent 开业前租金 | G22: =SUM(H22:N22) -> 0
A23: 14 | B23: 6007 | C23: 1012 | D23: 0.7 | E23: 3 | F23: Other R/E Costs 其他地产费用 | G23: =SUM(H23:N23) -> 0
A24: 15 | B24: 9999 | C24: 1013 | D24: 0.8 | E24: 3 | F24: Location Fee | G24: =SUM(H24:N24) -> 0
A25: 16 | B25: 7001 | C25: 1014 | D25: 0.9 | E25: 3 | F25: Capitalized Internal Cost (G&A) 资本化管理费用 | G25: =SUM(H25:N25) -> 0
A26: 17 | B26: 7012 | C26: 1015 | D26: 0.1 | E26: 3 | F26: Capitalized Interest Cost 利息资本化-餐厅开业前租金 | G26: =SUM(H26:N26) -> 0
A27: 18 | C27: 1016 | D27: B | E27: 1 | F27: LEASEHOLD IMPROVEMENT COST (L.H.I.) (承租物业改造费用)(Cons.) | G27: =SUM(G28,G34,G37,G48,G52,G61) -> 541896.01 | H27: =SUM(H28,H34,H37,H48,H52,H61) -> 526028.14 | I27: =SUM(I28,I34,I37,I48,I52,I61) -> 0 | J27: =SUM(J28,J34,J37,J48,J52,J61) -> 0 | K27: =SUM(K28,K34,K37,K48,K52,K61) -> 9027.2 | L27: =SUM(L28,L34,L37,L48,L52,L61) -> 6840.67 | M27: =SUM(M28,M34,M37,M48,M52,M61) -> 0 | N27: =SUM(N28,N34,N37,N48,N52,N61) -> 0
A28: 19 | C28: 1017 | D28: 1 | E28: 2 | F28: Architect/Engineering/structure fees(建筑/机电/结构-设计费) | G28: =SUM(G29,G32:G33) -> 0 | H28: =SUM(H29,H32:H33) -> 0 | I28: =SUM(I29,I32:I33) -> 0 | J28: =SUM(J29,J32:J33) -> 0 | K28: =SUM(K29,K32:K33) -> 0 | L28: =SUM(L29,L32:L33) -> 0 | M28: =SUM(M29,M32:M33) -> 0 | N28: =SUM(N29,N32:N33) -> 0
A29: 20 | C29: 1018 | D29: 1.1 | E29: 3 | F29: Consultation design of Architect/M & E Engineering 建筑/机电设计费 | G29: =SUM(G30:G31) -> 0 | H29: =SUM(H30:H31) -> 0 | I29: =SUM(I30:I31) -> 0 | J29: =SUM(J30:J31) -> 0 | K29: =SUM(K30:K31) -> 0 | L29: =SUM(L30:L31) -> 0 | M29: =SUM(M30:M31) -> 0 | N29: =SUM(N30:N31) -> 0
A30: 21 | B30: 1110 | C30: 1019 | D30: 1.1.1 | E30: 4 | F30: Local Design 本地设计费 | G30: =SUM(H30:N30) -> 0 | H30: =SUMIF(其他!B9:B65,FA!C30,其他!E9:E65) -> 0 | I30: =SUMIF(其他!B9:B65,FA!C30,其他!G9:G65) -> 0 | J30: =SUMIF(其他!B9:B65,FA!C30,其他!I9:I65) -> 0 | K30: =SUMIF(其他!B9:B65,FA!C30,其他!K9:K65) -> 0 | L30: =SUMIF(其他!B9:B65,FA!C30,其他!M9:M65) -> 0 | M30: =SUMIF(其他!B9:B65,FA!C30,其他!O9:O65) -> 0 | N30: =SUMIF(其他!B9:B65,FA!C30,其他!Q9:Q65) -> 0
A31: 22 | B31: 1110 | C31: 1020 | D31: 1.1.2 | E31: 4 | F31: APMEA CHARGEBACK 亚太设计费 | G31: =SUM(H31:N31) -> 0 | H31: =SUMIF(其他!B10:B66,FA!C31,其他!E10:E66) -> 0 | I31: =SUMIF(其他!B9:B65,FA!C31,其他!G9:G65) -> 0 | J31: =SUMIF(其他!B9:B65,FA!C31,其他!I9:I65) -> 0 | K31: =SUMIF(其他!B9:B65,FA!C31,其他!K9:K65) -> 0 | L31: =SUMIF(其他!B9:B65,FA!C31,其他!M9:M65) -> 0 | M31: =SUMIF(其他!B9:B65,FA!C31,其他!O9:O65) -> 0 | N31: =SUMIF(其他!B9:B65,FA!C31,其他!Q9:Q65) -> 0
A32: 23 | B32: 1120 | C32: 1021 | D32: 1.2 | E32: 3 | F32: Consultation design of structure reinforcement 结构加固设计费 | G32: =SUM(H32:N32) -> 0 | H32: =SUMIF(其他!B9:B65,FA!C32,其他!E9:E65) -> 0 | I32: =SUMIF(其他!B9:B65,FA!C32,其他!G9:G65) -> 0 | J32: =SUMIF(其他!B9:B65,FA!C32,其他!I9:I65) -> 0 | K32: =SUMIF(其他!B9:B65,FA!C32,其他!K9:K65) -> 0 | L32: =SUMIF(其他!B9:B65,FA!C32,其他!M9:M65) -> 0 | M32: =SUMIF(其他!B9:B65,FA!C32,其他!O9:O65) -> 0 | N32: =SUMIF(其他!B9:B65,FA!C32,其他!Q9:Q65) -> 0
A33: 24 | B33: 1130 | C33: 1022 | D33: 1.3 | E33: 3 | F33: Submission Fees (图纸审批费) | G33: =SUM(H33:N33) -> 0 | H33: =SUMIF(其他!B9:B65,FA!C33,其他!E9:E65) -> 0 | I33: =SUMIF(其他!B9:B65,FA!C33,其他!G9:G65) -> 0 | J33: =SUMIF(其他!B9:B65,FA!C33,其他!I9:I65) -> 0 | K33: =SUMIF(其他!B9:B65,FA!C33,其他!K9:K65) -> 0 | L33: =SUMIF(其他!B9:B65,FA!C33,其他!M9:M65) -> 0 | M33: =SUMIF(其他!B9:B65,FA!C33,其他!O9:O65) -> 0 | N33: =SUMIF(其他!B9:B65,FA!C33,其他!Q9:Q65) -> 0
A34: 25 | C34: 1023 | D34: 2 | E34: 2 | F34: Survey /test fees (测量/检测费) | G34: =SUM(G35:G36) -> 0 | H34: =SUM(H35:H36) -> 0 | I34: =SUM(I35:I36) -> 0 | J34: =SUM(J35:J36) -> 0 | K34: =SUM(K35:K36) -> 0 | L34: =SUM(L35:L36) -> 0 | M34: =SUM(M35:M36) -> 0 | N34: =SUM(N35:N36) -> 0
A35: 26 | B35: 1210 | C35: 1024 | D35: 2.1 | E35: 3 | F35: As-builds survey of existing building(埸地勘察费) | G35: =SUM(H35:N35) -> 0 | H35: =SUMIF(其他!B9:B65,FA!C35,其他!E9:E65) -> 0 | I35: =SUMIF(其他!B9:B65,FA!C35,其他!G9:G65) -> 0 | J35: =SUMIF(其他!B9:B65,FA!C35,其他!I9:I65) -> 0 | K35: =SUMIF(其他!B9:B65,FA!C35,其他!K9:K65) -> 0 | L35: =SUMIF(其他!B9:B65,FA!C35,其他!M9:M65) -> 0 | M35: =SUMIF(其他!B9:B65,FA!C35,其他!O9:O65) -> 0 | N35: =SUMIF(其他!B9:B65,FA!C35,其他!Q9:Q65) -> 0
A36: 27 | B36: 1220 | C36: 1025 | D36: 2.2 | E36: 3 | F36: Required test( i.e .water quality)(检测费用)(地质,水质等) | G36: =SUM(H36:N36) -> 0 | H36: =SUMIF('预算书-初步'!A13:A2600,27,'预算书-初步'!P13:P2600)+SUMIF(其他!B9:B65,FA!C36,其他!E9:E65) -> 0 | I36: =SUMIF(其他!B9:B65,FA!C36,其他!G9:G65) -> 0 | J36: =SUMIF(其他!B9:B65,FA!C36,其他!I9:I65) -> 0 | K36: =SUMIF(其他!B9:B65,FA!C36,其他!K9:K65) -> 0 | L36: =SUMIF(其他!B9:C65,C36,其他!M9:M65) -> 0 | M36: =SUMIF('预算书-初步'!A13:A2600,"大甜27",'预算书-初步'!P13:P2600)+SUMIF(其他!B9:B65,FA!C36,其他!O9:O65) -> 0 | N36: =SUMIF(其他!B9:B65,FA!C36,其他!Q9:Q65) -> 0
A37: 28 | C37: 1026 | D37: 3 | E37: 2 | F37: Permits/utility fees(许可证/公用事业费) | G37: =SUM(G38,G43:G47) -> 41284.4 | H37: =SUM(H38,H43:H47) -> 41284.4 | I37: =SUM(I38,I43:I47) -> 0 | J37: =SUM(J38,J43:J47) -> 0 | K37: =SUM(K38,K43:K47) -> 0 | L37: =SUM(L38,L43:L47) -> 0 | M37: =SUM(M38,M43:M47) -> 0 | N37: =SUM(N38,N43:N47) -> 0
A38: 29 | C38: 1027 | D38: 3.1 | E38: 3 | F38: Electrical services 用电费用 | G38: =SUM(G39:G42) -> 0 | H38: =SUM(H39:H42) -> 0 | I38: =SUM(I39:I42) -> 0 | J38: =SUM(J39:J42) -> 0 | K38: =SUM(K39:K42) -> 0 | L38: =SUM(L39:L42) -> 0 | M38: =SUM(M39:M42) -> 0 | N38: =SUM(N39:N42) -> 0
A39: 30 | B39: 1311 | C39: 1028 | D39: 3.1.1 | E39: 4 | F39: Payment to landlord for electrical supply 付给业主的供电工程费 | G39: =SUM(H39:N39) -> 0 | H39: =SUMIF(其他!B9:B65,FA!C39,其他!E9:E65) -> 0 | I39: =SUMIF(其他!B9:B65,FA!C39,其他!G9:G65) -> 0 | J39: =SUMIF(其他!B9:B65,FA!C39,其他!I9:I65) -> 0 | K39: =SUMIF(其他!B9:B65,FA!C39,其他!K9:K65) -> 0 | L39: =SUMIF(其他!B9:B65,FA!C39,其他!M9:M65) -> 0 | M39: =SUMIF(其他!B9:B65,FA!C39,其他!O9:O65) -> 0 | N39: =SUMIF(其他!B9:B65,FA!C39,其他!Q9:Q65) -> 0
A40: 31 | B40: 1312 | C40: 1029 | D40: 3.1.2 | E40: 4 | F40: Construction cost of sub-station/transforming room 配电房工程费 | G40: =SUM(H40:N40) -> 0 | H40: =SUMIF(其他!B9:B65,FA!C40,其他!E9:E65) -> 0 | I40: =SUMIF(其他!B9:B65,FA!C40,其他!G9:G65) -> 0 | J40: =SUMIF(其他!B9:B65,FA!C40,其他!I9:I65) -> 0 | K40: =SUMIF(其他!B9:B65,FA!C40,其他!K9:K65) -> 0 | L40: =SUMIF(其他!B9:B65,FA!C40,其他!M9:M65) -> 0 | M40: =SUMIF(其他!B9:B65,FA!C40,其他!O9:O65) -> 0 | N40: =SUMIF(其他!B9:B65,FA!C40,其他!Q9:Q65) -> 0
A41: 32 | B41: 1313 | C41: 1030 | D41: 3.1.3 | E41: 4 | F41: Fee to increase capacity 电增容费 | G41: =SUM(H41:N41) -> 0 | H41: =SUMIF(其他!B9:B65,FA!C41,其他!E9:E65) -> 0 | I41: =SUMIF(其他!B9:B65,FA!C41,其他!G9:G65) -> 0 | J41: =SUMIF(其他!B9:B65,FA!C41,其他!I9:I65) -> 0 | K41: =SUMIF(其他!B9:B65,FA!C41,其他!K9:K65) -> 0 | L41: =SUMIF(其他!B9:B65,FA!C41,其他!M9:M65) -> 0 | M41: =SUMIF(其他!B9:B65,FA!C41,其他!O9:O65) -> 0 | N41: =SUMIF(其他!B9:B65,FA!C41,其他!Q9:Q65) -> 0
A42: 33 | B42: 1314 | C42: 1031 | D42: 3.1.4 | E42: 4 | F42: Construction cost to bright electricity to store 红线电缆接线费 | G42: =SUM(H42:N42) -> 0 | H42: =SUMIF('预算书-初步'!A13:A2600,33,'预算书-初步'!P13:P2600)+SUMIF(其他!B9:B65,FA!C42,其他!E9:E65) -> 0 | I42: =SUMIF(其他!B9:B65,FA!C42,其他!G9:G65) -> 0 | J42: =SUMIF(其他!B9:B65,FA!C42,其他!I9:I65) -> 0 | K42: =SUMIF(其他!B9:B65,FA!C42,其他!K9:K65) -> 0 | L42: =SUMIF(其他!B9:B65,FA!C42,其他!M9:M65) -> 0 | M42: =SUMIF('预算书-初步'!A13:A2600,"大甜33",'预算书-初步'!P13:P2600)+SUMIF(其他!B9:B65,FA!C42,其他!O9:O65) -> 0 | N42: =SUMIF(其他!B9:B65,FA!C42,其他!Q9:Q65) -> 0
A43: 34 | B43: 1320 | C43: 1032 | D43: 3.2 | E43: 3 | F43: Sewer and water conneciton fees 给水,排水 接驳费 | G43: =SUM(H43:N43) -> 0 | H43: =SUMIF('预算书-初步'!A13:A2600,34,'预算书-初步'!P13:P2600)+SUMIF(其他!B9:B65,FA!C43,其他!E9:E65) -> 0 | I43: =SUMIF(其他!B9:B65,FA!C43,其他!G9:G65) -> 0 | J43: =SUMIF(其他!B9:B65,FA!C43,其他!I9:I65) -> 0 | K43: =SUMIF(其他!B9:B65,FA!C43,其他!K9:K65) -> 0 | L43: =SUMIF(其他!B9:B65,FA!C43,其他!M9:M65) -> 0 | M43: =SUMIF('预算书-初步'!A13:A2600,"大甜34",'预算书-初步'!P13:P2600)+SUMIF(其他!B9:B65,FA!C43,其他!O9:O65) -> 0 | N43: =SUMIF(其他!B9:B65,FA!C43,其他!Q9:Q65) -> 0
A44: 35 | B44: 1330 | C44: 1033 | D44: 3.3 | E44: 3 | F44: Gas services 煤气装置 | G44: =SUM(H44:N44) -> 0 | H44: =SUMIF(其他!B9:B65,FA!C44,其他!E9:E65) -> 0 | I44: =SUMIF(其他!B9:B65,FA!C44,其他!G9:G65) -> 0 | J44: =SUMIF(其他!B9:B65,FA!C44,其他!I9:I65) -> 0 | K44: =SUMIF(其他!B9:B65,FA!C44,其他!K9:K65) -> 0 | L44: =SUMIF(其他!B9:B65,FA!C44,其他!K9:K65) -> 0 | M44: =SUMIF(其他!B9:B65,FA!C44,其他!O9:O65) -> 0 | N44: =SUMIF(其他!B9:B65,FA!C44,其他!Q9:Q65) -> 0
A45: 36 | B45: 1340 | C45: 1034 | D45: 3.4 | E45: 3 | F45: Public heating service 公共暖气装置 | G45: =SUM(H45:N45) -> 0 | H45: =SUMIF(其他!B9:B65,FA!C45,其他!E9:E65) -> 0 | I45: =SUMIF(其他!B9:B65,FA!C45,其他!G9:G65) -> 0 | J45: =SUMIF(其他!B9:B65,FA!C45,其他!I9:I65) -> 0 | K45: =SUMIF(其他!B9:B65,FA!C45,其他!K9:K65) -> 0 | L45: =SUMIF(其他!B9:B65,FA!C45,其他!M9:M65) -> 0 | M45: =SUMIF(其他!B9:B65,FA!C45,其他!O9:O65) -> 0 | N45: =SUMIF(其他!B9:B65,FA!C45,其他!Q9:Q65) -> 0
A46: 37 | B46: 1350 | C46: 1035 | D46: 3.5 | E46: 3 | F46: Telephone services 电话系统 | G46: =SUM(H46:N46) -> 0 | H46: =SUMIF('预算书-初步'!A13:A2600,37,'预算书-初步'!P13:P2600)+SUMIF(其他!B9:B65,FA!C46,其他!E9:E65) -> 0 | I46: =SUMIF(其他!B9:B65,FA!C46,其他!G9:G65) -> 0 | J46: =SUMIF(其他!B9:B65,FA!C46,其他!I9:I65) -> 0 | K46: =SUMIF(其他!B9:B65,FA!C46,其他!K9:K65) -> 0 | L46: =SUMIF(其他!B9:B65,FA!C46,其他!M9:M65) -> 0 | M46: =SUMIF('预算书-初步'!A13:A2600,"大甜37",'预算书-初步'!P13:P2600)+SUMIF(其他!B9:B65,FA!C46,其他!O9:O65) -> 0 | N46: =SUMIF(其他!B9:B65,FA!C46,其他!Q9:Q65) -> 0
A47: 38 | B47: 1360 | C47: 1036 | D47: 3.6 | E47: 3 | F47: Other permits application fee 其他许可证申请费,含招标费/环评费等 | G47: =SUM(H47:N47) -> 41284.4 | H47: =SUMIF('预算书-初步'!A13:A2600,38,'预算书-初步'!P13:P2600)+SUMIF(其他!B9:B65,FA!C47,其他!E9:E65) -> 41284.4 | I47: =SUMIF(其他!B9:B65,FA!C47,其他!G9:G65) -> 0 | J47: =SUMIF(其他!B9:B65,FA!C47,其他!K9:K65) -> 0 | K47: =SUMIF(其他!B9:B65,FA!C47,其他!K9:K65) -> 0 | L47: =SUMIF(其他!B9:B65,FA!C47,其他!M9:M65) -> 0 | M47: =SUMIF('预算书-初步'!A13:A2600,"大甜38",'预算书-初步'!P13:P2600)+SUMIF(其他!B9:B65,FA!C47,其他!O9:O65) -> 0 | N47: =SUMIF(其他!B9:B65,FA!C47,其他!Q9:Q65) -> 0
A48: 39 | C48: 1037 | D48: 4 | E48: 2 | F48: Demolition cost 拆除费用 | G48: =SUM(G49:G51) -> 11678.15 | H48: =SUM(H49:H51) -> 11678.15 | I48: =SUM(I49:I51) -> 0 | J48: =SUM(J49:J51) -> 0 | K48: =SUM(K49:K51) -> 0 | L48: =SUM(L49:L51) -> 0 | M48: =SUM(M49:M51) -> 0 | N48: =SUM(N49:N51) -> 0
A49: 40 | B49: 1410 | C49: 1038 | D49: 4.1 | E49: 3 | F49: Structure demolition 埸地清拆 | G49: =SUM(H49:N49) -> 8732 | H49: =SUMIF('预算书-初步'!A13:A2600,40,'预算书-初步'!P13:P2600)+SUMIF(其他!B9:B65,FA!C49,其他!E9:E65) -> 8732 | I49: =SUMIF(其他!B9:B65,FA!C49,其他!G9:G65) -> 0 | J49: =SUMIF(其他!B9:B65,FA!C49,其他!I9:I65) -> 0 | K49: =SUMIF(其他!B9:B65,FA!C49,其他!K9:K65) -> 0 | L49: =SUMIF(其他!B9:B65,FA!C49,其他!M9:M65) -> 0 | M49: =SUMIF('预算书-初步'!A13:A2600,"大甜40",'预算书-初步'!P13:P2600)+SUMIF(其他!B9:B65,FA!C49,其他!O9:O65) -> 0 | N49: =SUMIF(其他!B9:B65,FA!C49,其他!Q9:Q65) -> 0
A50: 41 | B50: 1420 | C50: 1039 | D50: 4.2 | E50: 3 | F50: Hoarding 围墙板 | G50: =SUM(H50:N50) -> 2946.15 | H50: =SUMIF('预算书-初步'!A13:A2600,41,'预算书-初步'!P13:P2600)+SUMIF(其他!B9:B65,FA!C50,其他!E9:E65) -> 2946.15 | I50: =SUMIF(其他!B9:B65,FA!C50,其他!G9:G65) -> 0 | J50: =SUMIF(其他!B9:B65,FA!C50,其他!I9:I65) -> 0 | K50: =SUMIF(其他!B9:B65,FA!C50,其他!K9:K65) -> 0 | L50: =SUMIF(其他!B9:B65,FA!C50,其他!M9:M65) -> 0 | M50: =SUMIF('预算书-初步'!A13:A2600,"大甜41",'预算书-初步'!P13:P2600)+SUMIF(其他!B9:B65,FA!C50,其他!O9:O65) -> 0 | N50: =SUMIF(其他!B9:B65,FA!C50,其他!Q9:Q65) -> 0
A51: 42 | B51: 1430 | C51: 1040 | D51: 4.3 | E51: 3 | F51: Temporary security 临时安全设置 | G51: =SUM(H51:N51) -> 0 | H51: =SUMIF(其他!B9:B65,FA!C51,其他!E9:E65) -> 0 | I51: =SUMIF(其他!B9:B65,FA!C51,其他!G9:G65) -> 0 | J51: =SUMIF(其他!B9:B65,FA!C51,其他!I9:I65) -> 0 | K51: =SUMIF(其他!B9:B65,FA!C51,其他!K9:K65) -> 0 | L51: =SUMIF(其他!B9:B65,FA!C51,其他!M9:M65) -> 0 | M51: =SUMIF(其他!B9:B65,FA!C51,其他!O9:O65) -> 0 | N51: =SUMIF(其他!B9:B65,FA!C51,其他!Q9:Q65) -> 0
A52: 43 | C52: 1041 | D52: 5 | E52: 2 | F52: Site development cost 埸地发展费 | G52: =SUM(G53:G60) -> 21203.91 | H52: =SUM(H53:H60) -> 21203.91 | I52: =SUM(I53:I60) -> 0 | J52: =SUM(J53:J60) -> 0 | K52: =SUM(K53:K60) -> 0 | L52: =SUM(L53:L60) -> 0 | M52: =SUM(M53:M60) -> 0 | N52: =SUM(N53:N60) -> 0
A53: 44 | B53: 1510 | C53: 1042 | D53: 5.1 | E53: 3 | F53: Site preparation 埸地准备 | G53: =SUM(H53:N53) -> 21203.91 | H53: =SUMIF('预算书-初步'!A13:A2600,44,'预算书-初步'!P13:P2600)+SUMIF(其他!B9:B65,FA!C53,其他!E9:E65) -> 21203.91 | I53: =SUMIF(其他!B9:B65,FA!C53,其他!G9:G65) -> 0 | J53: =SUMIF(其他!B9:B65,FA!C53,其他!I9:I65) -> 0 | K53: =SUMIF(其他!B9:B65,FA!C53,其他!K9:K65) -> 0 | L53: =SUMIF(其他!B9:B65,FA!C53,其他!M9:M65) -> 0 | M53: =SUMIF('预算书-初步'!A13:A2600,"大甜44",'预算书-初步'!P13:P2600)+SUMIF(其他!B9:B65,FA!C53,其他!O9:O65) -> 0 | N53: =SUMIF(其他!B9:B65,FA!C53,其他!Q9:Q65) -> 0
A54: 45 | B54: 1520 | C54: 1043 | D54: 5.2 | E54: 3 | F54: Structure reinforcement 结构加固 | G54: =SUM(H54:N54) -> 0 | H54: =SUMIF('预算书-初步'!A13:A2600,45,'预算书-初步'!P13:P2600)+SUMIF(其他!B9:B65,FA!C54,其他!E9:E65) -> 0 | I54: =SUMIF(其他!B9:B65,FA!C54,其他!G9:G65) -> 0 | J54: =SUMIF(其他!B9:B65,FA!C54,其他!I9:I65) -> 0 | K54: =SUMIF(其他!B9:B65,FA!C54,其他!K9:K65) -> 0 | L54: =SUMIF(其他!B9:B65,FA!C54,其他!M9:M65) -> 0 | M54: =SUMIF('预算书-初步'!A13:A2600,"大甜45",'预算书-初步'!P13:P2600)+SUMIF(其他!B9:B65,FA!C54,其他!O9:O65) -> 0 | N54: =SUMIF(其他!B9:B65,FA!C54,其他!Q9:Q65) -> 0
A55: 46 | B55: 1530 | C55: 1044 | D55: 5.3 | E55: 3 | F55: External building works i.e.sidewalk 物业外工程，如户外地砖，人行道等 | G55: =SUM(H55:N55) -> 0 | H55: =SUMIF('预算书-初步'!A13:A2600,46,'预算书-初步'!P13:P2600)+SUMIF(其他!B9:B65,FA!C55,其他!E9:E65) -> 0 | I55: =SUMIF(其他!B9:B65,FA!C55,其他!G9:G65) -> 0 | J55: =SUMIF(其他!B9:B65,FA!C55,其他!I9:I65) -> 0 | K55: =SUMIF(其他!B9:B65,FA!C55,其他!K9:K65) -> 0 | L55: =SUMIF(其他!B9:B65,FA!C55,其他!M9:M65) -> 0 | M55: =SUMIF('预算书-初步'!A13:A2600,"大甜46",'预算书-初步'!P13:P2600)+SUMIF(其他!B9:B65,FA!C55,其他!O9:O65) -> 0 | N55: =SUMIF(其他!B9:B65,FA!C55,其他!Q9:Q65) -> 0
A56: 47 | B56: 1531 | C56: 1045 | D56: 5.4 | E56: 3 | F56: Curb、Driveway、Path、Parking 道路、停车场的地面和路沿石、垃圾站 | G56: =SUM(H56:N56) -> 0 | H56: =SUMIF('预算书-初步'!A13:A2600,47,'预算书-初步'!P13:P2600)+SUMIF(其他!B9:B65,FA!C56,其他!E9:E65) -> 0 | I56: =SUMIF(其他!B9:B65,FA!C56,其他!G9:G65) -> 0 | J56: =SUMIF(其他!B9:B65,FA!C56,其他!I9:I65) -> 0 | K56: =SUMIF(其他!B9:B65,FA!C56,其他!K9:K65) -> 0 | L56: =SUMIF(其他!B9:B65,FA!C56,其他!M9:M65) -> 0 | M56: =SUMIF('预算书-初步'!A13:A2600,"大甜47",'预算书-初步'!P13:P2600)+SUMIF(其他!B9:B65,FA!C56,其他!O9:O65) -> 0 | N56: =SUMIF(其他!B9:B65,FA!C56,其他!Q9:Q65) -> 0
A57: 48 | B57: 1532 | C57: 1046 | D57: 5.5 | E57: 3 | F57: Lot Lighting 场地照明 | G57: =SUM(H57:N57) -> 0 | H57: =SUMIF('预算书-初步'!A13:A2600,48,'预算书-初步'!P13:P2600)+SUMIF(其他!B9:B65,FA!C57,其他!E9:E65) -> 0 | I57: =SUMIF(其他!B9:B65,FA!C57,其他!G9:G65) -> 0 | J57: =SUMIF(其他!B9:B65,FA!C57,其他!I9:I65) -> 0 | K57: =SUMIF(其他!B9:B65,FA!C57,其他!K9:K65) -> 0 | L57: =SUMIF(其他!B9:B65,FA!C57,其他!M9:M65) -> 0 | M57: =SUMIF('预算书-初步'!A13:A2600,"大甜48",'预算书-初步'!P13:P2600)+SUMIF(其他!B9:B65,FA!C57,其他!O9:O65) -> 0 | N57: =SUMIF(其他!B9:B65,FA!C57,其他!Q9:Q65) -> 0
A58: 49 | B58: 1533 | C58: 1047 | D58: 5.6 | E58: 3 | F58: Drainage System 场地给排水系统 | G58: =SUM(H58:N58) -> 0 | H58: =SUMIF('预算书-初步'!A13:A2600,49,'预算书-初步'!P13:P2600)+SUMIF(其他!B9:B65,FA!C58,其他!E9:E65) -> 0 | I58: =SUMIF(其他!B9:B65,FA!C58,其他!G9:G65) -> 0 | J58: =SUMIF(其他!B9:B65,FA!C58,其他!I9:I65) -> 0 | K58: =SUMIF(其他!B9:B65,FA!C58,其他!K9:K65) -> 0 | L58: =SUMIF(其他!B9:B65,FA!C58,其他!M9:M65) -> 0 | M58: =SUMIF('预算书-初步'!A13:A2600,"大甜49",'预算书-初步'!P13:P2600)+SUMIF(其他!B9:B65,FA!C58,其他!O9:O65) -> 0 | N58: =SUMIF(其他!B9:B65,FA!C58,其他!Q9:Q65) -> 0
A59: 50 | B59: 1534 | C59: 1048 | D59: 5.7 | E59: 3 | F59: Landscape 绿化 | G59: =SUM(H59:N59) -> 0 | H59: =SUMIF('预算书-初步'!A13:A2600,50,'预算书-初步'!P13:P2600)+SUMIF(其他!B9:B65,FA!C59,其他!E9:E65) -> 0 | I59: =SUMIF(其他!B9:B65,FA!C59,其他!G9:G65) -> 0 | J59: =SUMIF(其他!B9:B65,FA!C59,其他!I9:I65) -> 0 | K59: =SUMIF(其他!B9:B65,FA!C59,其他!K9:K65) -> 0 | L59: =SUMIF(其他!B9:B65,FA!C59,其他!M9:M65) -> 0 | M59: =SUMIF('预算书-初步'!A13:A2600,"大甜50",'预算书-初步'!P13:P2600)+SUMIF(其他!B9:B65,FA!C59,其他!O9:O65) -> 0 | N59: =SUMIF(其他!B9:B65,FA!C59,其他!Q9:Q65) -> 0
A60: 51 | B60: 1540 | C60: 1049 | D60: 5.8 | E60: 3 | F60: Staircase Construction / Rebuild 楼梯结构新建/改造 | G60: =SUM(H60:N60) -> 0 | H60: =SUMIF('预算书-初步'!A13:A2600,51,'预算书-初步'!P13:P2600)+SUMIF(其他!B9:B65,FA!C60,其他!E9:E65) -> 0 | I60: =SUMIF(其他!B9:B65,FA!C60,其他!G9:G65) -> 0 | J60: =SUMIF(其他!B9:B65,FA!C60,其他!I9:I65) -> 0 | K60: =SUMIF(其他!B9:B65,FA!C60,其他!K9:K65) -> 0 | L60: =SUMIF(其他!B9:B65,FA!C60,其他!M9:M65) -> 0 | M60: =SUMIF('预算书-初步'!A13:A2600,"大甜51",'预算书-初步'!P13:P2600)+SUMIF(其他!B9:B65,FA!C60,其他!O9:O65) -> 0 | N60: =SUMIF(其他!B9:B65,FA!C60,其他!Q9:Q65) -> 0
A61: 52 | C61: 1050 | D61: 6 | E61: 2 | F61: Building construction cost 物业施工费用 | G61: =SUM(G62,G83,G88:G90) -> 467729.55 | H61: =SUM(H62,H83,H88:H90) -> 451861.68 | I61: =SUM(I62,I83,I88:I90) -> 0 | J61: =SUM(J62,J83,J88:J90) -> 0 | K61: =SUM(K62,K83,K88:K90) -> 9027.2 | L61: =SUM(L62,L83,L88:L90) -> 6840.67 | M61: =SUM(M62,M83,M88:M90) -> 0 | N61: =SUM(N62,N83,N88:N90) -> 0
A62: 53 | C62: 1051 | D62: 6.1 | E62: 3 | F62: General contract work 总承包 | G62: =SUM(G63,G74:G78,G81:G82) -> 466157.35 | H62: =SUM(H63,H74:H78,H81:H82) -> 450289.48 | I62: =SUM(I63,I74:I78,I81:I82) -> 0 | J62: =SUM(J63,J74:J78,J81:J82) -> 0 | K62: =SUM(K63,K74:K78,K81:K82) -> 9027.2 | L62: =SUM(L63,L74:L78,L81:L82) -> 6840.67 | M62: =SUM(M63,M74:M78,M81:M82) -> 0 | N62: =SUM(N63,N74:N78,N81:N82) -> 0
A63: 54 | B63: 1611 & 1800 | C63: 1052 | D63: 6.1.1 | E63: 4 | F63: Interior decoration 内部装修承包 | G63: =SUM(G64:G73) -> 176513.77 | H63: =SUM(H64:H73) -> 167483.83 | I63: =SUM(I64:I73) -> 0 | J63: =SUM(J64:J73) -> 0 | K63: =SUM(K64:K73) -> 4454.49 | L63: =SUM(L64:L73) -> 4575.45 | M63: =SUM(M64:M73) -> 0 | N63: =SUM(N64:N73) -> 0
A64: 55 | C64: 1053 | D64: 0 | E64: 5 | F64: Kitchen Decoration 厨房区装修，含经理室 | G64: =SUM(H64:N64) -> 47306.12 | H64: =SUMIF('预算书-初步'!A13:A2600,55,'预算书-初步'!P13:P2600)+SUMIF(其他!B9:B65,FA!C64,其他!E9:E65) -> 47306.12 | I64: =SUMIF(其他!B9:B65,FA!C64,其他!G9:G65) -> 0 | J64: =SUMIF(其他!B9:B65,FA!C64,其他!I9:I65) -> 0 | K64: =SUMIF(其他!B9:B65,FA!C64,其他!K9:K65) -> 0 | L64: =SUMIF(其他!B9:B65,FA!C64,其他!M9:M65) -> 0 | M64: =SUMIF('预算书-初步'!A13:A2600,"大甜55",'预算书-初步'!P13:P2600)+SUMIF(其他!B9:B65,FA!C64,其他!O9:O65) -> 0 | N64: =SUMIF(其他!B9:B65,FA!C64,其他!Q9:Q65) -> 0
A65: 56 | C65: 1054 | D65: 1 | E65: 5 | F65: Floor finishes (for Customers' area only) 地面-就餐区 | G65: =SUM(H65:N65) -> 22412.42 | H65: =SUMIF('预算书-初步'!A13:A2600,56,'预算书-初步'!P13:P2600)+SUMIF(其他!B9:B65,FA!C65,其他!E9:E65) -> 21078.96 | I65: =SUMIF('预算书-初步'!A13:A2600,8056,'预算书-初步'!P13:P2600)+SUMIF(其他!B9:B65,FA!C65,其他!G9:G65) -> 0 | J65: =SUMIF('预算书-初步'!A13:A2600,7056,'预算书-初步'!P13:P2600)+SUMIF(其他!B9:B65,FA!C65,其他!I9:I65) -> 0 | K65: =SUMIF(其他!B9:B65,FA!C65,其他!K9:K65)+SUMIF('预算书-初步'!A13:A2600,6056,'预算书-初步'!P13:P2600) -> 577.54 | L65: =SUMIF(其他!B9:B65,FA!C65,其他!M9:M65)+SUMIF('预算书-初步'!A13:A2600,9056,'预算书-初步'!P13:P2600) -> 755.92 | M65: =SUMIF('预算书-初步'!A13:A2600,"大甜56",'预算书-初步'!P13:P2600)+SUMIF(其他!B9:B65,FA!C65,其他!O9:O65) -> 0 | N65: =SUMIF(其他!B9:B65,FA!C65,其他!Q9:Q65) -> 0
A66: 57 | C66: 1055 | D66: 2 | E66: 5 | F66: Wall finishes (for Customers' area only) 墙面-就餐区 | G66: =SUM(H66:N66) -> 46323.3 | H66: =SUMIF('预算书-初步'!A13:A2600,57,'预算书-初步'!P13:P2600)+SUMIF(其他!B9:B65,FA!C66,其他!E9:E65) -> 42248.99 | I66: =SUMIF('预算书-初步'!A13:A2600,8057,'预算书-初步'!P13:P2600)+SUMIF(其他!B9:B65,FA!C66,其他!G9:G65) -> 0 | J66: =SUMIF('预算书-初步'!A13:A2600,7057,'预算书-初步'!P13:P2600)+SUMIF(其他!B9:B65,FA!C66,其他!I9:I65) -> 0 | K66: =SUMIF(其他!B9:B65,FA!C66,其他!K9:K65)+SUMIF('预算书-初步'!A13:A2600,6057,'预算书-初步'!P13:P2600) -> 254.78 | L66: =SUMIF('预算书-初步'!A13:A2600,9057,'预算书-初步'!P13:P2600)+SUMIF(其他!B9:B65,FA!C66,其他!M9:M65) -> 3819.53 | M66: =SUMIF('预算书-初步'!A13:A2600,"大甜57",'预算书-初步'!P13:P2600)+SUMIF(其他!B9:B65,FA!C66,其他!O9:O65) -> 0 | N66: =SUMIF(其他!B9:B65,FA!C66,其他!Q9:Q65) -> 0
A67: 58 | C67: 1056 | D67: 3 | E67: 5 | F67: Ceiling finishes (for Customers' area only) 天花-就餐区 | G67: =SUM(H67:N67) -> 19460.54 | H67: =SUMIF('预算书-初步'!A13:A2600,58,'预算书-初步'!P13:P2600)+SUMIF(其他!B9:B65,FA!C67,其他!E9:E65) -> 18578.17 | I67: =SUMIF('预算书-初步'!A13:A2600,8058,'预算书-初步'!P13:P2600)+SUMIF(其他!B9:B65,FA!C67,其他!G9:G65) -> 0 | J67: =SUMIF('预算书-初步'!A13:A2600,7058,'预算书-初步'!P13:P2600)+SUMIF(其他!B9:B65,FA!C67,其他!I9:I65) -> 0 | K67: =SUMIF(其他!B9:B65,FA!C67,其他!K9:K65)+SUMIF('预算书-初步'!A13:A2600,6058,'预算书-初步'!P13:P2600) -> 882.37 | L67: =SUMIF(其他!B9:B65,FA!C67,其他!M9:M65)+SUMIF('预算书-初步'!A13:A2600,9058,'预算书-初步'!P13:P2600) -> 0 | M67: =SUMIF('预算书-初步'!A13:A2600,"大甜58",'预算书-初步'!P13:P2600)+SUMIF(其他!B9:B65,FA!C67,其他!O9:O65) -> 0 | N67: =SUMIF(其他!B9:B65,FA!C67,其他!Q9:Q65) -> 0
A68: 59 | C68: 1057 | D68: 4 | E68: 5 | F68: Façade / Storefront 外立面 | G68: =SUM(H68:N68) -> 11760.55 | H68: =SUMIF('预算书-初步'!A13:A2600,59,'预算书-初步'!P13:P2600)+SUMIF(其他!B9:B65,FA!C68,其他!E9:E65) -> 11760.55 | I68: =SUMIF('预算书-初步'!A13:A2600,8059,'预算书-初步'!P13:P2600)+SUMIF(其他!B9:B65,FA!C68,其他!G9:G65) -> 0 | J68: =SUMIF('预算书-初步'!A13:A2600,7059,'预算书-初步'!P13:P2600)+SUMIF(其他!B9:B65,FA!C68,其他!I9:I65) -> 0 | K68: =SUMIF(其他!B9:B65,FA!C68,其他!K9:K65) -> 0 | L68: =SUMIF(其他!B9:B65,FA!C68,其他!M9:M65) -> 0 | M68: =SUMIF('预算书-初步'!A13:A2600,"大甜59",'预算书-初步'!P13:P2600)+SUMIF(其他!B9:B65,FA!C68,其他!O9:O65) -> 0 | N68: =SUMIF(其他!B9:B65,FA!C68,其他!Q9:Q65) -> 0
A69: 60 | C69: 1058 | D69: 5 | E69: 5 | F69: Counter 柜台 | G69: =SUM(H69:N69) -> 3869.8 | H69: =SUMIF('预算书-初步'!A13:A2600,60,'预算书-初步'!P13:P2600)+SUMIF(其他!B9:B65,FA!C69,其他!E9:E65) -> 1130 | I69: =SUMIF('预算书-初步'!A13:A2600,8060,'预算书-初步'!P13:P2600)+SUMIF(其他!B9:B65,FA!C69,其他!G9:G65) -> 0 | J69: =SUMIF('预算书-初步'!A13:A2600,7060,'预算书-初步'!P13:P2600)+SUMIF(其他!B9:B65,FA!C69,其他!I9:I65) -> 0 | K69: =SUMIF('预算书-初步'!A13:A2600,6060,'预算书-初步'!P13:P2600)+SUMIF(其他!B9:B65,FA!C69,其他!K9:K65) -> 2739.8 | L69: =SUMIF(其他!B9:B65,FA!C69,其他!M9:M65) -> 0 | M69: =SUMIF('预算书-初步'!A13:A2600,"大甜60",'预算书-初步'!P13:P2600)+SUMIF(其他!B9:B65,FA!C69,其他!O9:O65) -> 0 | N69: =SUMIF('预算书-初步'!A13:A2600,"甜吧60",'预算书-初步'!P13:P2600)+SUMIF(其他!B9:B65,FA!C69,其他!Q9:Q65) -> 0
A70: 61 | C70: 1059 | D70: 6 | E70: 5 | F70: Toilet Decoration 厕所装修-不含洁具 | G70: =SUM(H70:N70) -> 1991.08 | H70: =SUMIF('预算书-初步'!A13:A2600,61,'预算书-初步'!P13:P2600)+SUMIF(其他!B9:B65,FA!C70,其他!E9:E65) -> 1991.08 | I70: =SUMIF(其他!B9:B65,FA!C70,其他!G9:G65) -> 0 | J70: =SUMIF(其他!B9:B65,FA!C70,其他!I9:I65) -> 0 | K70: =SUMIF(其他!B9:B65,FA!C70,其他!K9:K65) -> 0 | L70: =SUMIF(其他!B9:B65,FA!C70,其他!M9:M65) -> 0 | M70: =SUMIF('预算书-初步'!A13:A2600,"大甜61",'预算书-初步'!P13:P2600)+SUMIF(其他!B9:B65,FA!C70,其他!O9:O65) -> 0 | N70: =SUMIF(其他!B9:B65,FA!C70,其他!Q9:Q65) -> 0
A71: 62 | C71: 1060 | D71: 7 | E71: 5 | F71: Stairs Decoration 楼梯装修-不含结构 | G71: =SUM(H71:N71) -> 0 | H71: =SUMIF('预算书-初步'!A13:A2600,62,'预算书-初步'!P13:P2600)+SUMIF(其他!B9:B65,FA!C71,其他!E9:E65) -> 0 | I71: =SUMIF(其他!B9:B65,FA!C71,其他!G9:G65) -> 0 | J71: =SUMIF(其他!B9:B65,FA!C71,其他!I9:I65) -> 0 | K71: =SUMIF(其他!B9:B65,FA!C71,其他!K9:K65) -> 0 | L71: =SUMIF(其他!B9:B65,FA!C71,其他!M9:M65) -> 0 | M71: =SUMIF('预算书-初步'!A13:A2600,"大甜62",'预算书-初步'!P13:P2600)+SUMIF(其他!B9:B65,FA!C71,其他!O9:O65) -> 0 | N71: =SUMIF(其他!B9:B65,FA!C71,其他!Q9:Q65) -> 0
A72: 63 | C72: 1061 | D72: 8 | E72: 5 | F72: Crew Room Decoration 员工室装修 | G72: =SUM(H72:N72) -> 5899.43 | H72: =SUMIF('预算书-初步'!A13:A2600,63,'预算书-初步'!P13:P2600)+SUMIF(其他!B9:B65,FA!C72,其他!E9:E65) -> 5899.43 | I72: =SUMIF(其他!B9:B65,FA!C72,其他!G9:G65) -> 0 | J72: =SUMIF(其他!B9:B65,FA!C72,其他!I9:I65) -> 0 | K72: =SUMIF(其他!B9:B65,FA!C72,其他!K9:K65) -> 0 | L72: =SUMIF(其他!B9:B65,FA!C72,其他!M9:M65) -> 0 | M72: =SUMIF('预算书-初步'!A13:A2600,"大甜63",'预算书-初步'!P13:P2600)+SUMIF(其他!B9:B65,FA!C72,其他!O9:O65) -> 0 | N72: =SUMIF(其他!B9:B65,FA!C72,其他!Q9:Q65) -> 0
A73: 64 | C73: 1062 | D73: 9 | E73: 5 | F73: Doors and others 门和门套等零星装饰 | G73: =SUM(H73:N73) -> 17490.53 | H73: =SUMIF('预算书-初步'!A13:A2600,64,'预算书-初步'!P13:P2600)+SUMIF(其他!B9:B65,FA!C73,其他!E9:E65) -> 17490.53 | I73: =SUMIF('预算书-初步'!A13:A2600,8064,'预算书-初步'!P13:P2600)+SUMIF(其他!B9:B65,FA!C73,其他!G9:G65) -> 0 | J73: =SUMIF('预算书-初步'!A13:A2600,7064,'预算书-初步'!P13:P2600)+SUMIF(其他!B9:B65,FA!C73,其他!I9:I65) -> 0 | K73: =SUMIF('预算书-初步'!A13:A2600,6064,'预算书-初步'!P13:P2600)+SUMIF(其他!B9:B65,FA!C73,其他!K9:K65) -> 0 | L73: =SUMIF(其他!B9:B65,FA!C73,其他!M9:M65) -> 0 | M73: =SUMIF('预算书-初步'!A13:A2600,"大甜64",'预算书-初步'!P13:P2600)+SUMIF(其他!B9:B65,FA!C73,其他!O9:O65) -> 0 | N73: =SUMIF('预算书-初步'!A15:A1669,"甜吧64",'预算书-初步'!P15:P1674)+SUMIF(其他!B9:B65,FA!C73,其他!Q9:Q65) -> 0
A74: 65 | B74: 1616 & 1643 | C74: 1063 | D74: 6.1.1.a | E74: 4 | F74: Interior decoration-Wall and wall painting装修材料-墙体, 墙身涂料 | G74: =SUM(H74:N74) -> 32249.61 | H74: =SUMIF('预算书-初步'!A13:A2600,65,'预算书-初步'!P13:P2600)+SUMIF(其他!B9:B65,FA!C74,其他!E9:E65) -> 32249.61 | I74: =SUMIF(其他!B9:B65,FA!C74,其他!G9:G65) -> 0 | J74: =SUMIF(其他!B9:B65,FA!C74,其他!I9:I65) -> 0 | K74: =SUMIF(其他!B9:B65,FA!C74,其他!K9:K65) -> 0 | L74: =SUMIF(其他!B9:B65,FA!C74,其他!M9:M65) -> 0 | M74: =SUMIF('预算书-初步'!A13:A2600,"大甜65",'预算书-初步'!P13:P2600)+SUMIF(其他!B9:B65,FA!C74,其他!O9:O65) -> 0 | N74: =SUMIF(其他!B9:B65,FA!C74,其他!Q9:Q65) -> 0
A75: 66 | B75: 1644 | C75: 1064 | D75: 6.1.1.b | E75: 4 | F75: Interior decoration-Wall Graphic 装修材料-墙画 | G75: =SUM(H75:N75) -> 0 | H75: =SUMIF('预算书-初步'!A13:A2600,66,'预算书-初步'!P13:P2600)+SUMIF(其他!B9:B65,FA!C75,其他!E9:E65) -> 0 | I75: =SUMIF('预算书-初步'!A13:A2600,8066,'预算书-初步'!P13:P2600)+SUMIF(其他!B9:B65,FA!C75,其他!G9:G65) -> 0 | J75: =SUMIF('预算书-初步'!A13:A2600,7066,'预算书-初步'!P13:P2600)+SUMIF(其他!B9:B65,FA!C75,其他!I9:I65) -> 0 | K75: =SUMIF(其他!B9:B65,FA!C75,其他!K9:K65) -> 0 | L75: =SUMIF(其他!B9:B65,FA!C75,其他!M9:M65) -> 0 | M75: =SUMIF('预算书-初步'!A13:A2600,"大甜66",'预算书-初步'!P13:P2600)+SUMIF(其他!B9:B65,FA!C75,其他!O9:O65) -> 0 | N75: =SUMIF(其他!B9:B65,FA!C75,其他!Q9:Q65) -> 0
A76: 67 | B76: 1645 | C76: 1065 | D76: 6.1.1.c | E76: 4 | F76: Interior decoration-sanitary wares 装修材料-卫生间洁具 | G76: =SUM(H76:N76) -> 2120.68 | H76: =SUMIF('预算书-初步'!A13:A2600,67,'预算书-初步'!P13:P2600)+SUMIF(其他!B9:B65,FA!C76,其他!E9:E65) -> 2120.68 | I76: =SUMIF(其他!B9:B65,FA!C76,其他!G9:G65) -> 0 | J76: =SUMIF(其他!B9:B65,FA!C76,其他!I9:I65) -> 0 | K76: =SUMIF(其他!B9:B65,FA!C76,其他!K9:K65) -> 0 | L76: =SUMIF(其他!B9:B65,FA!C76,其他!M9:M65) -> 0 | M76: =SUMIF('预算书-初步'!A13:A2600,"大甜67",'预算书-初步'!P13:P2600)+SUMIF(其他!B9:B65,FA!C76,其他!O9:O65) -> 0 | N76: =SUMIF(其他!B9:B65,FA!C76,其他!Q9:Q65) -> 0
A77: 68 | B77: 1612 | C77: 1066 | D77: 6.1.2 | E77: 4 | F77: Electrical sub-contract 电承包-不包括灯具 | G77: =SUM(H77:N77) -> 114957.94 | H77: =SUMIF('预算书-初步'!A13:A2600,68,'预算书-初步'!P13:P2600)+SUMIF(其他!B9:B65,FA!C77,其他!E9:E65) -> 108120.01 | I77: =SUMIF('预算书-初步'!A13:A2600,8068,'预算书-初步'!P13:P2600)+SUMIF(其他!B9:B65,FA!C77,其他!G9:G65) -> 0 | J77: =SUMIF('预算书-初步'!A13:A2600,7068,'预算书-初步'!P13:P2600)+SUMIF(其他!B9:B65,FA!C77,其他!I9:I65) -> 0 | K77: =SUMIF('预算书-初步'!A13:A2600,6068,'预算书-初步'!P13:P2600)+SUMIF(其他!B9:B65,FA!C77,其他!K9:K65) -> 4572.71 | L77: =SUMIF('预算书-初步'!A13:A2600,9068,'预算书-初步'!P13:P2600)+SUMIF(其他!B9:B65,FA!C77,其他!M9:M65) -> 2265.22 | M77: =SUMIF('预算书-初步'!A13:A2600,"大甜68",'预算书-初步'!P13:P2600)+SUMIF(其他!B9:B65,FA!C77,其他!O9:O65) -> 0 | N77: =SUMIF('预算书-初步'!A19:A1673,"甜吧68",'预算书-初步'!P19:P1678)+SUMIF(其他!B9:B65,FA!C77,其他!Q9:Q65) -> 0
A78: 69 | B78: 1646 | C78: 1067 | D78: 6.1.2.a | E78: 4 | F78: Electrical Light Fixture 电承包-灯具 | G78: =SUM(G79:G80) -> 17831.82 | H78: =SUM(H79:H80) -> 17831.82 | I78: =SUM(I79:I80) -> 0 | J78: =SUM(J79:J80) -> 0 | K78: =SUM(K79:K80) -> 0 | L78: =SUM(L79:L80) -> 0 | M78: =SUM(M79:M80) -> 0 | N78: =SUM(N79:N80) -> 0
A79: 70 | C79: 1068 | D79: 1 | E79: 5 | F79: Dining light fixture only 灯具-顾客就餐区-不包括装饰吊灯具 | G79: =SUM(H79:N79) -> 14410.2 | H79: =SUMIF('预算书-初步'!A13:A2600,70,'预算书-初步'!P13:P2600)+SUMIF(其他!B9:B65,FA!C79,其他!E9:E65) -> 14410.2 | I79: =SUMIF('预算书-初步'!A13:A2600,8070,'预算书-初步'!P13:P2600)+SUMIF(其他!B9:B65,FA!C79,其他!G9:G65) -> 0 | J79: =SUMIF(其他!B9:B65,FA!C79,其他!I9:I65) -> 0 | K79: =SUMIF(其他!B9:B65,FA!C79,其他!K9:K65) -> 0 | L79: =SUMIF(其他!B9:B65,FA!C79,其他!M9:M65) -> 0 | M79: =SUMIF('预算书-初步'!A13:A2600,"大甜70",'预算书-初步'!P13:P2600)+SUMIF(其他!B9:B65,FA!C79,其他!O9:O65) -> 0 | N79: =SUMIF(其他!B9:B65,FA!C79,其他!Q9:Q65) -> 0
A80: 71 | C80: 1069 | D80: 2 | E80: 5 | F80: Other light fixture only 其他灯具-包括厨房区及建筑照明 | G80: =SUM(H80:N80) -> 3421.62 | H80: =SUMIF('预算书-初步'!A13:A2600,71,'预算书-初步'!P13:P2600)+SUMIF(其他!B9:B65,FA!C80,其他!E9:E65) -> 3421.62 | I80: =SUMIF(其他!B9:B65,FA!C80,其他!G9:G65) -> 0 | J80: =SUMIF(其他!B9:B65,FA!C80,其他!I9:I65) -> 0 | K80: =SUMIF(其他!B9:B65,FA!C80,其他!K9:K65) -> 0 | L80: =SUMIF(其他!B9:B65,FA!C80,其他!M9:M65) -> 0 | M80: =SUMIF('预算书-初步'!A13:A2600,"大甜71",'预算书-初步'!P13:P2600)+SUMIF(其他!B9:B65,FA!C80,其他!O9:O65) -> 0 | N80: =SUMIF(其他!B9:B65,FA!C80,其他!Q9:Q65) -> 0
A81: 72 | B81: 1613 | C81: 1070 | D81: 6.1.3 | E81: 4 | F81: Plumbing & sanitation sub-constract 给排水承包 | G81: =SUM(H81:N81) -> 27735.24 | H81: =SUMIF('预算书-初步'!A13:A2600,72,'预算书-初步'!P13:P2600)+SUMIF(其他!B9:B65,FA!C81,其他!E9:E65) -> 27735.24 | I81: =SUMIF('预算书-初步'!A13:A2600,8072,'预算书-初步'!P13:P2600)+SUMIF(其他!B9:B65,FA!C81,其他!G9:G65) -> 0 | J81: =SUMIF(其他!B9:B65,FA!C81,其他!I9:I65) -> 0 | K81: =SUMIF(其他!B9:B65,FA!C81,其他!K9:K65) -> 0 | L81: =SUMIF(其他!B9:B65,FA!C81,其他!M9:M65) -> 0 | M81: =SUMIF('预算书-初步'!A13:A2600,"大甜72",'预算书-初步'!P13:P2600)+SUMIF(其他!B9:B65,FA!C81,其他!O9:O65) -> 0 | N81: =SUMIF(其他!B9:B65,FA!C81,其他!Q9:Q65) -> 0
A82: 73 | B82: 1614 & 1615 | C82: 1071 | D82: 6.1.4 | E82: 4 | F82: HVAC sub-contract 空调机组安装和管道承包，不含空调设备费用 | G82: =SUM(H82:N82) -> 94748.29 | H82: =SUMIF('预算书-初步'!A13:A2600,73,'预算书-初步'!P13:P2600)+SUMIF(其他!B9:B65,FA!C82,其他!E9:E65) -> 94748.29 | I82: =SUMIF('预算书-初步'!A13:A2600,8073,'预算书-初步'!P13:P2600)+SUMIF(其他!B9:B65,FA!C82,其他!G9:G65) -> 0 | J82: =SUMIF(其他!B9:B65,FA!C82,其他!I9:I65) -> 0 | K82: =SUMIF(其他!B9:B65,FA!C82,其他!K9:K65) -> 0 | L82: =SUMIF(其他!B9:B65,FA!C82,其他!M9:M65) -> 0 | M82: =SUMIF('预算书-初步'!A13:A2600,"大甜73",'预算书-初步'!P13:P2600)+SUMIF(其他!B9:B65,FA!C82,其他!O9:O65) -> 0 | N82: =SUMIF(其他!B9:B65,FA!C82,其他!Q9:Q65) -> 0
A83: 74 | C83: 1072 | D83: 6.2 | E83: 3 | F83: Fire protection service 消防工程 | G83: =SUM(G84:G87) -> 0 | H83: =SUM(H84:H87) -> 0 | I83: =SUM(I84:I87) -> 0 | J83: =SUM(J84:J87) -> 0 | K83: =SUM(K84:K87) -> 0 | L83: =SUM(L84:L87) -> 0 | M83: =SUM(M84:M87) -> 0 | N83: =SUM(N84:N87) -> 0
A84: 75 | B84: 1621 | C84: 1073 | D84: 6.2.1 | E84: 4 | F84: Fire service Design and engineering 消防设计 | G84: =SUM(H84:N84) -> 0 | H84: =SUMIF('预算书-初步'!A13:A2600,75,'预算书-初步'!P13:P2600)+SUMIF(其他!B9:B65,FA!C84,其他!E9:E65) -> 0 | I84: =SUMIF(其他!B9:B65,FA!C84,其他!G9:G65) -> 0 | J84: =SUMIF(其他!B9:B65,FA!C84,其他!I9:I65) -> 0 | K84: =SUMIF(其他!B9:B65,FA!C84,其他!K9:K65) -> 0 | L84: =SUMIF(其他!B9:B65,FA!C84,其他!M9:M65) -> 0 | M84: =SUMIF('预算书-初步'!A13:A2600,"大甜75",'预算书-初步'!P13:P2600)+SUMIF(其他!B9:B65,FA!C84,其他!O9:O65) -> 0 | N84: =SUMIF(其他!B9:B65,FA!C84,其他!Q9:Q65) -> 0
A85: 76 | B85: 1622 | C85: 1074 | D85: 6.2.2 | E85: 4 | F85: Sprinkler/hydrant system 喷淋/消防栓系统 | G85: =SUM(H85:N85) -> 0 | H85: =SUMIF('预算书-初步'!A13:A2600,76,'预算书-初步'!P13:P2600)+SUMIF(其他!B9:B65,FA!C85,其他!E9:E65) -> 0 | I85: =SUMIF(其他!B9:B65,FA!C85,其他!G9:G65) -> 0 | J85: =SUMIF(其他!B9:B65,FA!C85,其他!I9:I65) -> 0 | K85: =SUMIF(其他!B9:B65,FA!C85,其他!K9:K65) -> 0 | L85: =SUMIF(其他!B9:B65,FA!C85,其他!M9:M65) -> 0 | M85: =SUMIF('预算书-初步'!A13:A2600,"大甜76",'预算书-初步'!P13:P2600)+SUMIF(其他!B9:B65,FA!C85,其他!O9:O65) -> 0 | N85: =SUMIF(其他!B9:B65,FA!C85,其他!Q9:Q65) -> 0
A86: 77 | B86: 1623 | C86: 1075 | D86: 6.2.3 | E86: 4 | F86: Smoke/heat detector system 烟感/温感系统，强排烟系统 | G86: =SUM(H86:N86) -> 0 | H86: =SUMIF('预算书-初步'!A13:A2600,77,'预算书-初步'!P13:P2600)+SUMIF(其他!B9:B65,FA!C86,其他!E9:E65) -> 0 | I86: =SUMIF(其他!B9:B65,FA!C86,其他!G9:G65) -> 0 | J86: =SUMIF(其他!B9:B65,FA!C86,其他!I9:I65) -> 0 | K86: =SUMIF(其他!B9:B65,FA!C86,其他!K9:K65) -> 0 | L86: =SUMIF(其他!B9:B65,FA!C86,其他!M9:M65) -> 0 | M86: =SUMIF(其他!B9:B65,FA!C86,其他!O9:O65)+SUMIF('预算书-初步'!A13:A2600,"大甜77",'预算书-初步'!P13:P2600) -> 0 | N86: =SUMIF(其他!B9:B65,FA!C86,其他!Q9:Q65) -> 0
A87: 78 | B87: 1624 | C87: 1076 | D87: 6.2.4 | E87: 4 | F87: Manual Fire Extinguisher 手动灭火设备 | G87: =SUM(H87:N87) -> 0 | H87: =SUMIF(其他!B9:B65,FA!C87,其他!E9:E65) -> 0 | I87: =SUMIF(其他!B9:B65,FA!C87,其他!G9:G65) -> 0 | J87: =SUMIF(其他!B9:B65,FA!C87,其他!I9:I65) -> 0 | K87: =SUMIF(其他!B9:B65,FA!C87,其他!K9:K65) -> 0 | L87: =SUMIF(其他!B9:B65,FA!C87,其他!M9:M65) -> 0 | M87: =SUMIF(其他!B9:B65,FA!C87,其他!O9:O65) -> 0 | N87: =SUMIF(其他!B9:B65,FA!C87,其他!Q9:Q65) -> 0
A88: 79 | B88: 1630 | C88: 1077 | D88: 6.3 | E88: 3 | F88: Environment protection 环保工程：包括化粪池、隔油池、油烟净化器等 | G88: =SUM(H88:N88) -> 1572.2 | H88: =SUMIF('预算书-初步'!A13:A2600,79,'预算书-初步'!P13:P2600)+SUMIF(其他!B9:B65,FA!C88,其他!E9:E65) -> 1572.2 | I88: =SUMIF(其他!B9:B65,FA!C88,其他!G9:G65) -> 0 | J88: =SUMIF(其他!B9:B65,FA!C88,其他!I9:I65) -> 0 | K88: =SUMIF(其他!B9:B65,FA!C88,其他!K9:K65) -> 0 | L88: =SUMIF(其他!B9:B65,FA!C88,其他!M9:M65) -> 0 | M88: =SUMIF('预算书-初步'!A13:A2600,"大甜79",'预算书-初步'!P13:P2600)+SUMIF(其他!B9:B65,FA!C88,其他!O9:O65) -> 0 | N88: =SUMIF(其他!B9:B65,FA!C88,其他!Q9:Q65) -> 0
A89: 80 | B89: 1632 & 1650 | C89: 1078 | D89: 6.5 | E89: 3 | F89: Quantity survey fee & Insurance 工程量测算, 工程保险 | G89: =SUM(H89:N89) -> 0 | H89: =SUMIF(其他!B9:B65,FA!C89,其他!E9:E65) -> 0 | I89: =SUMIF(其他!B9:B65,FA!C89,其他!G9:G65) -> 0 | J89: =SUMIF(其他!B9:B65,FA!C89,其他!I9:I65) -> 0 | K89: =SUMIF(其他!B9:B65,FA!C89,其他!K9:K65) -> 0 | L89: =SUMIF(其他!B9:B65,FA!C89,其他!M9:M65) -> 0 | M89: =SUMIF(其他!B9:B65,FA!C89,其他!O9:O65) -> 0 | N89: =SUMIF(其他!B9:B65,FA!C89,其他!Q9:Q65) -> 0
A90: 81 | B90: 7011 | C90: 1079 | D90: 6.6 | E90: 3 | F90: Capitalized Interest Cost 利息资本化-餐厅建筑装修 | G90: =SUM(H90:N90) -> 0
A91: 82 | C91: 1080 | D91: C | E91: 1 | F91: KITCHEN EQUIPMENT,SIGNAGE SEATING,DECOR(E.S.S.D.)(厨房设备,招牌,座位,装饰) | G91: =SUM(G92,G97,G162,G167,G178) -> 61656.91 | H91: =SUM(H92,H97,H162,H167,H178) -> 61206.46 | I91: =SUM(I92,I97,I162,I167,I178) -> 0 | J91: =SUM(J92,J97,J162,J167,J178) -> 0 | K91: =SUM(K92,K97,K162,K167,K178) -> 450.45 | L91: =SUM(L92,L97,L162,L167,L178) -> 0 | M91: =SUM(M92,M97,M162,M167,M178) -> 0 | N91: =SUM(N92,N97,N162,N167,N178) -> 0
A92: 83 | C92: 1081 | D92: 7 | E92: 2 | F92: Signage (招牌)(Cons.) | G92: =SUM(G93:G96) -> 4724.71 | H92: =SUM(H93:H96) -> 4274.26 | I92: =SUM(I93:I96) -> 0 | J92: =SUM(J93:J96) -> 0 | K92: =SUM(K93:K96) -> 450.45 | L92: =SUM(L93:L96) -> 0 | M92: =SUM(M93:M96) -> 0 | N92: =SUM(N93:N96) -> 0
A93: 84 | B93: 3711-3714 | C93: 1082 | D93: 7.1 | E93: 3 | F93: Signage 招牌：外立面店招，侧招，方向指示牌，标牌等 | G93: =SUM(H93:N93) -> 0 | H93: =SUMIF(其他!B9:B65,FA!C93,其他!E9:E65) -> 0 | I93: =SUMIF(其他!B9:B65,FA!C93,其他!G9:G65) -> 0 | J93: =SUMIF(其他!B9:B65,FA!C93,其他!I9:I65) -> 0 | K93: =SUMIF(其他!B9:B65,FA!C93,其他!K9:K65) -> 0 | L93: =SUMIF(其他!B9:B65,FA!C93,其他!M9:M65) -> 0 | M93: =SUMIF(其他!B9:B65,FA!C93,其他!O9:O65) -> 0 | N93: =SUMIF(其他!B9:B65,FA!C93,其他!Q9:Q65) -> 0
A94: 85 | B94: 3718 | C94: 1083 | D94: 7.2 | E94: 3 | F94: Signage-others 其他：DT场地及车道招牌，特殊招牌等 | G94: =SUM(H94:N94) -> 0 | H94: =SUMIF(其他!B9:B65,FA!C94,其他!E9:E65) -> 0 | I94: =SUMIF(其他!B9:B65,FA!C94,其他!G9:G65) -> 0 | J94: =SUMIF(其他!B9:B65,FA!C94,其他!I9:I65) -> 0 | K94: =SUMIF(其他!B9:B65,FA!C94,其他!K9:K65) -> 0 | L94: =SUMIF(其他!B9:B65,FA!C94,其他!M9:M65) -> 0 | M94: =SUMIF(其他!B9:B65,FA!C94,其他!O9:O65) -> 0 | N94: =SUMIF(其他!B9:B65,FA!C94,其他!Q9:Q65) -> 0
A95: 86 | B95: 3791 | C95: 1084 | D95: 7.3 | E95: 3 | F95: Signage installtion 招牌安装，含杆标基础，立杆等 | G95: =SUM(H95:N95) -> 4724.71 | H95: =SUMIF('预算书-初步'!A13:A2600,86,'预算书-初步'!P13:P2600)+SUMIF(其他!B9:B65,FA!C95,其他!E9:E65) -> 4274.26 | I95: =SUMIF('预算书-初步'!A13:A2600,8086,'预算书-初步'!P13:P2600)+SUMIF(其他!B9:B65,FA!C95,其他!G9:G65) -> 0 | J95: =SUMIF('预算书-初步'!A13:A2600,7086,'预算书-初步'!P13:P2600)+SUMIF(其他!B9:B65,FA!C95,其他!I9:I65) -> 0 | K95: =SUMIF('预算书-初步'!A13:A2600,6086,'预算书-初步'!P13:P2600)+SUMIF(其他!B9:B65,FA!C95,其他!K9:K65) -> 450.45 | L95: =SUMIF(其他!B9:B65,FA!C95,其他!M9:M65) -> 0 | M95: =SUMIF('预算书-初步'!A13:A2600,"大甜86",'预算书-初步'!P13:P2600)+SUMIF(其他!B9:B65,FA!C95,其他!O9:O65) -> 0 | N95: =SUMIF('预算书-初步'!A38:A1691,"甜吧86",'预算书-初步'!P38:P1696)+SUMIF(其他!B9:B65,FA!C95,其他!Q9:Q65) -> 0
A96: 87 | B96: 3792-3794 | C96: 1085 | D96: 7.4 | E96: 3 | F96: Freight ,delivery customs, storage etc 运输，传送，报关，贮藏等 | G96: =SUM(H96:N96) -> 0 | H96: =SUMIF(其他!B9:B65,FA!C96,其他!E9:E65) -> 0 | I96: =SUMIF(其他!B9:B65,FA!C96,其他!G9:G65) -> 0 | J96: =SUMIF(其他!B9:B65,FA!C96,其他!I9:I65) -> 0 | K96: =SUMIF(其他!B9:B65,FA!C96,其他!K9:K65) -> 0 | L96: =SUMIF(其他!B9:B65,FA!C96,其他!M9:M65) -> 0 | M96: =SUMIF(其他!B9:B65,FA!C96,其他!O9:O65) -> 0 | N96: =SUMIF(其他!B9:B65,FA!C96,其他!Q9:Q65) -> 0
A97: 88 | C97: 1086 | D97: 8 | E97: 2 | F97: Equipment (设备)(EQ most) | G97: =SUM(G98,G108,G115,G139,G152,G160:G161) -> 52905.72 | H97: =SUM(H98,H108,H115,H139,H152,H160:H161) -> 52905.72 | I97: =SUM(I98,I108,I115,I139,I152,I160:I161) -> 0 | J97: =SUM(J98,J108,J115,J139,J152,J160:J161) -> 0 | K97: =SUM(K98,K108,K115,K139,K152,K160:K161) -> 0 | L97: =SUM(L98,L108,L115,L139,L152,L160:L161) -> 0 | M97: =SUM(M98,M108,M115,M139,M152,M160:M161) -> 0 | N97: =SUM(N98,N108,N115,N139,N152,N160:N161) -> 0
A98: 89 | C98: 1087 | D98: 8.1 | E98: 3 | F98: Fabricated Equipment 不锈钢设备制作 | G98: =SUM(G99:G107) -> 0 | H98: =SUM(H99:H107) -> 0 | I98: =SUM(I99:I107) -> 0 | J98: =SUM(J99:J107) -> 0 | K98: =SUM(K99:K107) -> 0 | L98: =SUM(L99:L107) -> 0 | M98: =SUM(M99:M107) -> 0 | N98: =SUM(N99:N107) -> 0
A99: 90 | B99: 8110 | C99: 1088 | D99: 8.1.1 | E99: 4 | F99: Customer service Counter Area 收银柜台 | G99: =SUM(H99:N99) -> 0 | H99: =SUMIF(其他!B9:B65,FA!C99,其他!E9:E65) -> 0 | I99: =SUMIF(其他!B9:B65,FA!C99,其他!G9:G65) -> 0 | J99: =SUMIF(其他!B9:B65,FA!C99,其他!I9:I65) -> 0 | K99: =SUMIF(其他!B9:B65,FA!C99,其他!K9:K65) -> 0 | L99: =SUMIF(其他!B9:B65,FA!C99,其他!M9:M65) -> 0 | M99: =SUMIF(其他!B9:B65,FA!C99,其他!O9:O65) -> 0 | N99: =SUMIF(其他!B9:B65,FA!C99,其他!Q9:Q65) -> 0
A100: 91 | B100: 8120 | C100: 1089 | D100: 8.1.2 | E100: 4 | F100: Central Island Area 中央岛 | G100: =SUM(H100:N100) -> 0 | H100: =SUMIF(其他!B9:B65,FA!C100,其他!E9:E65) -> 0 | I100: =SUMIF(其他!B9:B65,FA!C100,其他!G9:G65) -> 0 | J100: =SUMIF(其他!B9:B65,FA!C100,其他!I9:I65) -> 0 | K100: =SUMIF(其他!B9:B65,FA!C100,其他!K9:K65) -> 0 | L100: =SUMIF(其他!B9:B65,FA!C100,其他!M9:M65) -> 0 | M100: =SUMIF(其他!B9:B65,FA!C100,其他!O9:O65) -> 0 | N100: =SUMIF(其他!B9:B65,FA!C100,其他!Q9:Q65) -> 0
A101: 92 | B101: 8130 | C101: 1090 | D101: 8.1.3 | E101: 4 | F101: Grill Station Area 煎区 | G101: =SUM(H101:N101) -> 0 | H101: =SUMIF(其他!B9:B65,FA!C101,其他!E9:E65) -> 0 | I101: =SUMIF(其他!B9:B65,FA!C101,其他!G9:G65) -> 0 | J101: =SUMIF(其他!B9:B65,FA!C101,其他!I9:I65) -> 0 | K101: =SUMIF(其他!B9:B65,FA!C101,其他!K9:K65) -> 0 | L101: =SUMIF(其他!B9:B65,FA!C101,其他!M9:M65) -> 0 | M101: =SUMIF(其他!B9:B65,FA!C101,其他!O9:O65) -> 0 | N101: =SUMIF(其他!B9:B65,FA!C101,其他!Q9:Q65) -> 0
...

Sheet 资产分摊表
IT2: R
B3: Payment Type: Vendor Master | C3: Ecoin | D3: 6 | E3: Excel to MSIS AP with FA | H3: 100 | K3: =SUM(K5:K68) -> 0 | L3: =K3-P3 -> 0 | P3: =SUM(O18:O1245) -> 0 | Q3: =TotFAInvAmt-TotFAInputAmt -> -603552.92 | U3: =SUBTOTAL(9,U5:U1245) -> 603552.92
B4: MSIS-G Voucher # | C4: 麦当劳公司 | D4: 供应商编号 | E4: Vendor Name | F4: 发票号(20 Digits) | G4: FaPiao Flag (Y or N) | H4: Description (30 Digits) | I4: 发票日期（mmddyy） | J4: Due Date ( mmddyy) | K4: 发票金额 | L4: Quantity | M4: Unit | N4: Unit Price | O4: Total Gross Amount | P4: Inventory Description (26 Digits) | Q4: Asset Code | R4: 含税金额 | S4: 餐厅编号 | T4: Dept | U4: 不含税金额 | V4: 项目 | W4: Account | X4: Open Item | Y4: 工作单内容（设备名称） | Z4: Ref1 | AA4: Ref2 | AB4: 设备数量 | AC4: Book 1 Life | AD4: Asset# | AE4: PCC Desc | AF4: Desc 2 | AG4: New/Used Indicator | AH4: Book 2 Account | AI4: Book 2 Amount | AJ4: Book 2 Life | AK4: 麦当劳联系人 | AL4: Appr. Code | AM4: User Name | AN4: Pre-approve | AO4: Image Link | AP4: Image Send | AQ4: Barcode | AR4: 增值税专用发票税率（%） | AT4: 05 | BC4: sub-Category | BD4: PMTCode | BE4: 餐厅类型
Q5: 6002 | R5: =ROUND(U5*(1+AR5),0) -> 0 | S5: 0 | U5: =FA!H$16 -> 0 | Y5: 房产建筑DT | AB5: 1 | AR5: ='预算书-初步'!$F$10 -> 0.09 | AT5: 12 | BC5: 1000 | BD5: 1005 | BE5: 01
Q6: 6002 | R6: =ROUND(U6*(1+AR6),0) -> 0 | S6: =$S$5 -> 0 | U6: =FA!H$17 -> 0 | Y6: 主体建筑DT | AB6: 1 | AN6: =IF(AK6<>0,"N","") | AP6: =IF(F6<>0,"Y","") | AR6: ='预算书-初步'!$F$10 -> 0.09 | AT6: 20 | BC6: 1000 | BD6: 1006 | BE6: 01
Q7: 6002 | R7: =ROUND(U7*(1+AR7),0) -> 0 | S7: =$S$5 -> 0 | U7: =FA!H$18 -> 0 | Y7: 外立面DT | AB7: 1 | AN7: =IF(AK7<>0,"N","") | AP7: =IF(F7<>0,"Y","") | AR7: ='预算书-初步'!$F$10 -> 0.09 | AT7: 23 | BC7: 1000 | BD7: 1007 | BE7: 01
Q8: 1220 | R8: =ROUND(U8*(1+AR8),0) -> 0 | S8: =$S$5 -> 0 | U8: =FA!H$36 -> 0 | Y8: 检测费 | AB8: 1 | AR8: ='预算书-初步'!$F$10 -> 0.09 | BC8: 1000 | BD8: 1025 | BE8: 01
Q9: 1314 | R9: =ROUND(U9*(1+AR9),0) -> 0 | S9: =$S$5 -> 0 | U9: =FA!H$42 -> 0 | Y9: 电缆工程 | AB9: 1 | AR9: ='预算书-初步'!$F$10 -> 0.09 | BC9: 1000 | BD9: 1031 | BE9: 01
Q10: 1320 | R10: =ROUND(U10*(1+AR10),0) -> 0 | S10: =$S$5 -> 0 | U10: =FA!H$43 -> 0 | Y10: 供排水接驳费 | AB10: 1 | AR10: ='预算书-初步'!$F$10 -> 0.09 | BC10: 1000 | BD10: 1032 | BE10: 01
Q11: 1350 | R11: =ROUND(U11*(1+AR11),0) -> 0 | S11: =$S$5 -> 0 | U11: =FA!H$46 -> 0 | Y11: 电话系统 | AB11: 1 | AR11: ='预算书-初步'!$F$10 -> 0.09 | BC11: 1000 | BD11: 1035 | BE11: 01
Q12: 1360 | R12: =ROUND(U12*(1+AR12),0) -> 45000 | S12: =$S$5 -> 0 | U12: =FA!H$47 -> 41284.4 | Y12: 许可证申请费 | AB12: 1 | AR12: ='预算书-初步'!$F$10 -> 0.09 | BC12: 1000 | BD12: 1036 | BE12: 01
Q13: 1410 | R13: =ROUND(U13*(1+AR13),0) -> 9518 | S13: =$S$5 -> 0 | U13: =FA!H$49 -> 8732 | Y13: 埸地清拆 | AB13: 1 | AR13: ='预算书-初步'!$F$10 -> 0.09 | BC13: 1000 | BD13: 1038 | BE13: 01
Q14: 1420 | R14: =ROUND(U14*(1+AR14),0) -> 3211 | S14: =$S$5 -> 0 | U14: =FA!H$50 -> 2946.15 | Y14: 围墙板 | AB14: 1 | AR14: ='预算书-初步'!$F$10 -> 0.09 | BC14: 1000 | BD14: 1039 | BE14: 01
Q15: 1510 | R15: =ROUND(U15*(1+AR15),0) -> 23112 | S15: =$S$5 -> 0 | U15: =FA!H$53 -> 21203.91 | Y15: 埸地准备 | AB15: 1 | AN15: =IF(AK15<>0,"N","") | AP15: =IF(F15<>0,"Y","") | AR15: ='预算书-初步'!$F$10 -> 0.09 | BC15: 1000 | BD15: 1042 | BE15: 01
Q16: 1520 | R16: =ROUND(U16*(1+AR16),0) -> 0 | S16: =$S$5 -> 0 | U16: =FA!H$54 -> 0 | Y16: 结构加固 | AB16: 1 | AN16: =IF(AK16<>0,"N","") | AP16: =IF(F16<>0,"Y","") | AR16: ='预算书-初步'!$F$10 -> 0.09 | BC16: 1000 | BD16: 1043 | BE16: 01
Q17: 1530 | R17: =ROUND(U17*(1+AR17),0) -> 0 | S17: =$S$5 -> 0 | U17: =FA!H$55 -> 0 | Y17: 物业外工程 | AB17: 1 | AN17: =IF(AK17<>0,"N","") | AP17: =IF(F17<>0,"Y","") | AR17: ='预算书-初步'!$F$10 -> 0.09 | BC17: 1000 | BD17: 1044 | BE17: 01
Q18: 1531 | R18: =ROUND(U18*(1+AR18),0) -> 0 | S18: =$S$5 -> 0 | U18: =FA!H$56 -> 0 | Y18: 车道/停车场 | AB18: 1 | AN18: =IF(AK18<>0,"N","") | AP18: =IF(F18<>0,"Y","") | AR18: ='预算书-初步'!$F$10 -> 0.09 | BC18: 1000 | BD18: 1045 | BE18: 01
Q19: 1532 | R19: =ROUND(U19*(1+AR19),0) -> 0 | S19: =$S$5 -> 0 | U19: =FA!H$57 -> 0 | Y19: 场地照明 | AB19: 1 | AN19: =IF(AK19<>0,"N","") | AP19: =IF(F19<>0,"Y","") | AR19: ='预算书-初步'!$F$10 -> 0.09 | BC19: 1000 | BD19: 1046 | BE19: 01
Q20: 1533 | R20: =ROUND(U20*(1+AR20),0) -> 0 | S20: =$S$5 -> 0 | U20: =FA!H$58 -> 0 | Y20: 排水系统 | AB20: 1 | AN20: =IF(AK20<>0,"N","") | AP20: =IF(F20<>0,"Y","") | AR20: ='预算书-初步'!$F$10 -> 0.09 | BC20: 1000 | BD20: 1047 | BE20: 01
Q21: 1534 | R21: =ROUND(U21*(1+AR21),0) -> 0 | S21: =$S$5 -> 0 | U21: =FA!H$59 -> 0 | Y21: 绿化 | AB21: 1 | AN21: =IF(AK21<>0,"N","") | AP21: =IF(F21<>0,"Y","") | AR21: ='预算书-初步'!$F$10 -> 0.09 | BC21: 1000 | BD21: 1048 | BE21: 01
Q22: 1540 | R22: =ROUND(U22*(1+AR22),0) -> 0 | S22: =$S$5 -> 0 | U22: =FA!H$60 -> 0 | Y22: 楼梯工程 | AB22: 1 | AN22: =IF(AK22<>0,"N","") | AP22: =IF(F22<>0,"Y","") | AR22: ='预算书-初步'!$F$10 -> 0.09 | BC22: 1000 | BD22: 1049 | BE22: 01
Q23: 1611 | R23: =ROUND(U23*(1+AR23),0) -> 51564 | S23: =$S$5 -> 0 | U23: =FA!H$64 -> 47306.12 | Y23: 厨房区装修 | AB23: 1 | AN23: =IF(AK23<>0,"N","") | AP23: =IF(F23<>0,"Y","") | AR23: ='预算书-初步'!$F$10 -> 0.09 | BC23: 1000 | BD23: 1053 | BE23: 01
Q24: 1611 | R24: =ROUND(U24*(1+AR24),0) -> 22976 | S24: =$S$5 -> 0 | U24: =FA!H$65 -> 21078.96 | Y24: 地面装修 | AB24: 1 | AN24: =IF(AK24<>0,"N","") | AP24: =IF(F24<>0,"Y","") | AR24: ='预算书-初步'!$F$10 -> 0.09 | BC24: 1000 | BD24: 1054 | BE24: 01
Q25: 1611 | R25: =ROUND(U25*(1+AR25),0) -> 46051 | S25: =$S$5 -> 0 | U25: =FA!H$66 -> 42248.99 | Y25: 墙面装修 | AB25: 1 | AN25: =IF(AK25<>0,"N","") | AP25: =IF(F25<>0,"Y","") | AR25: ='预算书-初步'!$F$10 -> 0.09 | BC25: 1000 | BD25: 1055 | BE25: 01
Q26: 1611 | R26: =ROUND(U26*(1+AR26),0) -> 20250 | S26: =$S$5 -> 0 | U26: =FA!H$67 -> 18578.17 | Y26: 天花装修 | AB26: 1 | AN26: =IF(AK26<>0,"N","") | AP26: =IF(F26<>0,"Y","") | AR26: ='预算书-初步'!$F$10 -> 0.09 | BC26: 1000 | BD26: 1056 | BE26: 01
Q27: 1611 | R27: =ROUND(U27*(1+AR27),0) -> 12819 | S27: =$S$5 -> 0 | U27: =FA!H$68 -> 11760.55 | Y27: 外立面 | AB27: 1 | AN27: =IF(AK27<>0,"N","") | AP27: =IF(F27<>0,"Y","") | AR27: ='预算书-初步'!$F$10 -> 0.09 | BC27: 1000 | BD27: 1057 | BE27: 01
Q28: 1611 | R28: =ROUND(U28*(1+AR28),0) -> 1232 | S28: =$S$5 -> 0 | U28: =FA!H$69 -> 1130 | Y28: 柜台 | AB28: 1 | AR28: ='预算书-初步'!$F$10 -> 0.09 | BC28: 1000 | BD28: 1058 | BE28: 01
Q29: 1611 | R29: =ROUND(U29*(1+AR29),0) -> 2170 | S29: =$S$5 -> 0 | U29: =FA!H$70 -> 1991.08 | Y29: 厕所装修 | AB29: 1 | AR29: ='预算书-初步'!$F$10 -> 0.09 | BC29: 1000 | BD29: 1059 | BE29: 01
Q30: 1611 | R30: =ROUND(U30*(1+AR30),0) -> 0 | S30: =$S$5 -> 0 | U30: =FA!H$71 -> 0 | Y30: 楼梯装修 | AB30: 1 | AR30: ='预算书-初步'!$F$10 -> 0.09 | BC30: 1000 | BD30: 1060 | BE30: 01
Q31: 1611 | R31: =ROUND(U31*(1+AR31),0) -> 6430 | S31: =$S$5 -> 0 | U31: =FA!H$72 -> 5899.43 | Y31: 员工室装修 | AB31: 1 | AN31: =IF(AK31<>0,"N","") | AP31: =IF(F31<>0,"Y","") | AR31: ='预算书-初步'!$F$10 -> 0.09 | BC31: 1000 | BD31: 1061 | BE31: 01
Q32: 1611 | R32: =ROUND(U32*(1+AR32),0) -> 19065 | S32: =$S$5 -> 0 | U32: =FA!H$73 -> 17490.53 | Y32: 门等零星装饰 | AB32: 1 | AR32: ='预算书-初步'!$F$10 -> 0.09 | BC32: 1000 | BD32: 1062 | BE32: 01
Q33: 1643 | R33: =ROUND(U33*(1+AR33),0) -> 35152 | S33: =$S$5 -> 0 | U33: =FA!H$74 -> 32249.61 | Y33: 装修材料-墙体 | AB33: 1 | AN33: =IF(AK33<>0,"N","") | AP33: =IF(F33<>0,"Y","") | AR33: ='预算书-初步'!$F$10 -> 0.09 | BC33: 1000 | BD33: 1063 | BE33: 01
Q34: 1644 | R34: =ROUND(U34*(1+AR34),0) -> 0 | S34: =$S$5 -> 0 | U34: =FA!H$75 -> 0 | Y34: 装修材料-墙画 | AB34: 1 | AN34: =IF(AK34<>0,"N","") | AP34: =IF(F34<>0,"Y","") | AR34: ='预算书-初步'!$F$10 -> 0.09 | BC34: 1000 | BD34: 1064 | BE34: 01
Q35: 1645 | R35: =ROUND(U35*(1+AR35),0) -> 2312 | S35: =$S$5 -> 0 | U35: =FA!H$76 -> 2120.68 | Y35: 装修-卫生洁具 | AB35: 1 | AN35: =IF(AK35<>0,"N","") | AP35: =IF(F35<>0,"Y","") | AR35: ='预算书-初步'!$F$10 -> 0.09 | BC35: 1000 | BD35: 1065 | BE35: 01
Q36: 1612 | R36: =ROUND(U36*(1+AR36),0) -> 117851 | S36: =$S$5 -> 0 | U36: =FA!H$77 -> 108120.01 | Y36: 电承包-不包括灯具 | AB36: 1 | AN36: =IF(AK36<>0,"N","") | AP36: =IF(F36<>0,"Y","") | AR36: ='预算书-初步'!$F$10 -> 0.09 | BC36: 1000 | BD36: 1066 | BE36: 01
Q37: 1646 | R37: =ROUND(U37*(1+AR37),0) -> 15707 | S37: =$S$5 -> 0 | U37: =FA!H$79 -> 14410.2 | Y37: 圆吊灯+规格编号 | AB37: 1 | AN37: =IF(AK37<>0,"N","") | AP37: =IF(F37<>0,"Y","") | AR37: ='预算书-初步'!$F$10 -> 0.09 | BC37: 1000 | BD37: 1068 | BE37: 01
Q38: 1646 | R38: =ROUND(U38*(1+AR38),0) -> 3730 | S38: =$S$5 -> 0 | U38: =FA!H$80 -> 3421.62 | Y38: 其他灯具-包括厨房区及建筑照明 | AB38: 1 | AN38: =IF(AK38<>0,"N","") | AP38: =IF(F38<>0,"Y","") | AR38: ='预算书-初步'!$F$10 -> 0.09 | BC38: 1000 | BD38: 1069 | BE38: 01
Q39: 1613 | R39: =ROUND(U39*(1+AR39),0) -> 30231 | S39: =$S$5 -> 0 | U39: =FA!H$81 -> 27735.24 | Y39: 排水工程 | AB39: 1 | AN39: =IF(AK39<>0,"N","") | AP39: =IF(F39<>0,"Y","") | AR39: ='预算书-初步'!$F$10 -> 0.09 | BC39: 1000 | BD39: 1070 | BE39: 01
Q40: 1614 | R40: =ROUND(U40*(1+AR40),0) -> 103276 | S40: =$S$5 -> 0 | U40: =FA!H$82 -> 94748.29 | Y40: 空调管道工程 | AB40: 1 | AN40: =IF(AK40<>0,"N","") | AP40: =IF(F40<>0,"Y","") | AR40: ='预算书-初步'!$F$10 -> 0.09 | BC40: 1000 | BD40: 1071 | BE40: 01
Q41: 1621 | R41: =ROUND(U41*(1+AR41),0) -> 0 | S41: =$S$5 -> 0 | U41: =FA!H$84 -> 0 | Y41: 消防设计 | AB41: 1 | AN41: =IF(AK41<>0,"N","") | AP41: =IF(F41<>0,"Y","") | AR41: ='预算书-初步'!$F$10 -> 0.09 | BC41: 1000 | BD41: 1073 | BE41: 01
Q42: 1622 | R42: =ROUND(U42*(1+AR42),0) -> 0 | S42: =$S$5 -> 0 | U42: =FA!H$85 -> 0 | Y42: 喷淋消防栓系统 | AB42: 1 | AN42: =IF(AK42<>0,"N","") | AP42: =IF(F42<>0,"Y","") | AR42: ='预算书-初步'!$F$10 -> 0.09 | BC42: 1000 | BD42: 1074 | BE42: 01
Q43: 1623 | R43: =ROUND(U43*(1+AR43),0) -> 0 | S43: =$S$5 -> 0 | U43: =FA!H$86 -> 0 | Y43: 消防报警系统 | AB43: 1 | AR43: ='预算书-初步'!$F$10 -> 0.09 | BC43: 1000 | BD43: 1075 | BE43: 01
Q44: 1630 | R44: =ROUND(U44*(1+AR44),0) -> 1714 | S44: =$S$5 -> 0 | U44: =FA!H$88 -> 1572.2 | Y44: 环保工程：包括化粪池、隔油池、油烟净化器等 | AB44: 1 | AN44: =IF(AK44<>0,"N","") | AP44: =IF(F44<>0,"Y","") | AR44: ='预算书-初步'!$F$10 -> 0.09 | BC44: 1000 | BD44: 1077 | BE44: 01
Q45: 3791 | R45: =ROUND(U45*(1+AR45),0) -> 4659 | S45: =$S$5 -> 0 | U45: =FA!H$95 -> 4274.26 | Y45: 招牌安装，含杆标基础，立杆等 | AB45: 1 | AN45: =IF(AK45<>0,"N","") | AP45: =IF(F45<>0,"Y","") | AR45: ='预算书-初步'!$F$10 -> 0.09 | BC45: 1000 | BD45: 1084 | BE45: 01
Q46: 8410 | R46: =ROUND(U46*(1+AR46),0) -> 2917 | S46: =$S$5 -> 0 | U46: =FA!H$140 -> 2676.15 | Y46: 保险箱 | AB46: =SUMIFS(其他!F:F,其他!A:A,资产分摊表!Q46,其他!B:B,资产分摊表!BD46)+SUMIFS('预算书-初步'!K13:K1530,'预算书-初步'!A13:A1530,131) -> 1 | AN46: =IF(AK46<>0,"N","") | AP46: =IF(F46<>0,"Y","") | AR46: ='预算书-初步'!$F$10 -> 0.09 | BC46: 1000 | BD46: 1129 | BE46: 01
Q47: 8421 | R47: =ROUND(U47*(1+AR47),0) -> 0 | S47: =$S$5 -> 0 | U47: =SUMIF(其他!$A$9:$A$65,资产分摊表!Q47,其他!$E$9:$E$66) -> 0 | Y47: 电视/录像机／相机／影碟机 | AB47: =SUMIFS(其他!F:F,其他!A:A,资产分摊表!Q47,其他!B:B,资产分摊表!BD47)+SUMIFS('预算书-初步'!K13:K1530,'预算书-初步'!A13:A1530,132,'预算书-初步'!D13:D1530,8421) -> 0 | AR47: ='预算书-初步'!$F$10 -> 0.09 | BC47: 1000 | BD47: 1130 | BE47: 01
Q48: 8422 | R48: =ROUND(U48*(1+AR48),0) -> 9750 | S48: =$S$5 -> 0 | U48: =+SUMIFS('预算书-初步'!P14:P2600,'预算书-初步'!A14:A2600,132,'预算书-初步'!C14:C2600,8422)+SUMIF(其他!$A$9:$A$65,资产分摊表!Q48,其他!$E$9:$E$66) -> 8944.69 | Y48: 音响 | AB48: =SUMIFS(其他!F:F,其他!A:A,资产分摊表!Q48,其他!B:B,资产分摊表!BD48)+SUMIFS('预算书-初步'!K13:K1530,'预算书-初步'!A13:A1530,132,'预算书-初步'!D13:D1530,8422) -> 0 | AR48: ='预算书-初步'!$F$10 -> 0.09 | BC48: 1000 | BD48: 1130 | BE48: 01
Q49: 8423 | R49: =ROUND(U49*(1+AR49),0) -> 0 | S49: =$S$5 -> 0 | U49: =+SUMIFS('预算书-初步'!P14:P2600,'预算书-初步'!A14:A2600,132,'预算书-初步'!C14:C2600,8423)+SUMIF(其他!$A$9:$A$65,资产分摊表!Q49,其他!$E$9:$E$66) -> 0 | Y49: 电话/传真机 | AB49: =SUMIFS(其他!F:F,其他!A:A,资产分摊表!Q49,其他!B:B,资产分摊表!BD49)+SUMIFS('预算书-初步'!K13:K1530,'预算书-初步'!A13:A1530,132,'预算书-初步'!D13:D1530,8423) -> 0 | AR49: ='预算书-初步'!$F$10 -> 0.09 | BC49: 1000 | BD49: 1130 | BE49: 01
Q50: 8424 | R50: =ROUND(U50*(1+AR50),0) -> 9820 | S50: =$S$5 -> 0 | U50: =FA!H$142 -> 9009.01 | Y50: 安保监控系统 | AB50: 1 | AN50: =IF(AK50<>0,"N","") | AP50: =IF(F50<>0,"Y","") | AR50: ='预算书-初步'!$F$10 -> 0.09 | BC50: 1000 | BD50: 1131 | BE50: 01
Q51: 8426 | R51: =ROUND(U51*(1+AR51),0) -> 0 | S51: =$S$5 -> 0 | U51: =FA!H$143 -> 0 | Y51: 配电柜 | AB51: =SUMIFS(其他!F:F,其他!A:A,资产分摊表!Q51,其他!B:B,资产分摊表!BD51)+SUMIFS('预算书-初步'!K13:K1530,'预算书-初步'!A13:A1530,134,'预算书-初步'!D13:D1530,8426) -> 0 | AN51: =IF(AK51<>0,"N","") | AP51: =IF(F51<>0,"Y","") | AR51: ='预算书-初步'!$F$10 -> 0.09 | BC51: 1000 | BD51: 1132 | BE51: 01
Q52: 8451 | R52: =ROUND(U52*(1+AR52),0) -> 0 | S52: =$S$5 -> 0 | U52: =SUMIF(其他!$A$9:$A$65,$Q52,其他!$E$9:$E$65)+SUMIFS('预算书-初步'!P14:P2600,'预算书-初步'!A14:A2600,138,'预算书-初步'!C14:C2600,8451) -> 0 | Y52: 其他厨房工具-电熨斗 | AB52: 1 | AR52: ='预算书-初步'!$F$10 -> 0.09 | BC52: 1000 | BD52: 1136 | BE52: 01
Q53: 8452 | R53: =ROUND(U53*(1+AR53),0) -> 0 | S53: =$S$5 -> 0 | U53: =SUMIF(其他!$A$9:$A$65,$Q53,其他!$E$9:$E$65) -> 0 | Y53: 其他厨房工具 | AB53: 1 | AR53: ='预算书-初步'!$F$10 -> 0.09 | BC53: 1000 | BD53: 1136 | BE53: 01
Q54: 8453 | R54: =ROUND(U54*(1+AR54),0) -> 0 | S54: =$S$5 -> 0 | U54: =SUMIF(其他!$A$9:$A$65,$Q54,其他!$E$9:$E$65) -> 0 | Y54: 吸管箱 | AB54: 1 | AR54: ='预算书-初步'!$F$10 -> 0.09 | BC54: 1000 | BD54: 1136 | BE54: 01
Q55: 8455 | R55: =ROUND(U55*(1+AR55),0) -> 0 | S55: =$S$5 -> 0 | U55: =SUMIF(其他!$A$9:$A$65,$Q55,其他!$E$9:$E$65) -> 0 | Y55: 垃圾桶 | AB55: 1 | AR55: ='预算书-初步'!$F$10 -> 0.09 | BC55: 1000 | BD55: 1136 | BE55: 01
Q56: 8454 | R56: =ROUND(U56*(1+AR56),0) -> 1236 | S56: =$S$5 -> 0 | U56: =+SUMIFS('预算书-初步'!P14:P2600,'预算书-初步'!A14:A2600,138,'预算书-初步'!C14:C2600,8454)+SUMIF(其他!$A$9:$A$65,$Q56,其他!$E$9:$E$65) -> 1133.63 | Y56: 烘手机 | AB56: =SUMIFS(其他!F:F,其他!A:A,资产分摊表!Q56,其他!B:B,资产分摊表!BD56)+SUMIFS('预算书-初步'!K13:K1530,'预算书-初步'!A13:A1530,132,'预算书-初步'!D13:D1530,8454) -> 0 | AN56: =IF(AK56<>0,"N","") | AP56: =IF(F56<>0,"Y","") | AR56: ='预算书-初步'!$F$10 -> 0.09 | BC56: 1000 | BD56: 1136 | BE56: 01
Q57: 8456 | R57: =ROUND(U57*(1+AR57),0) -> 1717 | S57: =$S$5 -> 0 | U57: =+SUMIFS('预算书-初步'!P14:P2600,'预算书-初步'!A14:A2600,138,'预算书-初步'!C14:C2600,8456)+SUMIF(其他!$A$9:$A$65,$Q57,其他!$E$9:$E$65) -> 1575 | Y57: 灭蝇灯 | AB57: =SUMIFS(其他!F:F,其他!A:A,资产分摊表!Q57,其他!B:B,资产分摊表!BD57)+SUMIFS('预算书-初步'!K13:K1530,'预算书-初步'!A13:A1530,132,'预算书-初步'!D13:D1530,8456) -> 0 | AN57: =IF(AK57<>0,"N","") | AP57: =IF(F57<>0,"Y","") | AR57: ='预算书-初步'!$F$10 -> 0.09 | BC57: 1000 | BD57: 1136 | BE57: 01
Q58: 8425 | R58: =ROUND(U58*(1+AR58),0) -> 438 | S58: =$S$5 -> 0 | U58: =FA!H$151 -> 402 | Y58: 微波炉 | AB58: =SUMIFS(其他!F:F,其他!A:A,资产分摊表!Q58,其他!B:B,资产分摊表!BD58)+SUMIFS('预算书-初步'!K13:K1530,'预算书-初步'!A13:A1530,142,'预算书-初步'!D13:D1530,8425) -> 0 | AN58: =IF(AK58<>0,"N","") | AP58: =IF(F58<>0,"Y","") | AR58: ='预算书-初步'!$F$10 -> 0.09 | BC58: 1000 | BD58: 1140 | BE58: 01
Q59: 8491 | R59: =ROUND(U59*(1+AR59),0) -> 15253 | S59: =$S$5 -> 0 | U59: =FA!H$153 -> 13993.68 | Y59: 空调设备和控制系统 | AB59: 1 | AN59: =IF(AK59<>0,"N","") | AP59: =IF(F59<>0,"Y","") | AR59: ='预算书-初步'!$F$10 -> 0.09 | BC59: 1000 | BD59: 1150 | BE59: 01
Q60: 8492 | R60: =ROUND(U60*(1+AR60),0) -> 7512 | S60: =$S$5 -> 0 | U60: =FA!H$154 -> 6891.91 | Y60: 热水器 | AB60: =SUMIFS(其他!F:F,其他!A:A,资产分摊表!Q60,其他!B:B,资产分摊表!BD60)+SUMIFS('预算书-初步'!K13:K1530,'预算书-初步'!A13:A1530,145,'预算书-初步'!D13:D1530,8492) -> 0 | AN60: =IF(AK60<>0,"N","") | AP60: =IF(F60<>0,"Y","") | AR60: ='预算书-初步'!$F$10 -> 0.09 | BC60: 1000 | BD60: 1151 | BE60: 01
Q61: 8485 | R61: =ROUND(U61*(1+AR61),0) -> 8042 | S61: =$S$5 -> 0 | U61: =FA!H$157 -> 7377.65 | Y61: 铝门 | AB61: =SUMIFS(其他!F:F,其他!A:A,资产分摊表!Q61,其他!B:B,资产分摊表!BD61)+SUMIFS('预算书-初步'!K13:K1530,'预算书-初步'!A13:A1530,148,'预算书-初步'!D13:D1530,8485) -> 0 | AN61: =IF(AK61<>0,"N","") | AP61: =IF(F61<>0,"Y","") | AR61: ='预算书-初步'!$F$10 -> 0.09 | BC61: 1000 | BD61: 1154 | BE61: 01
Q62: 8496 | R62: =ROUND(U62*(1+AR62),0) -> 0 | S62: =$S$5 -> 0 | U62: =FA!H$158 -> 0 | Y62: 厨房抽油烟机 | AB62: =SUMIFS(其他!F:F,其他!A:A,资产分摊表!Q62,其他!B:B,资产分摊表!BD62)+SUMIFS('预算书-初步'!K13:K1530,'预算书-初步'!A13:A1530,149,'预算书-初步'!D13:D1530,8496) -> 0 | AN62: =IF(AK62<>0,"N","") | AP62: =IF(F62<>0,"Y","") | AR62: ='预算书-初步'!$F$10 -> 0.09 | BC62: 1000 | BD62: 1155 | BE62: 01
Q63: 8497 | R63: =ROUND(U63*(1+AR63),0) -> 0 | S63: =$S$5 -> 0 | U63: =FA!H$159 -> 0 | Y63: 其他五金件 | AB63: 1 | AN63: =IF(AK63<>0,"N","") | AP63: =IF(F63<>0,"Y","") | AR63: ='预算书-初步'!$F$10 -> 0.09 | BC63: 1000 | BD63: 1156 | BE63: 01
Q64: 8900 | R64: =ROUND(U64*(1+AR64),0) -> 23 | S64: =$S$5 -> 0 | U64: =FA!H$161 -> 21 | Y64: 其他设备 | AB64: 1 | AN64: =IF(AK64<>0,"N","") | AP64: =IF(F64<>0,"Y","") | AR64: ='预算书-初步'!$F$10 -> 0.09 | BC64: 1000 | BD64: 1158 | BE64: 01
Q65: 2991 | R65: =ROUND(U65*(1+AR65),0) -> 4071 | S65: =$S$5 -> 0 | U65: =FA!H$165 -> 3735 | Y65: 座位安装 | AB65: 1 | AN65: =IF(AK65<>0,"N","") | AP65: =IF(F65<>0,"Y","") | AR65: ='预算书-初步'!$F$10 -> 0.09 | BC65: 1000 | BD65: 1162 | BE65: 01
Q66: 4007 | R66: =ROUND(U66*(1+AR66),0) -> 0 | S66: =$S$5 -> 0 | U66: =FA!H$174 -> 0 | Y66: 主题装饰（家具供应商提供的屏风、吊灯等装饰品） | AB66: 1 | AN66: =IF(AK66<>0,"N","") | AP66: =IF(F66<>0,"Y","") | AR66: ='预算书-初步'!$F$10 -> 0.09 | BC66: 1000 | BD66: 1171 | BE66: 01
Q67: 4081 | R67: =ROUND(U67*(1+AR67),0) -> 0 | S67: =$S$5 -> 0 | U67: =FA!H$175 -> 0 | Y67: 其他装饰 | AB67: 1 | AN67: =IF(AK67<>0,"N","") | AP67: =IF(F67<>0,"Y","") | AR67: ='预算书-初步'!$F$10 -> 0.09 | BC67: 1000 | BD67: 1172 | BE67: 01
Q68: 4991 | R68: =ROUND(U68*(1+AR68),0) -> 318 | S68: =$S$5 -> 0 | U68: =FA!H$176 -> 291.48 | Y68: 装饰品- 安装 | AB68: 1 | AN68: =IF(AK68<>0,"N","") | AP68: =IF(F68<>0,"Y","") | AR68: ='预算书-初步'!$F$10 -> 0.09 | BC68: 1000 | BD68: 1173 | BE68: 01
Q69: 1110 | R69: =ROUND(U69*(1+AR69),0) -> 0 | S69: =$S$5 -> 0 | U69: =FA!H$30 -> 0 | Y69: 设计、QS | AB69: 1 | AN69: =IF(AK69<>0,"N","") | AP69: =IF(F69<>0,"Y","") | AR69: ='预算书-初步'!$F$10 -> 0.09 | BC69: 1000 | BD69: 1019 | BE69: 01
Q70: 1110 | R70: =ROUND(U70*(1+AR70),0) -> 0 | S70: =$S$5 -> 0 | U70: =FA!H$31 -> 0 | Y70: 设计、QS | AB70: 1 | AR70: ='预算书-初步'!$F$10 -> 0.09 | BC70: 1000 | BD70: 1020 | BE70: 01
Q71: 1120 | R71: =ROUND(U71*(1+AR71),0) -> 0 | S71: =$S$5 -> 0 | U71: =FA!H$32 -> 0 | Y71: 结构加固设计费 | AB71: 1 | AN71: =IF(AK71<>0,"N","") | AP71: =IF(F71<>0,"Y","") | AR71: ='预算书-初步'!$F$10 -> 0.09 | BC71: 1000 | BD71: 1021 | BE71: 01
Q72: 1130 | R72: =ROUND(U72*(1+AR72),0) -> 0 | S72: =$S$5 -> 0 | U72: =FA!H$33 -> 0 | Y72: 报建费 | AB72: 1 | AN72: =IF(AK72<>0,"N","") | AP72: =IF(F72<>0,"Y","") | AR72: ='预算书-初步'!$F$10 -> 0.09 | BC72: 1000 | BD72: 1022 | BE72: 01
Q73: 1210 | R73: =ROUND(U73*(1+AR73),0) -> 0 | S73: =$S$5 -> 0 | U73: =FA!H$35 -> 0 | Y73: 场地勘察费 | AB73: 1 | AN73: =IF(AK73<>0,"N","") | AP73: =IF(F73<>0,"Y","") | AR73: ='预算书-初步'!$F$10 -> 0.09 | BC73: 1000 | BD73: 1024 | BE73: 01
Q74: 1311 | R74: =ROUND(U74*(1+AR74),0) -> 0 | S74: =$S$5 -> 0 | U74: =FA!H$39 -> 0 | Y74: 付业主供电费 | AB74: 1 | AN74: =IF(AK74<>0,"N","") | AP74: =IF(F74<>0,"Y","") | AR74: ='预算书-初步'!$F$10 -> 0.09 | BC74: 1000 | BD74: 1028 | BE74: 01
Q75: 1312 | R75: =ROUND(U75*(1+AR75),0) -> 0 | S75: =$S$5 -> 0 | U75: =FA!H$40 -> 0 | Y75: 配电房工程费 | AB75: 1 | AN75: =IF(AK75<>0,"N","") | AP75: =IF(F75<>0,"Y","") | AR75: ='预算书-初步'!$F$10 -> 0.09 | BC75: 1000 | BD75: 1029 | BE75: 01
Q76: 1313 | R76: =ROUND(U76*(1+AR76),0) -> 0 | S76: =$S$5 -> 0 | U76: =FA!H$41 -> 0 | Y76: 电增容费 | AB76: 1 | AN76: =IF(AK76<>0,"N","") | AP76: =IF(F76<>0,"Y","") | AR76: ='预算书-初步'!$F$10 -> 0.09 | BC76: 1000 | BD76: 1030 | BE76: 01
Q77: 1330 | R77: =ROUND(U77*(1+AR77),0) -> 0 | S77: =$S$5 -> 0 | U77: =FA!H$44 -> 0 | Y77: 煤气装置 | AB77: 1 | AN77: =IF(AK77<>0,"N","") | AP77: =IF(F77<>0,"Y","") | AR77: ='预算书-初步'!$F$10 -> 0.09 | BC77: 1000 | BD77: 1033 | BE77: 01
Q78: 1340 | R78: =ROUND(U78*(1+AR78),0) -> 0 | S78: =$S$5 -> 0 | U78: =FA!H$45 -> 0 | Y78: 公共暖气装置 | AB78: 1 | AN78: =IF(AK78<>0,"N","") | AP78: =IF(F78<>0,"Y","") | AR78: ='预算书-初步'!$F$10 -> 0.09 | BC78: 1000 | BD78: 1034 | BE78: 01
Q79: 1430 | R79: =ROUND(U79*(1+AR79),0) -> 0 | S79: =$S$5 -> 0 | U79: =FA!H$51 -> 0 | Y79: 临时安全设置 | AB79: 1 | AN79: =IF(AK79<>0,"N","") | AP79: =IF(F79<>0,"Y","") | AR79: ='预算书-初步'!$F$10 -> 0.09 | BC79: 1000 | BD79: 1040 | BE79: 01
Q80: 1624 | R80: =ROUND(U80*(1+AR80),0) -> 0 | S80: =$S$5 -> 0 | U80: =FA!H$87 -> 0 | Y80: 手动灭火设备 | AB80: 1 | AN80: =IF(AK80<>0,"N","") | AP80: =IF(F80<>0,"Y","") | AR80: ='预算书-初步'!$F$10 -> 0.09 | BC80: 1000 | BD80: 1076 | BE80: 01
Q81: 2960 | R81: =ROUND(U81*(1+AR81),0) -> 0 | S81: =$S$5 -> 0 | U81: =FA!H$164 -> 0 | Y81: 其他桌椅 | AB81: 1 | AN81: =IF(AK81<>0,"N","") | AP81: =IF(F81<>0,"Y","") | AR81: ='预算书-初步'!$F$10 -> 0.09 | BC81: 1000 | BD81: 1161 | BE81: 01
Q82: 3718 | R82: =ROUND(U82*(1+AR82),0) -> 0 | S82: =$S$5 -> 0 | U82: =FA!H$94 -> 0 | Y82: 其他招牌 | AB82: 1 | AN82: =IF(AK82<>0,"N","") | AP82: =IF(F82<>0,"Y","") | AR82: ='预算书-初步'!$F$10 -> 0.09 | BC82: 1000 | BD82: 1083 | BE82: 01
Q83: 4001 | R83: =ROUND(U83*(1+AR83),0) -> 0 | S83: =$S$5 -> 0 | U83: =FA!H$168 -> 0 | Y83: 麦当劳叔叔像 | AB83: 1 | AN83: =IF(AK83<>0,"N","") | AP83: =IF(F83<>0,"Y","") | AR83: ='预算书-初步'!$F$10 -> 0.09 | BC83: 1000 | BD83: 1165 | BE83: 01
Q84: 4002 | R84: =ROUND(U84*(1+AR84),0) -> 0 | S84: =$S$5 -> 0 | U84: =FA!H$169 -> 0 | Y84: 墙画 | AB84: 1 | AN84: =IF(AK84<>0,"N","") | AP84: =IF(F84<>0,"Y","") | AR84: ='预算书-初步'!$F$10 -> 0.09 | BC84: 1000 | BD84: 1166 | BE84: 01
Q85: 4003 | R85: =ROUND(U85*(1+AR85),0) -> 0 | S85: =$S$5 -> 0 | U85: =FA!H$170 -> 0 | Y85: 人造植物 | AB85: 1 | AN85: =IF(AK85<>0,"N","") | AP85: =IF(F85<>0,"Y","") | AR85: ='预算书-初步'!$F$10 -> 0.09 | BC85: 1000 | BD85: 1167 | BE85: 01
Q86: 4004 | R86: =ROUND(U86*(1+AR86),0) -> 0 | S86: =$S$5 -> 0 | U86: =FA!H$171 -> 0 | Y86: 玻璃贴纸 | AB86: 1 | AN86: =IF(AK86<>0,"N","") | AP86: =IF(F86<>0,"Y","") | AR86: ='预算书-初步'!$F$10 -> 0.09 | BC86: 1000 | BD86: 1168 | BE86: 01
Q87: 4005 | R87: =ROUND(U87*(1+AR87),0) -> 0 | S87: =$S$5 -> 0 | U87: =FA!H$172 -> 0 | Y87: 克罗克像 | AB87: 1 | AN87: =IF(AK87<>0,"N","") | AP87: =IF(F87<>0,"Y","") | AR87: ='预算书-初步'!$F$10 -> 0.09 | BC87: 1000 | BD87: 1169 | BE87: 01
Q88: 4006 | R88: =ROUND(U88*(1+AR88),0) -> 0 | S88: =$S$5 -> 0 | U88: =FA!H$173 -> 0 | Y88: POP箱子 | AB88: 1 | AN88: =IF(AK88<>0,"N","") | AP88: =IF(F88<>0,"Y","") | AR88: ='预算书-初步'!$F$10 -> 0.09 | BC88: 1000 | BD88: 1170 | BE88: 01
Q89: 6003 | R89: =ROUND(U89*(1+AR89),0) -> 0 | S89: =$S$5 -> 0 | U89: =FA!H$19 -> 0 | Y89: 餐厅房产使用权 | AB89: 1 | AN89: =IF(AK89<>0,"N","") | AP89: =IF(F89<>0,"Y","") | AR89: ='预算书-初步'!$F$10 -> 0.09 | BC89: 1000 | BD89: 1008 | BE89: 01
Q90: 6004 | R90: =ROUND(U90*(1+AR90),0) -> 0 | S90: =$S$5 -> 0 | U90: =FA!H$20 -> 0 | Y90: 餐厅启动费 | AB90: 1 | AN90: =IF(AK90<>0,"N","") | AP90: =IF(F90<>0,"Y","") | AR90: ='预算书-初步'!$F$10 -> 0.09 | BC90: 1000 | BD90: 1009 | BE90: 01
Q91: 6005 | R91: =ROUND(U91*(1+AR91),0) -> 0 | S91: =$S$5 -> 0 | U91: =FA!H$21 -> 0 | Y91: 餐厅业主补偿金 | AB91: 1 | AN91: =IF(AK91<>0,"N","") | AP91: =IF(F91<>0,"Y","") | AR91: ='预算书-初步'!$F$10 -> 0.09 | BC91: 1000 | BD91: 1010 | BE91: 01
Q92: 6006 | R92: =ROUND(U92*(1+AR92),0) -> 0 | S92: =$S$5 -> 0 | U92: =FA!H$22 -> 0 | Y92: 餐厅开业前租金 | AB92: 1 | AN92: =IF(AK92<>0,"N","") | AP92: =IF(F92<>0,"Y","") | AR92: ='预算书-初步'!$F$10 -> 0.09 | BC92: 1000 | BD92: 1011 | BE92: 01
Q93: 6007 | R93: =ROUND(U93*(1+AR93),0) -> 0 | S93: =$S$5 -> 0 | U93: =FA!H$23 -> 0 | Y93: 餐厅开业地产费用 | AB93: 1 | AN93: =IF(AK93<>0,"N","") | AP93: =IF(F93<>0,"Y","") | AR93: ='预算书-初步'!$F$10 -> 0.09 | BC93: 1000 | BD93: 1012 | BE93: 01
Q94: 8310 | R94: =ROUND(U94*(1+AR94),0) -> 0 | S94: =$S$5 -> 0 | U94: =FA!H$116 -> 0 | Y94: 菜单牌 | AB94: 1 | AN94: =IF(AK94<>0,"N","") | AP94: =IF(F94<>0,"Y","") | AR94: ='预算书-初步'!$F$10 -> 0.09 | BC94: 1000 | BD94: 1105 | BE94: 01
Q95: 8457 | R95: =ROUND(U95*(1+AR95),0) -> 0 | S95: =$S$5 -> 0 | U95: =FA!H$150 -> 0 | Y95: 分离式厨房升降梯 | AB95: 1 | AN95: =IF(AK95<>0,"N","") | AP95: =IF(F95<>0,"Y","") | AR95: ='预算书-初步'!$F$10 -> 0.09 | BC95: 1000 | BD95: 1139 | BE95: 01
Q96: 8500 | R96: =ROUND(U96*(1+AR96),0) -> 0 | S96: =$S$5 -> 0 | U96: =FA!H$160 -> 0 | Y96: 儿童乐园 | AB96: 1 | AN96: =IF(AK96<>0,"N","") | AP96: =IF(F96<>0,"Y","") | AR96: ='预算书-初步'!$F$10 -> 0.09 | BC96: 1000 | BD96: 1157 | BE96: 01
Q97: 9999 | R97: =ROUND(U97*(1+AR97),0) -> 0 | S97: =$S$5 -> 0 | U97: =FA!H$24 -> 0 | Y97: Location Fee | AB97: 1 | AR97: ='预算书-初步'!$F$10 -> 0.09 | BC97: 1000 | BD97: 1013 | BE97: 01
Q98: 7001 | R98: =ROUND(U98*(1+AR98),0) -> 0 | S98: =$S$5 -> 0 | U98: =FA!H$25 -> 0 | Y98: (G&A) 资本化管理费用 | AB98: 1 | AR98: ='预算书-初步'!$F$10 -> 0.09 | BC98: 1000 | BD98: 1014 | BE98: 01
Q99: 7012 | R99: =ROUND(U99*(1+AR99),0) -> 0 | S99: =$S$5 -> 0 | U99: =FA!H$26 -> 0 | Y99: 利息资本化-餐厅开业前租金 | AB99: 1 | AR99: ='预算书-初步'!$F$10 -> 0.09 | BC99: 1000 | BD99: 1015 | BE99: 01
Q100: 1650 | R100: =ROUND(U100*(1+AR100),0) -> 0 | S100: =$S$5 -> 0 | U100: =FA!H$89 -> 0 | Y100: 工程量测算,工程保险 | AB100: 1 | AR100: ='预算书-初步'!$F$10 -> 0.09 | BC100: 1000 | BD100: 1078 | BE100: 01
Q101: 3711 | R101: =ROUND(U101*(1+AR101),0) -> 0 | S101: =$S$5 -> 0 | U101: =SUMIF(其他!$A$9:$A$65,$Q101,其他!$E$9:$E$65) -> 0 | Y101: 招牌：餐厅招牌 | AB101: 1 | AR101: ='预算书-初步'!$F$10 -> 0.09 | BC101: 1000 | BD101: 1082 | BE101: 01
...

Sheet 预算书-初步
A1: 麦当劳(中国)工程预算书(IN RMB) V20250409 | U1: 要求 | W1: 子目飘红15个 | Y1: 做店速度 3天内； | AB1: 总价绝对值偏差控制在±2%以内； | AE1: ABS偏差4%以内；
E2: 麦咖啡 | F2: 1 | H2: 区域 | J2: 中区 | M2: 麦当劳项目经理 | O2: 高虹 | U2: 总价金额 | V2: 总金额偏差 | W2: 总金额偏差率 | X2: ABS偏差 | Y2: ABS偏差率 | AA2: 初步差异： | AB2: 飘红 | AC2: 漏项 | AD2: 多项
E3: 店内甜品站 | H3: 市场 | J3: 上海 | M3: 餐厅类型 | O3: 新店 | P3: Instore | Q3: Instore | T3: REVIT | U3: =P2540 -> 603552.92 | AB3: 28
E4: 独立甜品站 | H4: 城市 | J4: 上海市 | M4: 招标方式 | O4: 集中招标 | T4: 初稿 | U4: =Q2540 -> 592962.58 | V4: =U3-U4 -> 10590.34 | W4: =V4/U3 -> 0.017546664 | X4: =V2540 -> 22875.06 | Y4: =X4/U3 -> 0.03790067
E5: MDS | F5: 1 | H5: 餐厅名称 | J5: 浦东张江中科路地铁站餐厅 | M5: 中标单价选用 | O5: 上海锦伟
E6: 卫生间 | H6: PP编码 | J6: 234618 | M6: 异地施工上浮系数 | O6: 0 | AA6: 如何通过检查发现？
E7: 楼梯 | H7: 面积 | J7: 185 | U7: 电箱图，弱点常规配置，餐厅常规配置 | AA7: 拿审核表检查错误，补充细节
E8: 分离式厨房 | H8: 座位数 | J8: 40 | M8: 编制人 | U8: 委托书，项目信息，部分市场特性等无需通过建模出具的清单
E9: 儿童乐园 | H9: 层高 | M9: 审核人 | U9: 建模正常可出清单 | Y9: 建模出量率 | Z9: 刨除不建模出量的，建模出量率
E10: 税率 | F10: 0.09 | H10: 设计风格 | J10: Geometry | M10: 编制日期 | U10: 技术原因，暂时无法出清单的 | Y10: =W9/(W7+W8+W9+W10) -> #DIV/0! | Z10: =W9/(W9+W10) -> #DIV/0!
A12: CO | B12: PMT Code | C12: Asset Code | D12: BE类型 | E12: 类别 | F12: 编号1 | G12: 编号2 | H12: 编号3 | I12: SKU编码 | J12: 项目名称 | K12: revit数量 | L12: 初稿数量 | M12: 单位 | N12: 综合单价（不含税） | O12: 综合单价（含税） | P12: revit合价 | Q12: 初稿合价 | R12: 检查 | S12: 备注 | T12: 工程量差异 | U12: 合价差异 | V12: 合价ABS | W12: 差异率 | X12: ABS差异 | Y12: 调平原因 | Z12: 清单来源 | AA12: 错误原因 | AG12: 取参逻辑 | AH12: 工程量来源
A13: 7 | B13: 1005 | C13: 6002 | D13: 01 | E13: 0 地产费用 | F13: 0.2 房产建筑 | G13: DT基础(分包) | H13: DT基础(分包) | I13: 1000040096 | J13: DT基础(分包) | M13: 项 | O13: =ROUND(N13*(1+$F$10),2) -> 0 | P13: =ROUND(K13*N13,2) -> 0 | Q13: =ROUND(L13*N13,2) -> 0 | T13: =K13-L13 -> 0 | U13: =P13-Q13 -> 0 | V13: =ABS(U13) -> 0 | W13: =T13/L13 -> #DIV/0! | X13: =ABS(W13) -> #DIV/0! | AH13: 委托书
A14: 8 | B14: 1006 | C14: 6002 | D14: 01 | E14: 0 地产费用 | F14: 0.2 房产建筑 | G14: DT主体建筑(分包) | H14: DT主体建筑(分包) | I14: 1000040097 | J14: DT主体建筑(分包) | M14: 项 | O14: =ROUND(N14*(1+$F$10),2) -> 0 | P14: =ROUND(K14*N14,2) -> 0 | Q14: =ROUND(L14*N14,2) -> 0 | T14: =K14-L14 -> 0 | U14: =P14-Q14 -> 0 | V14: =ABS(U14) -> 0 | W14: =T14/L14 -> #DIV/0! | X14: =ABS(W14) -> #DIV/0! | AH14: 委托书
A15: 33 | B15: 1031 | C15: 1314 | D15: 01 | E15: 3 许可证/公用事业费 | F15: 3.1 供电费用 | G15: 3.1.4 红线电缆接线费 | H15: 3.1.4 红线电缆接线费 | I15: 1000021726 | J15: 红线电缆YJV 120双拼 或 YJV240单根 含桥架（按桥架长度计算） | M15: 米 | N15: 1000.44 | O15: =ROUND(N15*(1+$F$10),2) -> 1090.48 | P15: =ROUND(K15*N15,2) -> 0 | Q15: =ROUND(L15*N15,2) -> 0 | T15: =K15-L15 -> 0 | U15: =P15-Q15 -> 0 | V15: =ABS(U15) -> 0 | W15: =T15/L15 -> #DIV/0! | X15: =ABS(W15) -> #DIV/0! | AH15: 委托书
A16: 33 | B16: 1031 | C16: 1314 | D16: 01 | E16: 3 许可证/公用事业费 | F16: 3.1 供电费用 | G16: 3.1.4 红线电缆接线费 | H16: 3.1.4 红线电缆接线费 | I16: 1000021725 | J16: 红线电缆 YJV 95 双拼 或 YJV185单根 含桥架（按桥架长度计算） | M16: 米 | N16: 872.84 | O16: =ROUND(N16*(1+$F$10),2) -> 951.4 | P16: =ROUND(K16*N16,2) -> 0 | Q16: =ROUND(L16*N16,2) -> 0 | T16: =K16-L16 -> 0 | U16: =P16-Q16 -> 0 | V16: =ABS(U16) -> 0 | W16: =T16/L16 -> #DIV/0! | X16: =ABS(W16) -> #DIV/0! | AH16: 委托书
A17: 33 | B17: 1031 | C17: 1314 | D17: 01 | E17: 3 许可证/公用事业费 | F17: 3.1 供电费用 | G17: 3.1.4 红线电缆接线费 | H17: 3.1.4 红线电缆接线费 | I17: 1000021727 | J17: 铠装红线电缆YJV 120双拼 或 YJV240单根 含桥架（按桥架长度计算） | M17: 米 | N17: 1000.44 | O17: =ROUND(N17*(1+$F$10),2) -> 1090.48 | P17: =ROUND(K17*N17,2) -> 0 | Q17: =ROUND(L17*N17,2) -> 0 | T17: =K17-L17 -> 0 | U17: =P17-Q17 -> 0 | V17: =ABS(U17) -> 0 | W17: =T17/L17 -> #DIV/0! | X17: =ABS(W17) -> #DIV/0! | AH17: 委托书
A18: 33 | B18: 1031 | C18: 1314 | D18: 01 | E18: 3 许可证/公用事业费 | F18: 3.1 供电费用 | G18: 3.1.4 红线电缆接线费 | H18: 3.1.4 红线电缆接线费 | I18: 1000021728 | J18: 铠装红线电缆 YJV 95 双拼 或 YJV185单根 含桥架（按桥架长度计算） | M18: 米 | N18: 872.84 | O18: =ROUND(N18*(1+$F$10),2) -> 951.4 | P18: =ROUND(K18*N18,2) -> 0 | Q18: =ROUND(L18*N18,2) -> 0 | T18: =K18-L18 -> 0 | U18: =P18-Q18 -> 0 | V18: =ABS(U18) -> 0 | W18: =T18/L18 -> #DIV/0! | X18: =ABS(W18) -> #DIV/0! | AH18: 委托书
A19: 33 | B19: 1031 | C19: 1314 | D19: 01 | E19: 3 许可证/公用事业费 | F19: 3.1 供电费用 | G19: 3.1.4 红线电缆接线费 | H19: 3.1.4 红线电缆接线费 | I19: 1000040026 | J19: 室外电缆沟（含井）开挖及回填 | M19: 米 | N19: 135.14 | O19: =ROUND(N19*(1+$F$10),2) -> 147.3 | P19: =ROUND(K19*N19,2) -> 0 | Q19: =ROUND(L19*N19,2) -> 0 | T19: =K19-L19 -> 0 | U19: =P19-Q19 -> 0 | V19: =ABS(U19) -> 0 | W19: =T19/L19 -> #DIV/0! | X19: =ABS(W19) -> #DIV/0! | AH19: 委托书
A20: 34 | B20: 1032 | C20: 1320 | D20: 01 | E20: 3 许可证/公用事业费 | F20: 3.2 给、排水接驳费 | G20: 给、排水接驳费 | H20: 给、排水接驳费 | I20: 1000021729 | J20: 给水接驳费 | M20: 米 | N20: 96.36 | O20: =ROUND(N20*(1+$F$10),2) -> 105.03 | P20: =ROUND(K20*N20,2) -> 0 | Q20: =ROUND(L20*N20,2) -> 0 | T20: =K20-L20 -> 0 | U20: =P20-Q20 -> 0 | V20: =ABS(U20) -> 0 | W20: =T20/L20 -> #DIV/0! | X20: =ABS(W20) -> #DIV/0! | AH20: 委托书
A21: 34 | B21: 1032 | C21: 1320 | D21: 01 | E21: 3 许可证/公用事业费 | F21: 3.2 给、排水接驳费 | G21: 给、排水接驳费 | H21: 给、排水接驳费 | I21: 1000021730 | J21: 排水接驳费 | M21: 米 | N21: 92.09 | O21: =ROUND(N21*(1+$F$10),2) -> 100.38 | P21: =ROUND(K21*N21,2) -> 0 | Q21: =ROUND(L21*N21,2) -> 0 | T21: =K21-L21 -> 0 | U21: =P21-Q21 -> 0 | V21: =ABS(U21) -> 0 | W21: =T21/L21 -> #DIV/0! | X21: =ABS(W21) -> #DIV/0! | AH21: 委托书
A22: 37 | B22: 1035 | C22: 1350 | D22: 01 | E22: 3 许可证/公用事业费 | F22: 3.5 电话系统 | G22: 电话申请费 | H22: 电话申请费 | I22: 1000040027 | J22: 电话申请费 | M22: 项 | N22: 1801.8 | O22: =ROUND(N22*(1+$F$10),2) -> 1963.96 | P22: =ROUND(K22*N22,2) -> 0 | Q22: =ROUND(L22*N22,2) -> 0 | T22: =K22-L22 -> 0 | U22: =P22-Q22 -> 0 | V22: =ABS(U22) -> 0 | W22: =T22/L22 -> #DIV/0! | X22: =ABS(W22) -> #DIV/0! | AH22: 委托书
A23: 38 | B23: 1036 | C23: 1360 | D23: 01 | E23: 3 许可证/公用事业费 | F23: 3.6 其他许可证申请费 | G23: 其他许可证申请费 | H23: 其他许可证申请费 | I23: 1000040028 | J23: 有线电视申请费 | M23: 项 | N23: 1351.35 | O23: =ROUND(N23*(1+$F$10),2) -> 1472.97 | P23: =ROUND(K23*N23,2) -> 0 | Q23: =ROUND(L23*N23,2) -> 0 | T23: =K23-L23 -> 0 | U23: =P23-Q23 -> 0 | V23: =ABS(U23) -> 0 | W23: =T23/L23 -> #DIV/0! | X23: =ABS(W23) -> #DIV/0! | AH23: 委托书
A24: 38 | B24: 1036 | C24: 1360 | D24: 01 | E24: 3 许可证/公用事业费 | F24: 3.6 其他许可证申请费 | G24: 其他许可证申请费 | H24: 其他许可证申请费 | I24: 1000040098 | J24: 其他许可证申请费（含：1.环评费、2.环保申请费、3.规划申报费、4.城管／市容申报费、5.建委／招标办之甲方报建费、6.卫生防疫站申报费、7.房屋鉴定费、8.市政申请费 | K24: 1 | L24: 1 | M24: 项 | N24: 41284.4 | O24: =ROUND(N24*(1+$F$10),2) -> 45000 | P24: =ROUND(K24*N24,2) -> 41284.4 | Q24: =ROUND(L24*N24,2) -> 41284.4 | T24: =K24-L24 -> 0 | U24: =P24-Q24 -> 0 | V24: =ABS(U24) -> 0 | W24: =T24/L24 -> 0 | X24: =ABS(W24) -> 0 | AH24: 委托书
A25: 40 | B25: 1038 | C25: 1410 | D25: 01 | E25: 4 拆除费 | F25: 4.1 场地清拆 | G25: 场地清拆 | H25: 场地清拆 | I25: 1000021731 | J25: 现场清拆（零星拆除,含非特殊位置清运） | K25: 185 | L25: 185 | M25: m2 | N25: 27.2 | O25: =ROUND(N25*(1+$F$10),2) -> 29.65 | P25: =ROUND(K25*N25,2) -> 5032 | Q25: =ROUND(L25*N25,2) -> 5032 | T25: =K25-L25 -> 0 | U25: =P25-Q25 -> 0 | V25: =ABS(U25) -> 0 | W25: =T25/L25 -> 0 | X25: =ABS(W25) -> 0 | AH25: 委托书
A26: 40 | B26: 1038 | C26: 1410 | D26: 01 | E26: 4 拆除费 | F26: 4.1 场地清拆 | G26: 场地清拆 | H26: 场地清拆 | I26: 1000021732 | J26: 现场清拆（大面积拆除--天地墙全面拆除，含非特殊位置清运） | M26: m2 | N26: 73 | O26: =ROUND(N26*(1+$F$10),2) -> 79.57 | P26: =ROUND(K26*N26,2) -> 0 | Q26: =ROUND(L26*N26,2) -> 0 | T26: =K26-L26 -> 0 | U26: =P26-Q26 -> 0 | V26: =ABS(U26) -> 0 | W26: =T26/L26 -> #DIV/0! | X26: =ABS(W26) -> #DIV/0! | AH26: 委托书
A27: 40 | B27: 1038 | C27: 1410 | D27: 01 | E27: 4 拆除费 | F27: 4.1 场地清拆 | G27: 场地清拆 | H27: 场地清拆 | I27: 1000021733 | J27: 现场清拆（特大面积拆除--天地墙全面拆除、结构拆除，含非特殊位置清运） | M27: m2 | N27: 109 | O27: =ROUND(N27*(1+$F$10),2) -> 118.81 | P27: =ROUND(K27*N27,2) -> 0 | Q27: =ROUND(L27*N27,2) -> 0 | T27: =K27-L27 -> 0 | U27: =P27-Q27 -> 0 | V27: =ABS(U27) -> 0 | W27: =T27/L27 -> #DIV/0! | X27: =ABS(W27) -> #DIV/0! | AH27: 委托书
A28: 40 | B28: 1038 | C28: 1410 | D28: 01 | E28: 4 拆除费 | F28: 4.1 场地清拆 | G28: 场地清拆 | H28: 场地清拆 | I28: 1000021734 | J28: 现场清拆（零星拆除,含特殊位置清运） | M28: m2 | N28: 54.5 | O28: =ROUND(N28*(1+$F$10),2) -> 59.41 | P28: =ROUND(K28*N28,2) -> 0 | Q28: =ROUND(L28*N28,2) -> 0 | T28: =K28-L28 -> 0 | U28: =P28-Q28 -> 0 | V28: =ABS(U28) -> 0 | W28: =T28/L28 -> #DIV/0! | X28: =ABS(W28) -> #DIV/0! | AH28: 委托书
A29: 40 | B29: 1038 | C29: 1410 | D29: 01 | E29: 4 拆除费 | F29: 4.1 场地清拆 | G29: 场地清拆 | H29: 场地清拆 | I29: 1000021735 | J29: 现场清拆（大面积拆除--天地墙全面拆除，含特殊位置清运） | M29: m2 | N29: 181.5 | O29: =ROUND(N29*(1+$F$10),2) -> 197.84 | P29: =ROUND(K29*N29,2) -> 0 | Q29: =ROUND(L29*N29,2) -> 0 | T29: =K29-L29 -> 0 | U29: =P29-Q29 -> 0 | V29: =ABS(U29) -> 0 | W29: =T29/L29 -> #DIV/0! | X29: =ABS(W29) -> #DIV/0! | AH29: 委托书
A30: 40 | B30: 1038 | C30: 1410 | D30: 01 | E30: 4 拆除费 | F30: 4.1 场地清拆 | G30: 场地清拆 | H30: 场地清拆 | I30: 1000021736 | J30: 现场清拆（特大面积拆除--天地墙全面拆除、结构拆除，含特殊位置清运） | M30: m2 | N30: 284.5 | O30: =ROUND(N30*(1+$F$10),2) -> 310.11 | P30: =ROUND(K30*N30,2) -> 0 | Q30: =ROUND(L30*N30,2) -> 0 | T30: =K30-L30 -> 0 | U30: =P30-Q30 -> 0 | V30: =ABS(U30) -> 0 | W30: =T30/L30 -> #DIV/0! | X30: =ABS(W30) -> #DIV/0! | AH30: 委托书
A31: 40 | B31: 1038 | C31: 1410 | D31: 01 | E31: 4 拆除费 | F31: 4.1 场地清拆 | G31: 场地清拆 | H31: 场地清拆 | I31: 1000021737 | J31: 场地清洁 | K31: 185 | L31: 185 | M31: m2 | N31: 20 | O31: =ROUND(N31*(1+$F$10),2) -> 21.8 | P31: =ROUND(K31*N31,2) -> 3700 | Q31: =ROUND(L31*N31,2) -> 3700 | T31: =K31-L31 -> 0 | U31: =P31-Q31 -> 0 | V31: =ABS(U31) -> 0 | W31: =T31/L31 -> 0 | X31: =ABS(W31) -> 0 | AH31: 委托书
A32: 41 | B32: 1039 | C32: 1420 | D32: 01 | E32: 4 拆除费 | F32: 4.2 围墙板 | G32: 围墙板 | H32: 围墙板 | I32: 1000021738 | J32: 场地围墙板等 | K32: 50.19 | L32: 49.9 | M32: m2 | N32: 58.7 | O32: =ROUND(N32*(1+$F$10),2) -> 63.98 | P32: =ROUND(K32*N32,2) -> 2946.15 | Q32: =ROUND(L32*N32,2) -> 2929.13 | T32: =K32-L32 -> 0.29 | U32: =P32-Q32 -> 17.02 | V32: =ABS(U32) -> 17.02 | W32: =T32/L32 -> 0.0058116232 | X32: =ABS(W32) -> 0.0058116232 | AG32: 基本墙面积
A33: 44 | B33: 1042 | C33: 1510 | D33: 01 | E33: 5 场地发展费 | F33: 5.1 场地准备 | G33: 场地准备 | H33: 措施费 | I33: 1000021739 | J33: 措施费（新店） | K33: 1 | L33: 1 | M33: 项 | N33: 15380 | O33: =ROUND(N33*(1+$F$10),2) -> 16764.2 | P33: =ROUND(K33*N33,2) -> 15380 | Q33: =ROUND(L33*N33,2) -> 15380 | T33: =K33-L33 -> 0 | U33: =P33-Q33 -> 0 | V33: =ABS(U33) -> 0 | W33: =T33/L33 -> 0 | X33: =ABS(W33) -> 0 | AH33: 委托书
A34: 44 | B34: 1042 | C34: 1510 | D34: 01 | E34: 5 场地发展费 | F34: 5.1 场地准备 | G34: 场地准备 | H34: 措施费 | I34: 1000022205 | J34: 措施费（改造店） | M34: 项 | N34: 26126.13 | O34: =ROUND(N34*(1+$F$10),2) -> 28477.48 | P34: =ROUND(K34*N34,2) -> 0 | Q34: =ROUND(L34*N34,2) -> 0 | T34: =K34-L34 -> 0 | U34: =P34-Q34 -> 0 | V34: =ABS(U34) -> 0 | W34: =T34/L34 -> #DIV/0! | X34: =ABS(W34) -> #DIV/0! | AH34: 委托书
A35: 44 | B35: 1042 | C35: 1510 | D35: 01 | E35: 5 场地发展费 | F35: 5.1 场地准备 | G35: 场地准备 | H35: 措施费 | I35: 1000040030 | J35: 北区冬季施工费 | M35: 项 | N35: 18018.02 | O35: =ROUND(N35*(1+$F$10),2) -> 19639.64 | P35: =ROUND(K35*N35,2) -> 0 | Q35: =ROUND(L35*N35,2) -> 0 | T35: =K35-L35 -> 0 | U35: =P35-Q35 -> 0 | V35: =ABS(U35) -> 0 | W35: =T35/L35 -> #DIV/0! | X35: =ABS(W35) -> #DIV/0! | AH35: 委托书
A36: 44 | B36: 1042 | C36: 1510 | D36: 01 | E36: 5 场地发展费 | F36: 5.1 场地准备 | G36: 场地准备 | H36: 措施费 | I36: 1000040099 | J36: 夜间施工人工补贴 | M36: 项 | O36: =ROUND(N36*(1+$F$10),2) -> 0 | P36: =ROUND(K36*N36,2) -> 0 | Q36: =ROUND(L36*N36,2) -> 0 | T36: =K36-L36 -> 0 | U36: =P36-Q36 -> 0 | V36: =ABS(U36) -> 0 | W36: =T36/L36 -> #DIV/0! | X36: =ABS(W36) -> #DIV/0! | AH36: 委托书
A37: 44 | B37: 1042 | C37: 1510 | D37: 01 | E37: 5 场地发展费 | F37: 5.1 场地准备 | G37: 场地准备 | H37: 地面处理 | I37: 1000021740 | J37: 地面局部抬高 | M37: m2 | N37: 88.25 | O37: =ROUND(N37*(1+$F$10),2) -> 96.19 | P37: =ROUND(K37*N37,2) -> 0 | Q37: =ROUND(L37*N37,2) -> 0 | T37: =K37-L37 -> 0 | U37: =P37-Q37 -> 0 | V37: =ABS(U37) -> 0 | W37: =T37/L37 -> #DIV/0! | X37: =ABS(W37) -> #DIV/0! | AG37: 楼板面积
A38: 44 | B38: 1042 | C38: 1510 | D38: 01 | E38: 5 场地发展费 | F38: 5.1 场地准备 | G38: 场地准备 | H38: 地面处理 | I38: 1000021741 | J38: 地面找平（水泥砂浆>50mm时) | K38: 12.77 | L38: 12.72 | M38: m2 | N38: 52.68 | O38: =ROUND(N38*(1+$F$10),2) -> 57.42 | P38: =ROUND(K38*N38,2) -> 672.72 | Q38: =ROUND(L38*N38,2) -> 670.09 | T38: =K38-L38 -> 0.05 | U38: =P38-Q38 -> 2.63 | V38: =ABS(U38) -> 2.63 | W38: =T38/L38 -> 0.0039308176 | X38: =ABS(W38) -> 0.0039308176 | AG38: 楼板面积
A39: 44 | B39: 1042 | C39: 1510 | D39: 01 | E39: 5 场地发展费 | F39: 5.1 场地准备 | G39: 场地准备 | H39: 防水处理 | I39: 1000021742 | J39: 地面防水层（五年保修） | K39: 85.2 | L39: 85.17 | M39: m2 | N39: 60.46 | O39: =ROUND(N39*(1+$F$10),2) -> 65.9 | P39: =ROUND(K39*N39,2) -> 5151.19 | Q39: =ROUND(L39*N39,2) -> 5149.38 | T39: =K39-L39 -> 0.03 | U39: =P39-Q39 -> 1.81 | V39: =ABS(U39) -> 1.81 | W39: =T39/L39 -> 0.0003522367 | X39: =ABS(W39) -> 0.0003522367 | AG39: 楼板面积+上翻高度*踢脚长
A40: 44 | B40: 1042 | C40: 1510 | D40: 01 | E40: 5 场地发展费 | F40: 5.1 场地准备 | G40: 场地准备 | H40: 防水处理 | I40: 1000021743 | J40: 顶板／外墙防水层 | M40: m2 | N40: 71.58 | O40: =ROUND(N40*(1+$F$10),2) -> 78.02 | P40: =ROUND(K40*N40,2) -> 0 | Q40: =ROUND(L40*N40,2) -> 0 | T40: =K40-L40 -> 0 | U40: =P40-Q40 -> 0 | V40: =ABS(U40) -> 0 | W40: =T40/L40 -> #DIV/0! | X40: =ABS(W40) -> #DIV/0! | AH40: 调整
A41: 44 | B41: 1042 | C41: 1510 | D41: 01 | E41: 5 场地发展费 | F41: 5.1 场地准备 | G41: 场地准备 | H41: 防水处理 | I41: 1000040031 | J41: 门头钢构架含防水层（当招牌悬挑时） | M41: 吨 | N41: 11207.21 | O41: =ROUND(N41*(1+$F$10),2) -> 12215.86 | P41: =ROUND(K41*N41,2) -> 0 | Q41: =ROUND(L41*N41,2) -> 0 | T41: =K41-L41 -> 0 | U41: =P41-Q41 -> 0 | V41: =ABS(U41) -> 0 | W41: =T41/L41 -> #DIV/0! | X41: =ABS(W41) -> #DIV/0! | AG41: 复合天花板 外挑1.5m以上，0.013单价
A42: 45 | B42: 1043 | C42: 1520 | D42: 01 | E42: 5 场地发展费 | F42: 5.2 结构加固 | G42: 结构加固 | H42: 钢结构 | I42: 1000021744 | J42: 层高大于6米时吊顶用角钢及吊筋补贴 | M42: m2 | N42: 14 | O42: =ROUND(N42*(1+$F$10),2) -> 15.26 | P42: =ROUND(K42*N42,2) -> 0 | Q42: =ROUND(L42*N42,2) -> 0 | T42: =K42-L42 -> 0 | U42: =P42-Q42 -> 0 | V42: =ABS(U42) -> 0 | W42: =T42/L42 -> #DIV/0! | X42: =ABS(W42) -> #DIV/0! | AH42: 调整
A43: 73 | B43: 1071 | C43: 1614 | D43: 01 | E43: 6 物业施工费 | F43: 6.1 总承包工程 | G43: 6.1.4 空调通风工程 | H43: 空调机/风机安装 | I43: 1000021745 | J43: 空调室外机（含厨房设备室外机）架空钢构平台 | K43: 0.5 | L43: 0.5 | M43: 吨 | N43: 8999.8 | O43: =ROUND(N43*(1+$F$10),2) -> 9809.78 | P43: =ROUND(K43*N43,2) -> 4499.9 | Q43: =ROUND(L43*N43,2) -> 4499.9 | T43: =K43-L43 -> 0 | U43: =P43-Q43 -> 0 | V43: =ABS(U43) -> 0 | W43: =T43/L43 -> 0 | X43: =ABS(W43) -> 0 | AH43: 委托书
A44: 73 | B44: 1071 | C44: 1614 | D44: 01 | E44: 6 物业施工费 | F44: 6.1 总承包工程 | G44: 6.1.4 空调通风工程 | H44: 空调机/风机安装 | I44: 1000021746 | J44: 空调室外机（含厨房设备室外机）混凝土基座 | M44: 项 | N44: 3313.15 | O44: =ROUND(N44*(1+$F$10),2) -> 3611.33 | P44: =ROUND(K44*N44,2) -> 0 | Q44: =ROUND(L44*N44,2) -> 0 | T44: =K44-L44 -> 0 | U44: =P44-Q44 -> 0 | V44: =ABS(U44) -> 0 | W44: =T44/L44 -> #DIV/0! | X44: =ABS(W44) -> #DIV/0! | AH44: 委托书
A45: 73 | B45: 1071 | C45: 1614 | D45: 01 | E45: 6 物业施工费 | F45: 6.1 总承包工程 | G45: 6.1.4 空调通风工程 | H45: 空调机/风机安装 | I45: 1000022172 | J45: 空调外机铁丝网围壁 | M45: m2 | N45: 114.79 | O45: =ROUND(N45*(1+$F$10),2) -> 125.12 | P45: =ROUND(K45*N45,2) -> 0 | Q45: =ROUND(L45*N45,2) -> 0 | T45: =K45-L45 -> 0 | U45: =P45-Q45 -> 0 | V45: =ABS(U45) -> 0 | W45: =T45/L45 -> #DIV/0! | X45: =ABS(W45) -> #DIV/0! | AG45: 基本墙面积
A46: 45 | B46: 1043 | C46: 1520 | D46: 01 | E46: 5 场地发展费 | F46: 5.2 结构加固 | G46: 结构加固 | H46: 钢结构 | I46: 1000040100 | J46: 钢构空调室外机架空平台刷防锈漆 | M46: 项 | O46: =ROUND(N46*(1+$F$10),2) -> 0 | P46: =ROUND(K46*N46,2) -> 0 | Q46: =ROUND(L46*N46,2) -> 0 | T46: =K46-L46 -> 0 | U46: =P46-Q46 -> 0 | V46: =ABS(U46) -> 0 | W46: =T46/L46 -> #DIV/0! | X46: =ABS(W46) -> #DIV/0! | AH46: 委托书
A47: 45 | B47: 1043 | C47: 1520 | D47: 01 | E47: 5 场地发展费 | F47: 5.2 结构加固 | G47: 结构加固 | H47: 结构加固 | I47: 1000040101 | J47: 结构加固 | M47: 项 | O47: =ROUND(N47*(1+$F$10),2) -> 0 | P47: =ROUND(K47*N47,2) -> 0 | Q47: =ROUND(L47*N47,2) -> 0 | T47: =K47-L47 -> 0 | U47: =P47-Q47 -> 0 | V47: =ABS(U47) -> 0 | W47: =T47/L47 -> #DIV/0! | X47: =ABS(W47) -> #DIV/0! | AH47: 调整
A48: 46 | B48: 1044 | C48: 1530 | D48: 01 | E48: 5 场地发展费 | F48: 5.3 物业外工程 | G48: 物业外工程 | H48: 地面 | I48: 1000021446 | J48: 室外地坪及踏步贴砖（琛雄） | M48: m2 | N48: 174.03 | O48: =ROUND(N48*(1+$F$10),2) -> 189.69 | P48: =ROUND(K48*N48,2) -> 0 | Q48: =ROUND(L48*N48,2) -> 0 | T48: =K48-L48 -> 0 | U48: =P48-Q48 -> 0 | V48: =ABS(U48) -> 0 | W48: =T48/L48 -> #DIV/0! | X48: =ABS(W48) -> #DIV/0! | AG48: 楼板面积+踏步侧边基本墙面积
A49: 46 | B49: 1044 | C49: 1530 | D49: 01 | E49: 5 场地发展费 | F49: 5.3 物业外工程 | G49: 物业外工程 | H49: 地面 | I49: 1000021642 | J49: 室外地坪及踏步贴砖（共荣） | M49: m2 | N49: 159.51 | O49: =ROUND(N49*(1+$F$10),2) -> 173.87 | P49: =ROUND(K49*N49,2) -> 0 | Q49: =ROUND(L49*N49,2) -> 0 | T49: =K49-L49 -> 0 | U49: =P49-Q49 -> 0 | V49: =ABS(U49) -> 0 | W49: =T49/L49 -> #DIV/0! | X49: =ABS(W49) -> #DIV/0! | AG49: 楼板面积+踏步侧边基本墙面积
A50: 46 | B50: 1044 | C50: 1530 | D50: 01 | E50: 5 场地发展费 | F50: 5.3 物业外工程 | G50: 物业外工程 | H50: 地面 | I50: 1000021447 | J50: 室外地坪及踏步贴砖（冠军） | M50: m2 | N50: 184.92 | O50: =ROUND(N50*(1+$F$10),2) -> 201.56 | P50: =ROUND(K50*N50,2) -> 0 | Q50: =ROUND(L50*N50,2) -> 0 | T50: =K50-L50 -> 0 | U50: =P50-Q50 -> 0 | V50: =ABS(U50) -> 0 | W50: =T50/L50 -> #DIV/0! | X50: =ABS(W50) -> #DIV/0! | AG50: 楼板面积+踏步侧边基本墙面积
A51: 46 | B51: 1044 | C51: 1530 | D51: 01 | E51: 5 场地发展费 | F51: 5.3 物业外工程 | G51: 物业外工程 | H51: 地面 | I51: 1000021747 | J51: 室外地坪及踏步贴芝麻灰花岗石 | M51: m2 | N51: 288.05 | O51: =ROUND(N51*(1+$F$10),2) -> 313.97 | P51: =ROUND(K51*N51,2) -> 0 | Q51: =ROUND(L51*N51,2) -> 0 | T51: =K51-L51 -> 0 | U51: =P51-Q51 -> 0 | V51: =ABS(U51) -> 0 | W51: =T51/L51 -> #DIV/0! | X51: =ABS(W51) -> #DIV/0! | AG51: 楼板面积+踏步侧边基本墙面积
A52: 46 | B52: 1044 | C52: 1530 | D52: 01 | E52: 5 场地发展费 | F52: 5.3 物业外工程 | G52: 物业外工程 | H52: 地面 | I52: 1000021748 | J52: 室外踏步基础 | M52: m3 | N52: 531.74 | O52: =ROUND(N52*(1+$F$10),2) -> 579.6 | P52: =ROUND(K52*N52,2) -> 0 | Q52: =ROUND(L52*N52,2) -> 0 | T52: =K52-L52 -> 0 | U52: =P52-Q52 -> 0 | V52: =ABS(U52) -> 0 | W52: =T52/L52 -> #DIV/0! | X52: =ABS(W52) -> #DIV/0! | AG52: 常规模型->体积
A53: 46 | B53: 1044 | C53: 1530 | D53: 01 | E53: 5 场地发展费 | F53: 5.3 物业外工程 | G53: 物业外工程 | H53: 地面 | I53: 1000021516 | J53: 步级沿口火烧石--防滑条 | M53: 米 | N53: 47.51 | O53: =ROUND(N53*(1+$F$10),2) -> 51.79 | P53: =ROUND(K53*N53,2) -> 0 | Q53: =ROUND(L53*N53,2) -> 0 | T53: =K53-L53 -> 0 | U53: =P53-Q53 -> 0 | V53: =ABS(U53) -> 0 | W53: =T53/L53 -> #DIV/0! | X53: =ABS(W53) -> #DIV/0! | AG53: 楼板边长度
A54: 46 | B54: 1044 | C54: 1530 | D54: 01 | E54: 5 场地发展费 | F54: 5.3 物业外工程 | G54: 物业外工程 | H54: 地面 | I54: 1000041816 | J54: 步级沿口火烧石--防滑条（共荣） | M54: 米 | N54: 43.88 | O54: =ROUND(N54*(1+$F$10),2) -> 47.83 | P54: =ROUND(K54*N54,2) -> 0 | Q54: =ROUND(L54*N54,2) -> 0 | T54: =K54-L54 -> 0 | U54: =P54-Q54 -> 0 | V54: =ABS(U54) -> 0 | W54: =T54/L54 -> #DIV/0! | X54: =ABS(W54) -> #DIV/0! | AG54: 楼板边长度
A55: 46 | B55: 1044 | C55: 1530 | D55: 01 | E55: 5 场地发展费 | F55: 5.3 物业外工程 | G55: 物业外工程 | H55: 地面 | I55: 1000041822 | J55: 步级沿口火烧石--防滑条（冠军） | M55: 米 | N55: 43.88 | O55: =ROUND(N55*(1+$F$10),2) -> 47.83 | P55: =ROUND(K55*N55,2) -> 0 | Q55: =ROUND(L55*N55,2) -> 0 | T55: =K55-L55 -> 0 | U55: =P55-Q55 -> 0 | V55: =ABS(U55) -> 0 | W55: =T55/L55 -> #DIV/0! | X55: =ABS(W55) -> #DIV/0! | AG55: 楼板边长度
A56: 46 | B56: 1044 | C56: 1530 | D56: 01 | E56: 5 场地发展费 | F56: 5.3 物业外工程 | G56: 物业外工程 | H56: 墙面 | I56: 1000021620 | J56: 室外其它墙面砖（琛雄） | M56: m2 | N56: 167.98 | O56: =ROUND(N56*(1+$F$10),2) -> 183.1 | P56: =ROUND(K56*N56,2) -> 0 | Q56: =ROUND(L56*N56,2) -> 0 | T56: =K56-L56 -> 0 | U56: =P56-Q56 -> 0 | V56: =ABS(U56) -> 0 | W56: =T56/L56 -> #DIV/0! | X56: =ABS(W56) -> #DIV/0! | AG56: 基本墙面积
A57: 46 | B57: 1044 | C57: 1530 | D57: 01 | E57: 5 场地发展费 | F57: 5.3 物业外工程 | G57: 物业外工程 | H57: 墙面 | I57: 1000021675 | J57: 室外其它墙面砖（共荣） | M57: m2 | N57: 147.41 | O57: =ROUND(N57*(1+$F$10),2) -> 160.68 | P57: =ROUND(K57*N57,2) -> 0 | Q57: =ROUND(L57*N57,2) -> 0 | T57: =K57-L57 -> 0 | U57: =P57-Q57 -> 0 | V57: =ABS(U57) -> 0 | W57: =T57/L57 -> #DIV/0! | X57: =ABS(W57) -> #DIV/0! | AG57: 基本墙面积
A58: 46 | B58: 1044 | C58: 1530 | D58: 01 | E58: 5 场地发展费 | F58: 5.3 物业外工程 | G58: 物业外工程 | H58: 墙面 | I58: 1000021621 | J58: 室外其它墙面砖（冠军） | M58: m2 | N58: 169.19 | O58: =ROUND(N58*(1+$F$10),2) -> 184.42 | P58: =ROUND(K58*N58,2) -> 0 | Q58: =ROUND(L58*N58,2) -> 0 | T58: =K58-L58 -> 0 | U58: =P58-Q58 -> 0 | V58: =ABS(U58) -> 0 | W58: =T58/L58 -> #DIV/0! | X58: =ABS(W58) -> #DIV/0! | AG58: 基本墙面积
A59: 46 | B59: 1044 | C59: 1530 | D59: 01 | E59: 5 场地发展费 | F59: 5.3 物业外工程 | G59: 物业外工程 | H59: 墙面 | I59: 1000021448 | J59: 油烟管及铜管桥架等包外墙铝板 | M59: m2 | N59: 376.58 | O59: =ROUND(N59*(1+$F$10),2) -> 410.47 | P59: =ROUND(K59*N59,2) -> 0 | Q59: =ROUND(L59*N59,2) -> 0 | T59: =K59-L59 -> 0 | U59: =P59-Q59 -> 0 | V59: =ABS(U59) -> 0 | W59: =T59/L59 -> #DIV/0! | X59: =ABS(W59) -> #DIV/0! | AG59: 基本墙面积
A60: 46 | B60: 1044 | C60: 1530 | D60: 01 | E60: 5 场地发展费 | F60: 5.3 物业外工程 | G60: 物业外工程 | H60: 墙面 | I60: 1000040102 | J60: 与业主接壤处装饰及结构处理 | M60: 项 | O60: =ROUND(N60*(1+$F$10),2) -> 0 | P60: =ROUND(K60*N60,2) -> 0 | Q60: =ROUND(L60*N60,2) -> 0 | T60: =K60-L60 -> 0 | U60: =P60-Q60 -> 0 | V60: =ABS(U60) -> 0 | W60: =T60/L60 -> #DIV/0! | X60: =ABS(W60) -> #DIV/0! | AH60: 调整
A61: 46 | B61: 1044 | C61: 1530 | D61: 01 | E61: 5 场地发展费 | F61: 5.3 物业外工程 | G61: 物业外工程 | H61: 墙面 | I61: 1000040103 | J61: 非麦当劳门面之墙体装修（包括与业主商场相邻之墙体外侧装修） | M61: 项 | O61: =ROUND(N61*(1+$F$10),2) -> 0 | P61: =ROUND(K61*N61,2) -> 0 | Q61: =ROUND(L61*N61,2) -> 0 | T61: =K61-L61 -> 0 | U61: =P61-Q61 -> 0 | V61: =ABS(U61) -> 0 | W61: =T61/L61 -> #DIV/0! | X61: =ABS(W61) -> #DIV/0! | AH61: 调整
A62: 46 | B62: 1044 | C62: 1530 | D62: 01 | E62: 5 场地发展费 | F62: 5.3 物业外工程 | G62: 物业外工程 | H62: 零星绿化 | I62: 1000040032 | J62: 室外零星植物绿化 | M62: m2 | N62: 172.07 | O62: =ROUND(N62*(1+$F$10),2) -> 187.56 | P62: =ROUND(K62*N62,2) -> 0 | Q62: =ROUND(L62*N62,2) -> 0 | T62: =K62-L62 -> 0 | U62: =P62-Q62 -> 0 | V62: =ABS(U62) -> 0 | W62: =T62/L62 -> #DIV/0! | X62: =ABS(W62) -> #DIV/0! | AH62: 调整
A63: 46 | B63: 1044 | C63: 1530 | D63: 01 | E63: 5 场地发展费 | F63: 5.3 物业外工程 | G63: 物业外工程 | H63: 花槽 | I63: 1000040033 | J63: 独立成品花槽 | M63: 只 | N63: 1635.14 | O63: =ROUND(N63*(1+$F$10),2) -> 1782.3 | P63: =ROUND(K63*N63,2) -> 0 | Q63: =ROUND(L63*N63,2) -> 0 | T63: =K63-L63 -> 0 | U63: =P63-Q63 -> 0 | V63: =ABS(U63) -> 0 | W63: =T63/L63 -> #DIV/0! | X63: =ABS(W63) -> #DIV/0! | AH63: 调整
A64: 46 | B64: 1044 | C64: 1530 | D64: 01 | E64: 5 场地发展费 | F64: 5.3 物业外工程 | G64: 物业外工程 | H64: 开洞 | I64: 1000021749 | J64: 分离式厨房楼板开洞费 | M64: 项 | N64: 1355 | O64: =ROUND(N64*(1+$F$10),2) -> 1476.95 | P64: =ROUND(K64*N64,2) -> 0 | Q64: =ROUND(L64*N64,2) -> 0 | T64: =K64-L64 -> 0 | U64: =P64-Q64 -> 0 | V64: =ABS(U64) -> 0 | W64: =T64/L64 -> #DIV/0! | X64: =ABS(W64) -> #DIV/0! | AH64: 委托书
A65: 47 | B65: 1045 | C65: 1531 | D65: 01 | E65: 5 场地发展费 | F65: 5.4 道路、停车场的地面和路沿石 | G65: DT道路、停车场的地面和路沿石 | H65: DT土方运输 | I65: 1000040104 | J65: 土方场外运输 | M65: 项 | O65: =ROUND(N65*(1+$F$10),2) -> 0 | P65: =ROUND(K65*N65,2) -> 0 | Q65: =ROUND(L65*N65,2) -> 0 | T65: =K65-L65 -> 0 | U65: =P65-Q65 -> 0 | V65: =ABS(U65) -> 0 | W65: =T65/L65 -> #DIV/0! | X65: =ABS(W65) -> #DIV/0! | AH65: 委托书
A66: 47 | B66: 1045 | C66: 1531 | D66: 01 | E66: 5 场地发展费 | F66: 5.4 道路、停车场的地面和路沿石 | G66: DT道路、停车场的地面和路沿石 | H66: DT机械 | I66: 1000040105 | J66: DT-道路大型机械进出场费 | M66: 项 | O66: =ROUND(N66*(1+$F$10),2) -> 0 | P66: =ROUND(K66*N66,2) -> 0 | Q66: =ROUND(L66*N66,2) -> 0 | T66: =K66-L66 -> 0 | U66: =P66-Q66 -> 0 | V66: =ABS(U66) -> 0 | W66: =T66/L66 -> #DIV/0! | X66: =ABS(W66) -> #DIV/0! | AH66: 委托书
A67: 47 | B67: 1045 | C67: 1531 | D67: 01 | E67: 5 场地发展费 | F67: 5.4 道路、停车场的地面和路沿石 | G67: DT道路、停车场的地面和路沿石 | H67: DT道路 | I67: 1000021750 | J67: DT-路沿石 | M67: 米 | N67: 101.02 | O67: =ROUND(N67*(1+$F$10),2) -> 110.11 | P67: =ROUND(K67*N67,2) -> 0 | Q67: =ROUND(L67*N67,2) -> 0 | T67: =K67-L67 -> 0 | U67: =P67-Q67 -> 0 | V67: =ABS(U67) -> 0 | W67: =T67/L67 -> #DIV/0! | X67: =ABS(W67) -> #DIV/0! | AG67: 楼板边长度
A68: 47 | B68: 1045 | C68: 1531 | D68: 01 | E68: 5 场地发展费 | F68: 5.4 道路、停车场的地面和路沿石 | G68: DT道路、停车场的地面和路沿石 | H68: DT道路 | I68: 1000021751 | J68: DT-道路基层-水泥石屑 | M68: m2 | N68: 108.25 | O68: =ROUND(N68*(1+$F$10),2) -> 117.99 | P68: =ROUND(K68*N68,2) -> 0 | Q68: =ROUND(L68*N68,2) -> 0 | T68: =K68-L68 -> 0 | U68: =P68-Q68 -> 0 | V68: =ABS(U68) -> 0 | W68: =T68/L68 -> #DIV/0! | X68: =ABS(W68) -> #DIV/0! | AG68: 楼板面积
A69: 47 | B69: 1045 | C69: 1531 | D69: 01 | E69: 5 场地发展费 | F69: 5.4 道路、停车场的地面和路沿石 | G69: DT道路、停车场的地面和路沿石 | H69: DT道路 | I69: 1000021752 | J69: DT-道路面层-混凝土 | M69: m2 | N69: 119.55 | O69: =ROUND(N69*(1+$F$10),2) -> 130.31 | P69: =ROUND(K69*N69,2) -> 0 | Q69: =ROUND(L69*N69,2) -> 0 | T69: =K69-L69 -> 0 | U69: =P69-Q69 -> 0 | V69: =ABS(U69) -> 0 | W69: =T69/L69 -> #DIV/0! | X69: =ABS(W69) -> #DIV/0! | AG69: 楼板面积
A70: 47 | B70: 1045 | C70: 1531 | D70: 01 | E70: 5 场地发展费 | F70: 5.4 道路、停车场的地面和路沿石 | G70: DT道路、停车场的地面和路沿石 | H70: DT道路 | I70: 1000021753 | J70: DT-道路面层-沥青+碎石 | M70: m2 | N70: 140.3 | O70: =ROUND(N70*(1+$F$10),2) -> 152.93 | P70: =ROUND(K70*N70,2) -> 0 | Q70: =ROUND(L70*N70,2) -> 0 | T70: =K70-L70 -> 0 | U70: =P70-Q70 -> 0 | V70: =ABS(U70) -> 0 | W70: =T70/L70 -> #DIV/0! | X70: =ABS(W70) -> #DIV/0! | AG70: 楼板面积
A71: 47 | B71: 1045 | C71: 1531 | D71: 01 | E71: 5 场地发展费 | F71: 5.4 道路、停车场的地面和路沿石 | G71: DT道路、停车场的地面和路沿石 | H71: DT道路 | I71: 1000021754 | J71: DT-拆除道路面层 | M71: m2 | N71: 28.27 | O71: =ROUND(N71*(1+$F$10),2) -> 30.81 | P71: =ROUND(K71*N71,2) -> 0 | Q71: =ROUND(L71*N71,2) -> 0 | T71: =K71-L71 -> 0 | U71: =P71-Q71 -> 0 | V71: =ABS(U71) -> 0 | W71: =T71/L71 -> #DIV/0! | X71: =ABS(W71) -> #DIV/0! | AG71: 楼板面积
A72: 47 | B72: 1045 | C72: 1531 | D72: 01 | E72: 5 场地发展费 | F72: 5.4 道路、停车场的地面和路沿石 | G72: DT道路、停车场的地面和路沿石 | H72: DT道路 | I72: 1000021755 | J72: DT-感应器预埋 | M72: 套 | N72: 106.03 | O72: =ROUND(N72*(1+$F$10),2) -> 115.57 | P72: =ROUND(K72*N72,2) -> 0 | Q72: =ROUND(L72*N72,2) -> 0 | T72: =K72-L72 -> 0 | U72: =P72-Q72 -> 0 | V72: =ABS(U72) -> 0 | W72: =T72/L72 -> #DIV/0! | X72: =ABS(W72) -> #DIV/0! | AG72: 个数
A73: 47 | B73: 1045 | C73: 1531 | D73: 01 | E73: 5 场地发展费 | F73: 5.4 道路、停车场的地面和路沿石 | G73: DT道路、停车场的地面和路沿石 | H73: DT道路 | I73: 1000021756 | J73: DT-路面、停车场画线 | M73: 项 | N73: 15300 | O73: =ROUND(N73*(1+$F$10),2) -> 16677 | P73: =ROUND(K73*N73,2) -> 0 | Q73: =ROUND(L73*N73,2) -> 0 | T73: =K73-L73 -> 0 | U73: =P73-Q73 -> 0 | V73: =ABS(U73) -> 0 | W73: =T73/L73 -> #DIV/0! | X73: =ABS(W73) -> #DIV/0! | AH73: 委托书
A74: 47 | B74: 1045 | C74: 1531 | D74: 01 | E74: 5 场地发展费 | F74: 5.4 道路、停车场的地面和路沿石 | G74: DT道路、停车场的地面和路沿石 | H74: DT道路 | I74: 1000021757 | J74: DT-停车位限位器（挡轮器）（每套2只） | M74: 套 | N74: 60.99 | O74: =ROUND(N74*(1+$F$10),2) -> 66.48 | P74: =ROUND(K74*N74,2) -> 0 | Q74: =ROUND(L74*N74,2) -> 0 | T74: =K74-L74 -> 0 | U74: =P74-Q74 -> 0 | V74: =ABS(U74) -> 0 | W74: =T74/L74 -> #DIV/0! | X74: =ABS(W74) -> #DIV/0! | AG74: 个数
A75: 47 | B75: 1045 | C75: 1531 | D75: 01 | E75: 5 场地发展费 | F75: 5.4 道路、停车场的地面和路沿石 | G75: DT道路、停车场的地面和路沿石 | H75: DT道路 | I75: 1000021758 | J75: DT-减速带 | M75: 米 | N75: 146.19 | O75: =ROUND(N75*(1+$F$10),2) -> 159.35 | P75: =ROUND(K75*N75,2) -> 0 | Q75: =ROUND(L75*N75,2) -> 0 | T75: =K75-L75 -> 0 | U75: =P75-Q75 -> 0 | V75: =ABS(U75) -> 0 | W75: =T75/L75 -> #DIV/0! | X75: =ABS(W75) -> #DIV/0! | AG75: 长度（自建族设置）
A76: 47 | B76: 1045 | C76: 1531 | D76: 01 | E76: 5 场地发展费 | F76: 5.4 道路、停车场的地面和路沿石 | G76: DT道路、停车场的地面和路沿石 | H76: DT地面 | I76: 1000021759 | J76: DT-植（嵌）草砖 | M76: m2 | N76: 265.42 | O76: =ROUND(N76*(1+$F$10),2) -> 289.31 | P76: =ROUND(K76*N76,2) -> 0 | Q76: =ROUND(L76*N76,2) -> 0 | T76: =K76-L76 -> 0 | U76: =P76-Q76 -> 0 | V76: =ABS(U76) -> 0 | W76: =T76/L76 -> #DIV/0! | X76: =ABS(W76) -> #DIV/0! | AG76: 楼板面积
A77: 47 | B77: 1045 | C77: 1531 | D77: 01 | E77: 5 场地发展费 | F77: 5.4 道路、停车场的地面和路沿石 | G77: DT道路、停车场的地面和路沿石 | H77: DT地面 | I77: 1000021760 | J77: DT-压花地面（仅压花工艺） | M77: m2 | N77: 40.55 | O77: =ROUND(N77*(1+$F$10),2) -> 44.2 | P77: =ROUND(K77*N77,2) -> 0 | Q77: =ROUND(L77*N77,2) -> 0 | T77: =K77-L77 -> 0 | U77: =P77-Q77 -> 0 | V77: =ABS(U77) -> 0 | W77: =T77/L77 -> #DIV/0! | X77: =ABS(W77) -> #DIV/0! | AG77: 楼板面积
A78: 47 | B78: 1045 | C78: 1531 | D78: 01 | E78: 5 场地发展费 | F78: 5.4 道路、停车场的地面和路沿石 | G78: DT道路、停车场的地面和路沿石 | H78: DT防护 | I78: 1000021761 | J78: DT防撞杆 | M78: 只 | N78: 257.95 | O78: =ROUND(N78*(1+$F$10),2) -> 281.17 | P78: =ROUND(K78*N78,2) -> 0 | Q78: =ROUND(L78*N78,2) -> 0 | T78: =K78-L78 -> 0 | U78: =P78-Q78 -> 0 | V78: =ABS(U78) -> 0 | W78: =T78/L78 -> #DIV/0! | X78: =ABS(W78) -> #DIV/0! | AG78: 个数
A79: 47 | B79: 1045 | C79: 1531 | D79: 01 | E79: 5 场地发展费 | F79: 5.4 道路、停车场的地面和路沿石 | G79: DT道路、停车场的地面和路沿石 | H79: DT防护 | I79: 1000021762 | J79: DT防护栏杆安装 | M79: 只 | N79: 81.83 | O79: =ROUND(N79*(1+$F$10),2) -> 89.19 | P79: =ROUND(K79*N79,2) -> 0 | Q79: =ROUND(L79*N79,2) -> 0 | T79: =K79-L79 -> 0 | U79: =P79-Q79 -> 0 | V79: =ABS(U79) -> 0 | W79: =T79/L79 -> #DIV/0! | X79: =ABS(W79) -> #DIV/0! | AG79: 个数
A80: 47 | B80: 1045 | C80: 1531 | D80: 01 | E80: 5 场地发展费 | F80: 5.4 道路、停车场的地面和路沿石 | G80: DT道路、停车场的地面和路沿石 | H80: DT埋管、电线 | I80: 1000021763 | J80: DT-招牌电线 | M80: 米 | N80: 35.3 | O80: =ROUND(N80*(1+$F$10),2) -> 38.48 | P80: =ROUND(K80*N80,2) -> 0 | Q80: =ROUND(L80*N80,2) -> 0 | T80: =K80-L80 -> 0 | U80: =P80-Q80 -> 0 | V80: =ABS(U80) -> 0 | W80: =T80/L80 -> #DIV/0! | X80: =ABS(W80) -> #DIV/0! | AG80: 总长度（插件计算）线管
A81: 48 | B81: 1046 | C81: 1532 | D81: 01 | E81: 5 场地发展费 | F81: 5.5 场地照明 | G81: DT场地照明 | H81: DT场地灯具安装 | I81: 1000021764 | J81: 安装DT- L11 单头 | M81: 个 | N81: 723.44 | O81: =ROUND(N81*(1+$F$10),2) -> 788.55 | P81: =ROUND(K81*N81,2) -> 0 | Q81: =ROUND(L81*N81,2) -> 0 | T81: =K81-L81 -> 0 | U81: =P81-Q81 -> 0 | V81: =ABS(U81) -> 0 | W81: =T81/L81 -> #DIV/0! | X81: =ABS(W81) -> #DIV/0! | AG81: 个数
A82: 48 | B82: 1046 | C82: 1532 | D82: 01 | E82: 5 场地发展费 | F82: 5.5 场地照明 | G82: DT场地照明 | H82: DT场地灯具安装 | I82: 1000021765 | J82: 安装DT- L11 双头 | M82: 个 | N82: 723.44 | O82: =ROUND(N82*(1+$F$10),2) -> 788.55 | P82: =ROUND(K82*N82,2) -> 0 | Q82: =ROUND(L82*N82,2) -> 0 | T82: =K82-L82 -> 0 | U82: =P82-Q82 -> 0 | V82: =ABS(U82) -> 0 | W82: =T82/L82 -> #DIV/0! | X82: =ABS(W82) -> #DIV/0! | AG82: 个数
A83: 48 | B83: 1046 | C83: 1532 | D83: 01 | E83: 5 场地发展费 | F83: 5.5 场地照明 | G83: DT场地照明 | H83: DT场地灯具安装 | I83: 1000021766 | J83: 安装DT- LED时尚草坪灯具500MM L12 | M83: 个 | N83: 137.35 | O83: =ROUND(N83*(1+$F$10),2) -> 149.71 | P83: =ROUND(K83*N83,2) -> 0 | Q83: =ROUND(L83*N83,2) -> 0 | T83: =K83-L83 -> 0 | U83: =P83-Q83 -> 0 | V83: =ABS(U83) -> 0 | W83: =T83/L83 -> #DIV/0! | X83: =ABS(W83) -> #DIV/0! | AG83: 个数
A84: 48 | B84: 1046 | C84: 1532 | D84: 01 | E84: 5 场地发展费 | F84: 5.5 场地照明 | G84: DT场地照明 | H84: DT场地灯具安装 | I84: 1000021767 | J84: DT-安装 飞利浦牌36w防水防尘荧光灯1管 | M84: 个 | N84: 151.65 | O84: =ROUND(N84*(1+$F$10),2) -> 165.3 | P84: =ROUND(K84*N84,2) -> 0 | Q84: =ROUND(L84*N84,2) -> 0 | T84: =K84-L84 -> 0 | U84: =P84-Q84 -> 0 | V84: =ABS(U84) -> 0 | W84: =T84/L84 -> #DIV/0! | X84: =ABS(W84) -> #DIV/0! | AG84: 个数
A85: 48 | B85: 1046 | C85: 1532 | D85: 01 | E85: 5 场地发展费 | F85: 5.5 场地照明 | G85: DT场地照明 | H85: DT场地灯具安装 | I85: 1000021768 | J85: DT-安装 飞利浦牌36w防水防尘荧光灯2管 | M85: 个 | N85: 151.65 | O85: =ROUND(N85*(1+$F$10),2) -> 165.3 | P85: =ROUND(K85*N85,2) -> 0 | Q85: =ROUND(L85*N85,2) -> 0 | T85: =K85-L85 -> 0 | U85: =P85-Q85 -> 0 | V85: =ABS(U85) -> 0 | W85: =T85/L85 -> #DIV/0! | X85: =ABS(W85) -> #DIV/0! | AG85: 个数
... A108: 49 | B108: 1047 | C108: 1533 | D108: 01 | E108: 5 场地发展费 | F108: 5.6 场地给排水系统（含隔油池） | G108: DT场地给排水系统 | H108: DT室外给水 | I108: 1000040046 | J108: DT-水表 | M108: 套 | N108: 891.89 | O108: =ROUND(N108*(1+$F$10),2) -> 972.16 | P108: =ROUND(K108*N108,2) -> 0 | Q108: =ROUND(L108*N108,2) -> 0 | T108: =K108-L108 -> 0 | U108: =P108-Q108 -> 0 | V108: =ABS(U108) -> 0 | W108: =T108/L108 -> #DIV/0! | X108: =ABS(W108) -> #DIV/0! | AG108: 个数
A109: 50 | B109: 1048 | C109: 1534 | D109: 01 | E109: 5 场地发展费 | F109: 5.6 场地给排水系统（含隔油池） | G109: DT绿化 | H109: DT绿化 | I109: 1000040047 | J109: DT-室外植物绿化工程 | M109: m2 | N109: 172.07 | O109: =ROUND(N109*(1+$F$10),2) -> 187.56 | P109: =ROUND(K109*N109,2) -> 0 | Q109: =ROUND(L109*N109,2) -> 0 | T109: =K109-L109 -> 0 | U109: =P109-Q109 -> 0 | V109: =ABS(U109) -> 0 | W109: =T109/L109 -> #DIV/0! | X109: =ABS(W109) -> #DIV/0! | AH109: 委托书
A110: 51 | B110: 1049 | C110: 1540 | D110: 01 | E110: 5 场地发展费 | F110: 5.8 楼梯结构新建/改造 | G110: 楼梯结构新建/改造 | H110: 楼梯结构新建/改造 | I110: 1000021771 | J110: 新建钢结构楼梯（含设计及资质证明） | M110: 吨 | N110: 9020 | O110: =ROUND(N110*(1+$F$10),2) -> 9831.8 | P110: =ROUND(K110*N110,2) -> 0 | Q110: =ROUND(L110*N110,2) -> 0 | T110: =K110-L110 -> 0 | U110: =P110-Q110 -> 0 | V110: =ABS(U110) -> 0 | W110: =T110/L110 -> #DIV/0! | X110: =ABS(W110) -> #DIV/0! | AH110: CAD手算
A111: 51 | B111: 1049 | C111: 1540 | D111: 01 | E111: 5 场地发展费 | F111: 5.8 楼梯结构新建/改造 | G111: 楼梯结构新建/改造 | H111: 楼梯结构新建/改造 | I111: 1000040106 | J111: 新建钢砼楼梯 | M111: 项 | O111: =ROUND(N111*(1+$F$10),2) -> 0 | P111: =ROUND(K111*N111,2) -> 0 | Q111: =ROUND(L111*N111,2) -> 0 | T111: =K111-L111 -> 0 | U111: =P111-Q111 -> 0 | V111: =ABS(U111) -> 0 | W111: =T111/L111 -> #DIV/0! | X111: =ABS(W111) -> #DIV/0! | AH111: 委托书
A112: 51 | B112: 1049 | C112: 1540 | D112: 01 | E112: 5 场地发展费 | F112: 5.8 楼梯结构新建/改造 | G112: 楼梯结构新建/改造 | H112: 楼梯结构新建/改造 | I112: 1000040107 | J112: 改建钢结构楼梯 | M112: 项 | O112: =ROUND(N112*(1+$F$10),2) -> 0 | P112: =ROUND(K112*N112,2) -> 0 | Q112: =ROUND(L112*N112,2) -> 0 | T112: =K112-L112 -> 0 | U112: =P112-Q112 -> 0 | V112: =ABS(U112) -> 0 | W112: =T112/L112 -> #DIV/0! | X112: =ABS(W112) -> #DIV/0! | AH112: 委托书
A113: 51 | B113: 1049 | C113: 1540 | D113: 01 | E113: 5 场地发展费 | F113: 5.8 楼梯结构新建/改造 | G113: 楼梯结构新建/改造 | H113: 楼梯结构新建/改造 | I113: 1000040108 | J113: 改建钢砼楼梯 | M113: 项 | O113: =ROUND(N113*(1+$F$10),2) -> 0 | P113: =ROUND(K113*N113,2) -> 0 | Q113: =ROUND(L113*N113,2) -> 0 | T113: =K113-L113 -> 0 | U113: =P113-Q113 -> 0 | V113: =ABS(U113) -> 0 | W113: =T113/L113 -> #DIV/0! | X113: =ABS(W113) -> #DIV/0! | AH113: 委托书
A114: 56 | B114: 1054 | C114: 1611 | D114: 01 | E114: 6 物业施工费 | F114: 6.1 总承包工程 | G114: 6.1.1 内部装修工程 | H114: 大堂地面（不含卫生间及楼梯） | I114: 1000021456 | J114: 国产同质砖（琛雄，含不超过50mm厚的找平层） | M114: m2 | N114: 180.78 | O114: =ROUND(N114*(1+$F$10),2) -> 197.05 | P114: =ROUND(K114*N114,2) -> 0 | Q114: =ROUND(L114*N114,2) -> 0 | T114: =K114-L114 -> 0 | U114: =P114-Q114 -> 0 | V114: =ABS(U114) -> 0 | W114: =T114/L114 -> #DIV/0! | X114: =ABS(W114) -> #DIV/0! | AG114: 楼板面积
A115: 56 | B115: 1054 | C115: 1611 | D115: 01 | E115: 6 物业施工费 | F115: 6.1 总承包工程 | G115: 6.1.1 内部装修工程 | H115: 大堂地面（不含卫生间及楼梯） | I115: 1000021457 | J115: 国产同质砖踢脚（琛雄） | M115: 米 | N115: 41.36 | O115: =ROUND(N115*(1+$F$10),2) -> 45.08 | P115: =ROUND(K115*N115,2) -> 0 | Q115: =ROUND(L115*N115,2) -> 0 | T115: =K115-L115 -> 0 | U115: =P115-Q115 -> 0 | V115: =ABS(U115) -> 0 | W115: =T115/L115 -> #DIV/0! | X115: =ABS(W115) -> #DIV/0! | AG115: 踢脚长度
A116: 56 | B116: 1054 | C116: 1611 | D116: 01 | E116: 6 物业施工费 | F116: 6.1 总承包工程 | G116: 6.1.1 内部装修工程 | H116: 大堂地面（不含卫生间及楼梯） | I116: 1000021643 | J116: 国产同质砖（共荣，含不超过50mm厚的找平层） | M116: m2 | N116: 160.21 | O116: =ROUND(N116*(1+$F$10),2) -> 174.63 | P116: =ROUND(K116*N116,2) -> 0 | Q116: =ROUND(L116*N116,2) -> 0 | T116: =K116-L116 -> 0 | U116: =P116-Q116 -> 0 | V116: =ABS(U116) -> 0 | W116: =T116/L116 -> #DIV/0! | X116: =ABS(W116) -> #DIV/0! | AG116: 楼板面积
A117: 56 | B117: 1054 | C117: 1611 | D117: 01 | E117: 6 物业施工费 | F117: 6.1 总承包工程 | G117: 6.1.1 内部装修工程 | H117: 大堂地面（不含卫生间及楼梯） | I117: 1000021644 | J117: 国产同质砖踢脚（共荣） | M117: 米 | N117: 38.94 | O117: =ROUND(N117*(1+$F$10),2) -> 42.44 | P117: =ROUND(K117*N117,2) -> 0 | Q117: =ROUND(L117*N117,2) -> 0 | T117: =K117-L117 -> 0 | U117: =P117-Q117 -> 0 | V117: =ABS(U117) -> 0 | W117: =T117/L117 -> #DIV/0! | X117: =ABS(W117) -> #DIV/0! | AG117: 踢脚长度
A118: 56 | B118: 1054 | C118: 1611 | D118: 01 | E118: 6 物业施工费 | F118: 6.1 总承包工程 | G118: 6.1.1 内部装修工程 | H118: 大堂地面（不含卫生间及楼梯） | I118: 1000021622 | J118: 国产同质砖（冠军，含不超过50mm厚的找平层） | M118: m2 | N118: 181.99 | O118: =ROUND(N118*(1+$F$10),2) -> 198.37 | P118: =ROUND(K118*N118,2) -> 0 | Q118: =ROUND(L118*N118,2) -> 0 | T118: =K118-L118 -> 0 | U118: =P118-Q118 -> 0 | V118: =ABS(U118) -> 0 | W118: =T118/L118 -> #DIV/0! | X118: =ABS(W118) -> #DIV/0! | AG118: 楼板面积
A119: 56 | B119: 1054 | C119: 1611 | D119: 01 | E119: 6 物业施工费 | F119: 6.1 总承包工程 | G119: 6.1.1 内部装修工程 | H119: 大堂地面（不含卫生间及楼梯） | I119: 1000021623 | J119: 国产同质砖踢脚（冠军） | M119: 米 | N119: 42.57 | O119: =ROUND(N119*(1+$F$10),2) -> 46.4 | P119: =ROUND(K119*N119,2) -> 0 | Q119: =ROUND(L119*N119,2) -> 0 | T119: =K119-L119 -> 0 | U119: =P119-Q119 -> 0 | V119: =ABS(U119) -> 0 | W119: =T119/L119 -> #DIV/0! | X119: =ABS(W119) -> #DIV/0! | AG119: 踢脚长度
A120: 56 | B120: 1054 | C120: 1611 | D120: 01 | E120: 6 物业施工费 | F120: 6.1 总承包工程 | G120: 6.1.1 内部装修工程 | H120: 大堂地面（不含卫生间及楼梯） | I120: 1000051755 | J120: 600*600mm灰色水泥地砖（琛雄，含不超过50mm厚的找平层） | M120: m2 | N120: 187.98 | O120: =ROUND(N120*(1+$F$10),2) -> 204.9 | P120: =ROUND(K120*N120,2) -> 0 | Q120: =ROUND(L120*N120,2) -> 0 | T120: =K120-L120 -> 0 | U120: =P120-Q120 -> 0 | V120: =ABS(U120) -> 0 | W120: =T120/L120 -> #DIV/0! | X120: =ABS(W120) -> #DIV/0! | AG120: 楼板面积
A121: 56 | B121: 1054 | C121: 1611 | D121: 01 | E121: 6 物业施工费 | F121: 6.1 总承包工程 | G121: 6.1.1 内部装修工程 | H121: 大堂地面（不含卫生间及楼梯） | I121: 1000051756 | J121: 600*600mm灰色水泥地砖（共荣，含不超过50mm厚的找平层） | M121: m2 | N121: 171.66 | O121: =ROUND(N121*(1+$F$10),2) -> 187.11 | P121: =ROUND(K121*N121,2) -> 0 | Q121: =ROUND(L121*N121,2) -> 0 | T121: =K121-L121 -> 0 | U121: =P121-Q121 -> 0 | V121: =ABS(U121) -> 0 | W121: =T121/L121 -> #DIV/0! | X121: =ABS(W121) -> #DIV/0! | AG121: 楼板面积
A122: 56 | B122: 1054 | C122: 1611 | D122: 01 | E122: 6 物业施工费 | F122: 6.1 总承包工程 | G122: 6.1.1 内部装修工程 | H122: 大堂地面（不含卫生间及楼梯） | I122: 1000051757 | J122: 600*600mm灰色水泥地砖（冠军，含不超过50mm厚的找平层） | M122: m2 | N122: 189.15 | O122: =ROUND(N122*(1+$F$10),2) -> 206.17 | P122: =ROUND(K122*N122,2) -> 0 | Q122: =ROUND(L122*N122,2) -> 0 | T122: =K122-L122 -> 0 | U122: =P122-Q122 -> 0 | V122: =ABS(U122) -> 0 | W122: =T122/L122 -> #DIV/0! | X122: =ABS(W122) -> #DIV/0! | AG122: 楼板面积
A123: 56 | B123: 1054 | C123: 1611 | D123: 01 | E123: 6 物业施工费 | F123: 6.1 总承包工程 | G123: 6.1.1 内部装修工程 | H123: 大堂地面（不含卫生间及楼梯） | I123: 1000053612 | J123: 灰色水泥纹踢脚（琛雄） | M123: 米 | N123: 41.36 | O123: =ROUND(N123*(1+$F$10),2) -> 45.08 | P123: =ROUND(K123*N123,2) -> 0 | Q123: =ROUND(L123*N123,2) -> 0 | T123: =K123-L123 -> 0 | U123: =P123-Q123 -> 0 | V123: =ABS(U123) -> 0 | W123: =T123/L123 -> #DIV/0! | X123: =ABS(W123) -> #DIV/0! | AG123: 踢脚长度
...

Sheet 预算书-找差异
A1: 麦当劳(中国)工程预算书(IN RMB) V20250409 | U1: 要求 | W1: 子目飘红15个 | Y1: 做店速度 3天内； | AB1: 总价绝对值偏差控制在±2%以内； | AE1: ABS偏差4%以内；
E2: 麦咖啡 | F2: 1 | H2: 区域 | J2: 中区 | M2: 麦当劳项目经理 | O2: 高虹 | U2: 总价金额 | V2: 总金额偏差 | W2: 总金额偏差率 | X2: ABS偏差 | Y2: ABS偏差率 | AA2: 初步差异： | AB2: 飘红 | AC2: 漏项 | AD2: 多项
E3: 店内甜品站 | H3: 市场 | J3: 上海 | M3: 餐厅类型 | O3: 新店 | P3: Instore | Q3: Instore | T3: REVIT | U3: =P2540 -> 602809.05 | AB3: 13 | AD3: 2
E4: 独立甜品站 | H4: 城市 | J4: 上海市 | M4: 招标方式 | O4: 集中招标 | T4: 初稿 | U4: =Q2540 -> 593377.83 | V4: =U3-U4 -> 9431.22 | W4: =V4/U3 -> 0.015645452 | X4: =V2540 -> 15685.78 | Y4: =X4/U3 -> 0.026021142
E5: MDS | F5: 1 | H5: 餐厅名称 | J5: 浦东张江中科路地铁站餐厅 | M5: 中标单价选用 | O5: 上海锦伟
E6: 卫生间 | H6: PP编码 | J6: 234618 | M6: 异地施工上浮系数 | O6: 0 | AA6: 如何通过检查发现？
E7: 楼梯 | H7: 面积 | J7: 185 | U7: 电箱图，弱点常规配置，餐厅常规配置 | W7: 53 | AA7: 拿审核表检查错误，补充细节
E8: 分离式厨房 | H8: 座位数 | J8: 40 | M8: 编制人 | U8: 委托书，项目信息，部分市场特性等无需通过建模出具的清单 | W8: 10
E9: 儿童乐园 | H9: 层高 | M9: 审核人 | U9: 建模正常可出清单 | W9: 148 | Y9: 建模出量率 | Z9: 刨除不建模出量的，建模出量率
E10: 税率 | F10: 0.09 | H10: 设计风格 | J10: Geometry | M10: 编制日期 | U10: 技术原因，暂时无法出清单的 | W10: 11 | Y10: =W9/(W7+W8+W9+W10) -> 0.66666667 | Z10: =W9/(W9+W10) -> 0.93081761
A12: CO | B12: PMT Code | C12: Asset Code | D12: BE类型 | E12: 类别 | F12: 编号1 | G12: 编号2 | H12: 编号3 | I12: SKU编码 | J12: 项目名称 | K12: revit数量 | L12: 初稿数量 | M12: 单位 | N12: 综合单价（不含税） | O12: 综合单价（含税） | P12: revit合价 | Q12: 初稿合价 | R12: 检查 | S12: 备注 | T12: 工程量差异 | U12: 合价差异 | V12: 合价ABS | W12: 差异率 | X12: ABS差异 | Y12: 调平原因 | Z12: 清单来源 | AA12: 错误原因
A13: 7 | B13: 1005 | C13: 6002 | D13: 01 | E13: 0 地产费用 | F13: 0.2 房产建筑 | G13: DT基础(分包) | H13: DT基础(分包) | I13: 1000040096 | J13: DT基础(分包) | M13: 项 | O13: =ROUND(N13*(1+$F$10),2) -> 0 | P13: =ROUND(K13*N13,2) -> 0 | Q13: =ROUND(L13*N13,2) -> 0 | T13: =K13-L13 -> 0 | U13: =P13-Q13 -> 0 | V13: =ABS(U13) -> 0 | W13: =T13/L13 -> #DIV/0! | X13: =ABS(W13) -> #DIV/0!
A14: 8 | B14: 1006 | C14: 6002 | D14: 01 | E14: 0 地产费用 | F14: 0.2 房产建筑 | G14: DT主体建筑(分包) | H14: DT主体建筑(分包) | I14: 1000040097 | J14: DT主体建筑(分包) | M14: 项 | O14: =ROUND(N14*(1+$F$10),2) -> 0 | P14: =ROUND(K14*N14,2) -> 0 | Q14: =ROUND(L14*N14,2) -> 0 | T14: =K14-L14 -> 0 | U14: =P14-Q14 -> 0 | V14: =ABS(U14) -> 0 | W14: =T14/L14 -> #DIV/0! | X14: =ABS(W14) -> #DIV/0!
A15: 33 | B15: 1031 | C15: 1314 | D15: 01 | E15: 3 许可证/公用事业费 | F15: 3.1 供电费用 | G15: 3.1.4 红线电缆接线费 | H15: 3.1.4 红线电缆接线费 | I15: 1000021726 | J15: 红线电缆YJV 120双拼 或 YJV240单根 含桥架（按桥架长度计算） | M15: 米 | N15: 1000.44 | O15: =ROUND(N15*(1+$F$10),2) -> 1090.48 | P15: =ROUND(K15*N15,2) -> 0 | Q15: =ROUND(L15*N15,2) -> 0 | T15: =K15-L15 -> 0 | U15: =P15-Q15 -> 0 | V15: =ABS(U15) -> 0 | W15: =T15/L15 -> #DIV/0! | X15: =ABS(W15) -> #DIV/0!
A16: 33 | B16: 1031 | C16: 1314 | D16: 01 | E16: 3 许可证/公用事业费 | F16: 3.1 供电费用 | G16: 3.1.4 红线电缆接线费 | H16: 3.1.4 红线电缆接线费 | I16: 1000021725 | J16: 红线电缆 YJV 95 双拼 或 YJV185单根 含桥架（按桥架长度计算） | M16: 米 | N16: 872.84 | O16: =ROUND(N16*(1+$F$10),2) -> 951.4 | P16: =ROUND(K16*N16,2) -> 0 | Q16: =ROUND(L16*N16,2) -> 0 | T16: =K16-L16 -> 0 | U16: =P16-Q16 -> 0 | V16: =ABS(U16) -> 0 | W16: =T16/L16 -> #DIV/0! | X16: =ABS(W16) -> #DIV/0!
A17: 33 | B17: 1031 | C17: 1314 | D17: 01 | E17: 3 许可证/公用事业费 | F17: 3.1 供电费用 | G17: 3.1.4 红线电缆接线费 | H17: 3.1.4 红线电缆接线费 | I17: 1000021727 | J17: 铠装红线电缆YJV 120双拼 或 YJV240单根 含桥架（按桥架长度计算） | M17: 米 | N17: 1000.44 | O17: =ROUND(N17*(1+$F$10),2) -> 1090.48 | P17: =ROUND(K17*N17,2) -> 0 | Q17: =ROUND(L17*N17,2) -> 0 | T17: =K17-L17 -> 0 | U17: =P17-Q17 -> 0 | V17: =ABS(U17) -> 0 | W17: =T17/L17 -> #DIV/0! | X17: =ABS(W17) -> #DIV/0!
A18: 33 | B18: 1031 | C18: 1314 | D18: 01 | E18: 3 许可证/公用事业费 | F18: 3.1 供电费用 | G18: 3.1.4 红线电缆接线费 | H18: 3.1.4 红线电缆接线费 | I18: 1000021728 | J18: 铠装红线电缆 YJV 95 双拼 或 YJV185单根 含桥架（按桥架长度计算） | M18: 米 | N18: 872.84 | O18: =ROUND(N18*(1+$F$10),2) -> 951.4 | P18: =ROUND(K18*N18,2) -> 0 | Q18: =ROUND(L18*N18,2) -> 0 | T18: =K18-L18 -> 0 | U18: =P18-Q18 -> 0 | V18: =ABS(U18) -> 0 | W18: =T18/L18 -> #DIV/0! | X18: =ABS(W18) -> #DIV/0!
A19: 33 | B19: 1031 | C19: 1314 | D19: 01 | E19: 3 许可证/公用事业费 | F19: 3.1 供电费用 | G19: 3.1.4 红线电缆接线费 | H19: 3.1.4 红线电缆接线费 | I19: 1000040026 | J19: 室外电缆沟（含井）开挖及回填 | M19: 米 | N19: 135.14 | O19: =ROUND(N19*(1+$F$10),2) -> 147.3 | P19: =ROUND(K19*N19,2) -> 0 | Q19: =ROUND(L19*N19,2) -> 0 | T19: =K19-L19 -> 0 | U19: =P19-Q19 -> 0 | V19: =ABS(U19) -> 0 | W19: =T19/L19 -> #DIV/0! | X19: =ABS(W19) -> #DIV/0!
A20: 34 | B20: 1032 | C20: 1320 | D20: 01 | E20: 3 许可证/公用事业费 | F20: 3.2 给、排水接驳费 | G20: 给、排水接驳费 | H20: 给、排水接驳费 | I20: 1000021729 | J20: 给水接驳费 | M20: 米 | N20: 96.36 | O20: =ROUND(N20*(1+$F$10),2) -> 105.03 | P20: =ROUND(K20*N20,2) -> 0 | Q20: =ROUND(L20*N20,2) -> 0 | T20: =K20-L20 -> 0 | U20: =P20-Q20 -> 0 | V20: =ABS(U20) -> 0 | W20: =T20/L20 -> #DIV/0! | X20: =ABS(W20) -> #DIV/0!
A21: 34 | B21: 1032 | C21: 1320 | D21: 01 | E21: 3 许可证/公用事业费 | F21: 3.2 给、排水接驳费 | G21: 给、排水接驳费 | H21: 给、排水接驳费 | I21: 1000021730 | J21: 排水接驳费 | M21: 米 | N21: 92.09 | O21: =ROUND(N21*(1+$F$10),2) -> 100.38 | P21: =ROUND(K21*N21,2) -> 0 | Q21: =ROUND(L21*N21,2) -> 0 | T21: =K21-L21 -> 0 | U21: =P21-Q21 -> 0 | V21: =ABS(U21) -> 0 | W21: =T21/L21 -> #DIV/0! | X21: =ABS(W21) -> #DIV/0!
A22: 37 | B22: 1035 | C22: 1350 | D22: 01 | E22: 3 许可证/公用事业费 | F22: 3.5 电话系统 | G22: 电话申请费 | H22: 电话申请费 | I22: 1000040027 | J22: 电话申请费 | M22: 项 | N22: 1801.8 | O22: =ROUND(N22*(1+$F$10),2) -> 1963.96 | P22: =ROUND(K22*N22,2) -> 0 | Q22: =ROUND(L22*N22,2) -> 0 | T22: =K22-L22 -> 0 | U22: =P22-Q22 -> 0 | V22: =ABS(U22) -> 0 | W22: =T22/L22 -> #DIV/0! | X22: =ABS(W22) -> #DIV/0!
A23: 38 | B23: 1036 | C23: 1360 | D23: 01 | E23: 3 许可证/公用事业费 | F23: 3.6 其他许可证申请费 | G23: 其他许可证申请费 | H23: 其他许可证申请费 | I23: 1000040028 | J23: 有线电视申请费 | M23: 项 | N23: 1351.35 | O23: =ROUND(N23*(1+$F$10),2) -> 1472.97 | P23: =ROUND(K23*N23,2) -> 0 | Q23: =ROUND(L23*N23,2) -> 0 | T23: =K23-L23 -> 0 | U23: =P23-Q23 -> 0 | V23: =ABS(U23) -> 0 | W23: =T23/L23 -> #DIV/0! | X23: =ABS(W23) -> #DIV/0!
A24: 38 | B24: 1036 | C24: 1360 | D24: 01 | E24: 3 许可证/公用事业费 | F24: 3.6 其他许可证申请费 | G24: 其他许可证申请费 | H24: 其他许可证申请费 | I24: 1000040098 | J24: 其他许可证申请费（含：1.环评费、2.环保申请费、3.规划申报费、4.城管／市容申报费、5.建委／招标办之甲方报建费、6.卫生防疫站申报费、7.房屋鉴定费、8.市政申请费 | K24: 1 | L24: 1 | M24: 项 | N24: 41284.4 | O24: =ROUND(N24*(1+$F$10),2) -> 45000 | P24: =ROUND(K24*N24,2) -> 41284.4 | Q24: =ROUND(L24*N24,2) -> 41284.4 | T24: =K24-L24 -> 0 | U24: =P24-Q24 -> 0 | V24: =ABS(U24) -> 0 | W24: =T24/L24 -> 0 | X24: =ABS(W24) -> 0
A25: 40 | B25: 1038 | C25: 1410 | D25: 01 | E25: 4 拆除费 | F25: 4.1 场地清拆 | G25: 场地清拆 | H25: 场地清拆 | I25: 1000021731 | J25: 现场清拆（零星拆除,含非特殊位置清运） | K25: 185 | L25: 185 | M25: m2 | N25: 27.2 | O25: =ROUND(N25*(1+$F$10),2) -> 29.65 | P25: =ROUND(K25*N25,2) -> 5032 | Q25: =ROUND(L25*N25,2) -> 5032 | T25: =K25-L25 -> 0 | U25: =P25-Q25 -> 0 | V25: =ABS(U25) -> 0 | W25: =T25/L25 -> 0 | X25: =ABS(W25) -> 0
A26: 40 | B26: 1038 | C26: 1410 | D26: 01 | E26: 4 拆除费 | F26: 4.1 场地清拆 | G26: 场地清拆 | H26: 场地清拆 | I26: 1000021732 | J26: 现场清拆（大面积拆除--天地墙全面拆除，含非特殊位置清运） | M26: m2 | N26: 73 | O26: =ROUND(N26*(1+$F$10),2) -> 79.57 | P26: =ROUND(K26*N26,2) -> 0 | Q26: =ROUND(L26*N26,2) -> 0 | T26: =K26-L26 -> 0 | U26: =P26-Q26 -> 0 | V26: =ABS(U26) -> 0 | W26: =T26/L26 -> #DIV/0! | X26: =ABS(W26) -> #DIV/0!
A27: 40 | B27: 1038 | C27: 1410 | D27: 01 | E27: 4 拆除费 | F27: 4.1 场地清拆 | G27: 场地清拆 | H27: 场地清拆 | I27: 1000021733 | J27: 现场清拆（特大面积拆除--天地墙全面拆除、结构拆除，含非特殊位置清运） | M27: m2 | N27: 109 | O27: =ROUND(N27*(1+$F$10),2) -> 118.81 | P27: =ROUND(K27*N27,2) -> 0 | Q27: =ROUND(L27*N27,2) -> 0 | T27: =K27-L27 -> 0 | U27: =P27-Q27 -> 0 | V27: =ABS(U27) -> 0 | W27: =T27/L27 -> #DIV/0! | X27: =ABS(W27) -> #DIV/0!
A28: 40 | B28: 1038 | C28: 1410 | D28: 01 | E28: 4 拆除费 | F28: 4.1 场地清拆 | G28: 场地清拆 | H28: 场地清拆 | I28: 1000021734 | J28: 现场清拆（零星拆除,含特殊位置清运） | M28: m2 | N28: 54.5 | O28: =ROUND(N28*(1+$F$10),2) -> 59.41 | P28: =ROUND(K28*N28,2) -> 0 | Q28: =ROUND(L28*N28,2) -> 0 | T28: =K28-L28 -> 0 | U28: =P28-Q28 -> 0 | V28: =ABS(U28) -> 0 | W28: =T28/L28 -> #DIV/0! | X28: =ABS(W28) -> #DIV/0!
A29: 40 | B29: 1038 | C29: 1410 | D29: 01 | E29: 4 拆除费 | F29: 4.1 场地清拆 | G29: 场地清拆 | H29: 场地清拆 | I29: 1000021735 | J29: 现场清拆（大面积拆除--天地墙全面拆除，含特殊位置清运） | M29: m2 | N29: 181.5 | O29: =ROUND(N29*(1+$F$10),2) -> 197.84 | P29: =ROUND(K29*N29,2) -> 0 | Q29: =ROUND(L29*N29,2) -> 0 | T29: =K29-L29 -> 0 | U29: =P29-Q29 -> 0 | V29: =ABS(U29) -> 0 | W29: =T29/L29 -> #DIV/0! | X29: =ABS(W29) -> #DIV/0!
A30: 40 | B30: 1038 | C30: 1410 | D30: 01 | E30: 4 拆除费 | F30: 4.1 场地清拆 | G30: 场地清拆 | H30: 场地清拆 | I30: 1000021736 | J30: 现场清拆（特大面积拆除--天地墙全面拆除、结构拆除，含特殊位置清运） | M30: m2 | N30: 284.5 | O30: =ROUND(N30*(1+$F$10),2) -> 310.11 | P30: =ROUND(K30*N30,2) -> 0 | Q30: =ROUND(L30*N30,2) -> 0 | T30: =K30-L30 -> 0 | U30: =P30-Q30 -> 0 | V30: =ABS(U30) -> 0 | W30: =T30/L30 -> #DIV/0! | X30: =ABS(W30) -> #DIV/0!
A31: 40 | B31: 1038 | C31: 1410 | D31: 01 | E31: 4 拆除费 | F31: 4.1 场地清拆 | G31: 场地清拆 | H31: 场地清拆 | I31: 1000021737 | J31: 场地清洁 | K31: 185 | L31: 185 | M31: m2 | N31: 20 | O31: =ROUND(N31*(1+$F$10),2) -> 21.8 | P31: =ROUND(K31*N31,2) -> 3700 | Q31: =ROUND(L31*N31,2) -> 3700 | T31: =K31-L31 -> 0 | U31: =P31-Q31 -> 0 | V31: =ABS(U31) -> 0 | W31: =T31/L31 -> 0 | X31: =ABS(W31) -> 0
A32: 41 | B32: 1039 | C32: 1420 | D32: 01 | E32: 4 拆除费 | F32: 4.2 围墙板 | G32: 围墙板 | H32: 围墙板 | I32: 1000021738 | J32: 场地围墙板等 | K32: 50.19 | L32: 49.9 | M32: m2 | N32: 58.7 | O32: =ROUND(N32*(1+$F$10),2) -> 63.98 | P32: =ROUND(K32*N32,2) -> 2946.15 | Q32: =ROUND(L32*N32,2) -> 2929.13 | T32: =K32-L32 -> 0.29 | U32: =P32-Q32 -> 17.02 | V32: =ABS(U32) -> 17.02 | W32: =T32/L32 -> 0.0058116232 | X32: =ABS(W32) -> 0.0058116232
A33: 44 | B33: 1042 | C33: 1510 | D33: 01 | E33: 5 场地发展费 | F33: 5.1 场地准备 | G33: 场地准备 | H33: 措施费 | I33: 1000021739 | J33: 措施费（新店） | K33: 1 | L33: 1 | M33: 项 | N33: 15380 | O33: =ROUND(N33*(1+$F$10),2) -> 16764.2 | P33: =ROUND(K33*N33,2) -> 15380 | Q33: =ROUND(L33*N33,2) -> 15380 | T33: =K33-L33 -> 0 | U33: =P33-Q33 -> 0 | V33: =ABS(U33) -> 0 | W33: =T33/L33 -> 0 | X33: =ABS(W33) -> 0
A34: 44 | B34: 1042 | C34: 1510 | D34: 01 | E34: 5 场地发展费 | F34: 5.1 场地准备 | G34: 场地准备 | H34: 措施费 | I34: 1000022205 | J34: 措施费（改造店） | M34: 项 | N34: 26126.13 | O34: =ROUND(N34*(1+$F$10),2) -> 28477.48 | P34: =ROUND(K34*N34,2) -> 0 | Q34: =ROUND(L34*N34,2) -> 0 | T34: =K34-L34 -> 0 | U34: =P34-Q34 -> 0 | V34: =ABS(U34) -> 0 | W34: =T34/L34 -> #DIV/0! | X34: =ABS(W34) -> #DIV/0!
A35: 44 | B35: 1042 | C35: 1510 | D35: 01 | E35: 5 场地发展费 | F35: 5.1 场地准备 | G35: 场地准备 | H35: 措施费 | I35: 1000040030 | J35: 北区冬季施工费 | M35: 项 | N35: 18018.02 | O35: =ROUND(N35*(1+$F$10),2) -> 19639.64 | P35: =ROUND(K35*N35,2) -> 0 | Q35: =ROUND(L35*N35,2) -> 0 | T35: =K35-L35 -> 0 | U35: =P35-Q35 -> 0 | V35: =ABS(U35) -> 0 | W35: =T35/L35 -> #DIV/0! | X35: =ABS(W35) -> #DIV/0!
A36: 44 | B36: 1042 | C36: 1510 | D36: 01 | E36: 5 场地发展费 | F36: 5.1 场地准备 | G36: 场地准备 | H36: 措施费 | I36: 1000040099 | J36: 夜间施工人工补贴 | M36: 项 | O36: =ROUND(N36*(1+$F$10),2) -> 0 | P36: =ROUND(K36*N36,2) -> 0 | Q36: =ROUND(L36*N36,2) -> 0 | T36: =K36-L36 -> 0 | U36: =P36-Q36 -> 0 | V36: =ABS(U36) -> 0 | W36: =T36/L36 -> #DIV/0! | X36: =ABS(W36) -> #DIV/0!
A37: 44 | B37: 1042 | C37: 1510 | D37: 01 | E37: 5 场地发展费 | F37: 5.1 场地准备 | G37: 场地准备 | H37: 地面处理 | I37: 1000021740 | J37: 地面局部抬高 | M37: m2 | N37: 88.25 | O37: =ROUND(N37*(1+$F$10),2) -> 96.19 | P37: =ROUND(K37*N37,2) -> 0 | Q37: =ROUND(L37*N37,2) -> 0 | T37: =K37-L37 -> 0 | U37: =P37-Q37 -> 0 | V37: =ABS(U37) -> 0 | W37: =T37/L37 -> #DIV/0! | X37: =ABS(W37) -> #DIV/0!
A38: 44 | B38: 1042 | C38: 1510 | D38: 01 | E38: 5 场地发展费 | F38: 5.1 场地准备 | G38: 场地准备 | H38: 地面处理 | I38: 1000021741 | J38: 地面找平（水泥砂浆>50mm时) | K38: 12.77 | L38: 12.72 | M38: m2 | N38: 52.68 | O38: =ROUND(N38*(1+$F$10),2) -> 57.42 | P38: =ROUND(K38*N38,2) -> 672.72 | Q38: =ROUND(L38*N38,2) -> 670.09 | T38: =K38-L38 -> 0.05 | U38: =P38-Q38 -> 2.63 | V38: =ABS(U38) -> 2.63 | W38: =T38/L38 -> 0.0039308176 | X38: =ABS(W38) -> 0.0039308176
A39: 44 | B39: 1042 | C39: 1510 | D39: 01 | E39: 5 场地发展费 | F39: 5.1 场地准备 | G39: 场地准备 | H39: 防水处理 | I39: 1000021742 | J39: 地面防水层（五年保修） | K39: 85.2 | L39: 85.17 | M39: m2 | N39: 60.46 | O39: =ROUND(N39*(1+$F$10),2) -> 65.9 | P39: =ROUND(K39*N39,2) -> 5151.19 | Q39: =ROUND(L39*N39,2) -> 5149.38 | T39: =K39-L39 -> 0.03 | U39: =P39-Q39 -> 1.81 | V39: =ABS(U39) -> 1.81 | W39: =T39/L39 -> 0.0003522367 | X39: =ABS(W39) -> 0.0003522367
A40: 44 | B40: 1042 | C40: 1510 | D40: 01 | E40: 5 场地发展费 | F40: 5.1 场地准备 | G40: 场地准备 | H40: 防水处理 | I40: 1000021743 | J40: 顶板／外墙防水层 | M40: m2 | N40: 71.58 | O40: =ROUND(N40*(1+$F$10),2) -> 78.02 | P40: =ROUND(K40*N40,2) -> 0 | Q40: =ROUND(L40*N40,2) -> 0 | T40: =K40-L40 -> 0 | U40: =P40-Q40 -> 0 | V40: =ABS(U40) -> 0 | W40: =T40/L40 -> #DIV/0! | X40: =ABS(W40) -> #DIV/0!
A41: 44 | B41: 1042 | C41: 1510 | D41: 01 | E41: 5 场地发展费 | F41: 5.1 场地准备 | G41: 场地准备 | H41: 防水处理 | I41: 1000040031 | J41: 门头钢构架含防水层（当招牌悬挑时） | M41: 吨 | N41: 11207.21 | O41: =ROUND(N41*(1+$F$10),2) -> 12215.86 | P41: =ROUND(K41*N41,2) -> 0 | Q41: =ROUND(L41*N41,2) -> 0 | T41: =K41-L41 -> 0 | U41: =P41-Q41 -> 0 | V41: =ABS(U41) -> 0 | W41: =T41/L41 -> #DIV/0! | X41: =ABS(W41) -> #DIV/0!
A42: 45 | B42: 1043 | C42: 1520 | D42: 01 | E42: 5 场地发展费 | F42: 5.2 结构加固 | G42: 结构加固 | H42: 钢结构 | I42: 1000021744 | J42: 层高大于6米时吊顶用角钢及吊筋补贴 | M42: m2 | N42: 14 | O42: =ROUND(N42*(1+$F$10),2) -> 15.26 | P42: =ROUND(K42*N42,2) -> 0 | Q42: =ROUND(L42*N42,2) -> 0 | T42: =K42-L42 -> 0 | U42: =P42-Q42 -> 0 | V42: =ABS(U42) -> 0 | W42: =T42/L42 -> #DIV/0! | X42: =ABS(W42) -> #DIV/0!
A43: 73 | B43: 1071 | C43: 1614 | D43: 01 | E43: 6 物业施工费 | F43: 6.1 总承包工程 | G43: 6.1.4 空调通风工程 | H43: 空调机/风机安装 | I43: 1000021745 | J43: 空调室外机（含厨房设备室外机）架空钢构平台 | K43: 0.5 | L43: 0.5 | M43: 吨 | N43: 8999.8 | O43: =ROUND(N43*(1+$F$10),2) -> 9809.78 | P43: =ROUND(K43*N43,2) -> 4499.9 | Q43: =ROUND(L43*N43,2) -> 4499.9 | T43: =K43-L43 -> 0 | U43: =P43-Q43 -> 0 | V43: =ABS(U43) -> 0 | W43: =T43/L43 -> 0 | X43: =ABS(W43) -> 0
A44: 73 | B44: 1071 | C44: 1614 | D44: 01 | E44: 6 物业施工费 | F44: 6.1 总承包工程 | G44: 6.1.4 空调通风工程 | H44: 空调机/风机安装 | I44: 1000021746 | J44: 空调室外机（含厨房设备室外机）混凝土基座 | M44: 项 | N44: 3313.15 | O44: =ROUND(N44*(1+$F$10),2) -> 3611.33 | P44: =ROUND(K44*N44,2) -> 0 | Q44: =ROUND(L44*N44,2) -> 0 | T44: =K44-L44 -> 0 | U44: =P44-Q44 -> 0 | V44: =ABS(U44) -> 0 | W44: =T44/L44 -> #DIV/0! | X44: =ABS(W44) -> #DIV/0!
A45: 73 | B45: 1071 | C45: 1614 | D45: 01 | E45: 6 物业施工费 | F45: 6.1 总承包工程 | G45: 6.1.4 空调通风工程 | H45: 空调机/风机安装 | I45: 1000022172 | J45: 空调外机铁丝网围壁 | M45: m2 | N45: 114.79 | O45: =ROUND(N45*(1+$F$10),2) -> 125.12 | P45: =ROUND(K45*N45,2) -> 0 | Q45: =ROUND(L45*N45,2) -> 0 | T45: =K45-L45 -> 0 | U45: =P45-Q45 -> 0 | V45: =ABS(U45) -> 0 | W45: =T45/L45 -> #DIV/0! | X45: =ABS(W45) -> #DIV/0!
A46: 45 | B46: 1043 | C46: 1520 | D46: 01 | E46: 5 场地发展费 | F46: 5.2 结构加固 | G46: 结构加固 | H46: 钢结构 | I46: 1000040100 | J46: 钢构空调室外机架空平台刷防锈漆 | M46: 项 | O46: =ROUND(N46*(1+$F$10),2) -> 0 | P46: =ROUND(K46*N46,2) -> 0 | Q46: =ROUND(L46*N46,2) -> 0 | T46: =K46-L46 -> 0 | U46: =P46-Q46 -> 0 | V46: =ABS(U46) -> 0 | W46: =T46/L46 -> #DIV/0! | X46: =ABS(W46) -> #DIV/0!
A47: 45 | B47: 1043 | C47: 1520 | D47: 01 | E47: 5 场地发展费 | F47: 5.2 结构加固 | G47: 结构加固 | H47: 结构加固 | I47: 1000040101 | J47: 结构加固 | M47: 项 | O47: =ROUND(N47*(1+$F$10),2) -> 0 | P47: =ROUND(K47*N47,2) -> 0 | Q47: =ROUND(L47*N47,2) -> 0 | T47: =K47-L47 -> 0 | U47: =P47-Q47 -> 0 | V47: =ABS(U47) -> 0 | W47: =T47/L47 -> #DIV/0! | X47: =ABS(W47) -> #DIV/0!
A48: 46 | B48: 1044 | C48: 1530 | D48: 01 | E48: 5 场地发展费 | F48: 5.3 物业外工程 | G48: 物业外工程 | H48: 地面 | I48: 1000021446 | J48: 室外地坪及踏步贴砖（琛雄） | M48: m2 | N48: 174.03 | O48: =ROUND(N48*(1+$F$10),2) -> 189.69 | P48: =ROUND(K48*N48,2) -> 0 | Q48: =ROUND(L48*N48,2) -> 0 | T48: =K48-L48 -> 0 | U48: =P48-Q48 -> 0 | V48: =ABS(U48) -> 0 | W48: =T48/L48 -> #DIV/0! | X48: =ABS(W48) -> #DIV/0!
A49: 46 | B49: 1044 | C49: 1530 | D49: 01 | E49: 5 场地发展费 | F49: 5.3 物业外工程 | G49: 物业外工程 | H49: 地面 | I49: 1000021642 | J49: 室外地坪及踏步贴砖（共荣） | M49: m2 | N49: 159.51 | O49: =ROUND(N49*(1+$F$10),2) -> 173.87 | P49: =ROUND(K49*N49,2) -> 0 | Q49: =ROUND(L49*N49,2) -> 0 | T49: =K49-L49 -> 0 | U49: =P49-Q49 -> 0 | V49: =ABS(U49) -> 0 | W49: =T49/L49 -> #DIV/0! | X49: =ABS(W49) -> #DIV/0!
A50: 46 | B50: 1044 | C50: 1530 | D50: 01 | E50: 5 场地发展费 | F50: 5.3 物业外工程 | G50: 物业外工程 | H50: 地面 | I50: 1000021447 | J50: 室外地坪及踏步贴砖（冠军） | M50: m2 | N50: 184.92 | O50: =ROUND(N50*(1+$F$10),2) -> 201.56 | P50: =ROUND(K50*N50,2) -> 0 | Q50: =ROUND(L50*N50,2) -> 0 | T50: =K50-L50 -> 0 | U50: =P50-Q50 -> 0 | V50: =ABS(U50) -> 0 | W50: =T50/L50 -> #DIV/0! | X50: =ABS(W50) -> #DIV/0!
A51: 46 | B51: 1044 | C51: 1530 | D51: 01 | E51: 5 场地发展费 | F51: 5.3 物业外工程 | G51: 物业外工程 | H51: 地面 | I51: 1000021747 | J51: 室外地坪及踏步贴芝麻灰花岗石 | M51: m2 | N51: 288.05 | O51: =ROUND(N51*(1+$F$10),2) -> 313.97 | P51: =ROUND(K51*N51,2) -> 0 | Q51: =ROUND(L51*N51,2) -> 0 | T51: =K51-L51 -> 0 | U51: =P51-Q51 -> 0 | V51: =ABS(U51) -> 0 | W51: =T51/L51 -> #DIV/0! | X51: =ABS(W51) -> #DIV/0!
A52: 46 | B52: 1044 | C52: 1530 | D52: 01 | E52: 5 场地发展费 | F52: 5.3 物业外工程 | G52: 物业外工程 | H52: 地面 | I52: 1000021748 | J52: 室外踏步基础 | M52: m3 | N52: 531.74 | O52: =ROUND(N52*(1+$F$10),2) -> 579.6 | P52: =ROUND(K52*N52,2) -> 0 | Q52: =ROUND(L52*N52,2) -> 0 | T52: =K52-L52 -> 0 | U52: =P52-Q52 -> 0 | V52: =ABS(U52) -> 0 | W52: =T52/L52 -> #DIV/0! | X52: =ABS(W52) -> #DIV/0!
A53: 46 | B53: 1044 | C53: 1530 | D53: 01 | E53: 5 场地发展费 | F53: 5.3 物业外工程 | G53: 物业外工程 | H53: 地面 | I53: 1000021516 | J53: 步级沿口火烧石--防滑条 | M53: 米 | N53: 47.51 | O53: =ROUND(N53*(1+$F$10),2) -> 51.79 | P53: =ROUND(K53*N53,2) -> 0 | Q53: =ROUND(L53*N53,2) -> 0 | T53: =K53-L53 -> 0 | U53: =P53-Q53 -> 0 | V53: =ABS(U53) -> 0 | W53: =T53/L53 -> #DIV/0! | X53: =ABS(W53) -> #DIV/0!
A54: 46 | B54: 1044 | C54: 1530 | D54: 01 | E54: 5 场地发展费 | F54: 5.3 物业外工程 | G54: 物业外工程 | H54: 地面 | I54: 1000041816 | J54: 步级沿口火烧石--防滑条（共荣） | M54: 米 | N54: 43.88 | O54: =ROUND(N54*(1+$F$10),2) -> 47.83 | P54: =ROUND(K54*N54,2) -> 0 | Q54: =ROUND(L54*N54,2) -> 0 | T54: =K54-L54 -> 0 | U54: =P54-Q54 -> 0 | V54: =ABS(U54) -> 0 | W54: =T54/L54 -> #DIV/0! | X54: =ABS(W54) -> #DIV/0!
A55: 46 | B55: 1044 | C55: 1530 | D55: 01 | E55: 5 场地发展费 | F55: 5.3 物业外工程 | G55: 物业外工程 | H55: 地面 | I55: 1000041822 | J55: 步级沿口火烧石--防滑条（冠军） | M55: 米 | N55: 43.88 | O55: =ROUND(N55*(1+$F$10),2) -> 47.83 | P55: =ROUND(K55*N55,2) -> 0 | Q55: =ROUND(L55*N55,2) -> 0 | T55: =K55-L55 -> 0 | U55: =P55-Q55 -> 0 | V55: =ABS(U55) -> 0 | W55: =T55/L55 -> #DIV/0! | X55: =ABS(W55) -> #DIV/0!
A56: 46 | B56: 1044 | C56: 1530 | D56: 01 | E56: 5 场地发展费 | F56: 5.3 物业外工程 | G56: 物业外工程 | H56: 墙面 | I56: 1000021620 | J56: 室外其它墙面砖（琛雄） | M56: m2 | N56: 167.98 | O56: =ROUND(N56*(1+$F$10),2) -> 183.1 | P56: =ROUND(K56*N56,2) -> 0 | Q56: =ROUND(L56*N56,2) -> 0 | T56: =K56-L56 -> 0 | U56: =P56-Q56 -> 0 | V56: =ABS(U56) -> 0 | W56: =T56/L56 -> #DIV/0! | X56: =ABS(W56) -> #DIV/0!
A57: 46 | B57: 1044 | C57: 1530 | D57: 01 | E57: 5 场地发展费 | F57: 5.3 物业外工程 | G57: 物业外工程 | H57: 墙面 | I57: 1000021675 | J57: 室外其它墙面砖（共荣） | M57: m2 | N57: 147.41 | O57: =ROUND(N57*(1+$F$10),2) -> 160.68 | P57: =ROUND(K57*N57,2) -> 0 | Q57: =ROUND(L57*N57,2) -> 0 | T57: =K57-L57 -> 0 | U57: =P57-Q57 -> 0 | V57: =ABS(U57) -> 0 | W57: =T57/L57 -> #DIV/0! | X57: =ABS(W57) -> #DIV/0!
A58: 46 | B58: 1044 | C58: 1530 | D58: 01 | E58: 5 场地发展费 | F58: 5.3 物业外工程 | G58: 物业外工程 | H58: 墙面 | I58: 1000021621 | J58: 室外其它墙面砖（冠军） | M58: m2 | N58: 169.19 | O58: =ROUND(N58*(1+$F$10),2) -> 184.42 | P58: =ROUND(K58*N58,2) -> 0 | Q58: =ROUND(L58*N58,2) -> 0 | T58: =K58-L58 -> 0 | U58: =P58-Q58 -> 0 | V58: =ABS(U58) -> 0 | W58: =T58/L58 -> #DIV/0! | X58: =ABS(W58) -> #DIV/0!
A59: 46 | B59: 1044 | C59: 1530 | D59: 01 | E59: 5 场地发展费 | F59: 5.3 物业外工程 | G59: 物业外工程 | H59: 墙面 | I59: 1000021448 | J59: 油烟管及铜管桥架等包外墙铝板 | M59: m2 | N59: 376.58 | O59: =ROUND(N59*(1+$F$10),2) -> 410.47 | P59: =ROUND(K59*N59,2) -> 0 | Q59: =ROUND(L59*N59,2) -> 0 | T59: =K59-L59 -> 0 | U59: =P59-Q59 -> 0 | V59: =ABS(U59) -> 0 | W59: =T59/L59 -> #DIV/0! | X59: =ABS(W59) -> #DIV/0!
A60: 46 | B60: 1044 | C60: 1530 | D60: 01 | E60: 5 场地发展费 | F60: 5.3 物业外工程 | G60: 物业外工程 | H60: 墙面 | I60: 1000040102 | J60: 与业主接壤处装饰及结构处理 | M60: 项 | O60: =ROUND(N60*(1+$F$10),2) -> 0 | P60: =ROUND(K60*N60,2) -> 0 | Q60: =ROUND(L60*N60,2) -> 0 | T60: =K60-L60 -> 0 | U60: =P60-Q60 -> 0 | V60: =ABS(U60) -> 0 | W60: =T60/L60 -> #DIV/0! | X60: =ABS(W60) -> #DIV/0!
A61: 46 | B61: 1044 | C61: 1530 | D61: 01 | E61: 5 场地发展费 | F61: 5.3 物业外工程 | G61: 物业外工程 | H61: 墙面 | I61: 1000040103 | J61: 非麦当劳门面之墙体装修（包括与业主商场相邻之墙体外侧装修） | M61: 项 | O61: =ROUND(N61*(1+$F$10),2) -> 0 | P61: =ROUND(K61*N61,2) -> 0 | Q61: =ROUND(L61*N61,2) -> 0 | T61: =K61-L61 -> 0 | U61: =P61-Q61 -> 0 | V61: =ABS(U61) -> 0 | W61: =T61/L61 -> #DIV/0! | X61: =ABS(W61) -> #DIV/0!
A62: 46 | B62: 1044 | C62: 1530 | D62: 01 | E62: 5 场地发展费 | F62: 5.3 物业外工程 | G62: 物业外工程 | H62: 零星绿化 | I62: 1000040032 | J62: 室外零星植物绿化 | M62: m2 | N62: 172.07 | O62: =ROUND(N62*(1+$F$10),2) -> 187.56 | P62: =ROUND(K62*N62,2) -> 0 | Q62: =ROUND(L62*N62,2) -> 0 | T62: =K62-L62 -> 0 | U62: =P62-Q62 -> 0 | V62: =ABS(U62) -> 0 | W62: =T62/L62 -> #DIV/0! | X62: =ABS(W62) -> #DIV/0!
A63: 46 | B63: 1044 | C63: 1530 | D63: 01 | E63: 5 场地发展费 | F63: 5.3 物业外工程 | G63: 物业外工程 | H63: 花槽 | I63: 1000040033 | J63: 独立成品花槽 | M63: 只 | N63: 1635.14 | O63: =ROUND(N63*(1+$F$10),2) -> 1782.3 | P63: =ROUND(K63*N63,2) -> 0 | Q63: =ROUND(L63*N63,2) -> 0 | T63: =K63-L63 -> 0 | U63: =P63-Q63 -> 0 | V63: =ABS(U63) -> 0 | W63: =T63/L63 -> #DIV/0! | X63: =ABS(W63) -> #DIV/0!
A64: 46 | B64: 1044 | C64: 1530 | D64: 01 | E64: 5 场地发展费 | F64: 5.3 物业外工程 | G64: 物业外工程 | H64: 开洞 | I64: 1000021749 | J64: 分离式厨房楼板开洞费 | M64: 项 | N64: 1355 | O64: =ROUND(N64*(1+$F$10),2) -> 1476.95 | P64: =ROUND(K64*N64,2) -> 0 | Q64: =ROUND(L64*N64,2) -> 0 | T64: =K64-L64 -> 0 | U64: =P64-Q64 -> 0 | V64: =ABS(U64) -> 0 | W64: =T64/L64 -> #DIV/0! | X64: =ABS(W64) -> #DIV/0!
A65: 47 | B65: 1045 | C65: 1531 | D65: 01 | E65: 5 场地发展费 | F65: 5.4 道路、停车场的地面和路沿石 | G65: DT道路、停车场的地面和路沿石 | H65: DT土方运输 | I65: 1000040104 | J65: 土方场外运输 | M65: 项 | O65: =ROUND(N65*(1+$F$10),2) -> 0 | P65: =ROUND(K65*N65,2) -> 0 | Q65: =ROUND(L65*N65,2) -> 0 | T65: =K65-L65 -> 0 | U65: =P65-Q65 -> 0 | V65: =ABS(U65) -> 0 | W65: =T65/L65 -> #DIV/0! | X65: =ABS(W65) -> #DIV/0!
A66: 47 | B66: 1045 | C66: 1531 | D66: 01 | E66: 5 场地发展费 | F66: 5.4 道路、停车场的地面和路沿石 | G66: DT道路、停车场的地面和路沿石 | H66: DT机械 | I66: 1000040105 | J66: DT-道路大型机械进出场费 | M66: 项 | O66: =ROUND(N66*(1+$F$10),2) -> 0 | P66: =ROUND(K66*N66,2) -> 0 | Q66: =ROUND(L66*N66,2) -> 0 | T66: =K66-L66 -> 0 | U66: =P66-Q66 -> 0 | V66: =ABS(U66) -> 0 | W66: =T66/L66 -> #DIV/0! | X66: =ABS(W66) -> #DIV/0!
A67: 47 | B67: 1045 | C67: 1531 | D67: 01 | E67: 5 场地发展费 | F67: 5.4 道路、停车场的地面和路沿石 | G67: DT道路、停车场的地面和路沿石 | H67: DT道路 | I67: 1000021750 | J67: DT-路沿石 | M67: 米 | N67: 101.02 | O67: =ROUND(N67*(1+$F$10),2) -> 110.11 | P67: =ROUND(K67*N67,2) -> 0 | Q67: =ROUND(L67*N67,2) -> 0 | T67: =K67-L67 -> 0 | U67: =P67-Q67 -> 0 | V67: =ABS(U67) -> 0 | W67: =T67/L67 -> #DIV/0! | X67: =ABS(W67) -> #DIV/0!
A68: 47 | B68: 1045 | C68: 1531 | D68: 01 | E68: 5 场地发展费 | F68: 5.4 道路、停车场的地面和路沿石 | G68: DT道路、停车场的地面和路沿石 | H68: DT道路 | I68: 1000021751 | J68: DT-道路基层-水泥石屑 | M68: m2 | N68: 108.25 | O68: =ROUND(N68*(1+$F$10),2) -> 117.99 | P68: =ROUND(K68*N68,2) -> 0 | Q68: =ROUND(L68*N68,2) -> 0 | T68: =K68-L68 -> 0 | U68: =P68-Q68 -> 0 | V68: =ABS(U68) -> 0 | W68: =T68/L68 -> #DIV/0! | X68: =ABS(W68) -> #DIV/0!
A69: 47 | B69: 1045 | C69: 1531 | D69: 01 | E69: 5 场地发展费 | F69: 5.4 道路、停车场的地面和路沿石 | G69: DT道路、停车场的地面和路沿石 | H69: DT道路 | I69: 1000021752 | J69: DT-道路面层-混凝土 | M69: m2 | N69: 119.55 | O69: =ROUND(N69*(1+$F$10),2) -> 130.31 | P69: =ROUND(K69*N69,2) -> 0 | Q69: =ROUND(L69*N69,2) -> 0 | T69: =K69-L69 -> 0 | U69: =P69-Q69 -> 0 | V69: =ABS(U69) -> 0 | W69: =T69/L69 -> #DIV/0! | X69: =ABS(W69) -> #DIV/0!
A70: 47 | B70: 1045 | C70: 1531 | D70: 01 | E70: 5 场地发展费 | F70: 5.4 道路、停车场的地面和路沿石 | G70: DT道路、停车场的地面和路沿石 | H70: DT道路 | I70: 1000021753 | J70: DT-道路面层-沥青+碎石 | M70: m2 | N70: 140.3 | O70: =ROUND(N70*(1+$F$10),2) -> 152.93 | P70: =ROUND(K70*N70,2) -> 0 | Q70: =ROUND(L70*N70,2) -> 0 | T70: =K70-L70 -> 0 | U70: =P70-Q70 -> 0 | V70: =ABS(U70) -> 0 | W70: =T70/L70 -> #DIV/0! | X70: =ABS(W70) -> #DIV/0!
A71: 47 | B71: 1045 | C71: 1531 | D71: 01 | E71: 5 场地发展费 | F71: 5.4 道路、停车场的地面和路沿石 | G71: DT道路、停车场的地面和路沿石 | H71: DT道路 | I71: 1000021754 | J71: DT-拆除道路面层 | M71: m2 | N71: 28.27 | O71: =ROUND(N71*(1+$F$10),2) -> 30.81 | P71: =ROUND(K71*N71,2) -> 0 | Q71: =ROUND(L71*N71,2) -> 0 | T71: =K71-L71 -> 0 | U71: =P71-Q71 -> 0 | V71: =ABS(U71) -> 0 | W71: =T71/L71 -> #DIV/0! | X71: =ABS(W71) -> #DIV/0!
A72: 47 | B72: 1045 | C72: 1531 | D72: 01 | E72: 5 场地发展费 | F72: 5.4 道路、停车场的地面和路沿石 | G72: DT道路、停车场的地面和路沿石 | H72: DT道路 | I72: 1000021755 | J72: DT-感应器预埋 | M72: 套 | N72: 106.03 | O72: =ROUND(N72*(1+$F$10),2) -> 115.57 | P72: =ROUND(K72*N72,2) -> 0 | Q72: =ROUND(L72*N72,2) -> 0 | T72: =K72-L72 -> 0 | U72: =P72-Q72 -> 0 | V72: =ABS(U72) -> 0 | W72: =T72/L72 -> #DIV/0! | X72: =ABS(W72) -> #DIV/0!
A73: 47 | B73: 1045 | C73: 1531 | D73: 01 | E73: 5 场地发展费 | F73: 5.4 道路、停车场的地面和路沿石 | G73: DT道路、停车场的地面和路沿石 | H73: DT道路 | I73: 1000021756 | J73: DT-路面、停车场画线 | M73: 项 | N73: 15300 | O73: =ROUND(N73*(1+$F$10),2) -> 16677 | P73: =ROUND(K73*N73,2) -> 0 | Q73: =ROUND(L73*N73,2) -> 0 | T73: =K73-L73 -> 0 | U73: =P73-Q73 -> 0 | V73: =ABS(U73) -> 0 | W73: =T73/L73 -> #DIV/0! | X73: =ABS(W73) -> #DIV/0!
A74: 47 | B74: 1045 | C74: 1531 | D74: 01 | E74: 5 场地发展费 | F74: 5.4 道路、停车场的地面和路沿石 | G74: DT道路、停车场的地面和路沿石 | H74: DT道路 | I74: 1000021757 | J74: DT-停车位限位器（挡轮器）（每套2只） | M74: 套 | N74: 60.99 | O74: =ROUND(N74*(1+$F$10),2) -> 66.48 | P74: =ROUND(K74*N74,2) -> 0 | Q74: =ROUND(L74*N74,2) -> 0 | T74: =K74-L74 -> 0 | U74: =P74-Q74 -> 0 | V74: =ABS(U74) -> 0 | W74: =T74/L74 -> #DIV/0! | X74: =ABS(W74) -> #DIV/0!
A75: 47 | B75: 1045 | C75: 1531 | D75: 01 | E75: 5 场地发展费 | F75: 5.4 道路、停车场的地面和路沿石 | G75: DT道路、停车场的地面和路沿石 | H75: DT道路 | I75: 1000021758 | J75: DT-减速带 | M75: 米 | N75: 146.19 | O75: =ROUND(N75*(1+$F$10),2) -> 159.35 | P75: =ROUND(K75*N75,2) -> 0 | Q75: =ROUND(L75*N75,2) -> 0 | T75: =K75-L75 -> 0 | U75: =P75-Q75 -> 0 | V75: =ABS(U75) -> 0 | W75: =T75/L75 -> #DIV/0! | X75: =ABS(W75) -> #DIV/0!
A76: 47 | B76: 1045 | C76: 1531 | D76: 01 | E76: 5 场地发展费 | F76: 5.4 道路、停车场的地面和路沿石 | G76: DT道路、停车场的地面和路沿石 | H76: DT地面 | I76: 1000021759 | J76: DT-植（嵌）草砖 | M76: m2 | N76: 265.42 | O76: =ROUND(N76*(1+$F$10),2) -> 289.31 | P76: =ROUND(K76*N76,2) -> 0 | Q76: =ROUND(L76*N76,2) -> 0 | T76: =K76-L76 -> 0 | U76: =P76-Q76 -> 0 | V76: =ABS(U76) -> 0 | W76: =T76/L76 -> #DIV/0! | X76: =ABS(W76) -> #DIV/0!
A77: 47 | B77: 1045 | C77: 1531 | D77: 01 | E77: 5 场地发展费 | F77: 5.4 道路、停车场的地面和路沿石 | G77: DT道路、停车场的地面和路沿石 | H77: DT地面 | I77: 1000021760 | J77: DT-压花地面（仅压花工艺） | M77: m2 | N77: 40.55 | O77: =ROUND(N77*(1+$F$10),2) -> 44.2 | P77: =ROUND(K77*N77,2) -> 0 | Q77: =ROUND(L77*N77,2) -> 0 | T77: =K77-L77 -> 0 | U77: =P77-Q77 -> 0 | V77: =ABS(U77) -> 0 | W77: =T77/L77 -> #DIV/0! | X77: =ABS(W77) -> #DIV/0!
A78: 47 | B78: 1045 | C78: 1531 | D78: 01 | E78: 5 场地发展费 | F78: 5.4 道路、停车场的地面和路沿石 | G78: DT道路、停车场的地面和路沿石 | H78: DT防护 | I78: 1000021761 | J78: DT防撞杆 | M78: 只 | N78: 257.95 | O78: =ROUND(N78*(1+$F$10),2) -> 281.17 | P78: =ROUND(K78*N78,2) -> 0 | Q78: =ROUND(L78*N78,2) -> 0 | T78: =K78-L78 -> 0 | U78: =P78-Q78 -> 0 | V78: =ABS(U78) -> 0 | W78: =T78/L78 -> #DIV/0! | X78: =ABS(W78) -> #DIV/0!
... A110: 51 | B110: 1049 | C110: 1540 | D110: 01 | E110: 5 场地发展费 | F110: 5.8 楼梯结构新建/改造 | G110: 楼梯结构新建/改造 | H110: 楼梯结构新建/改造 | I110: 1000021771 | J110: 新建钢结构楼梯（含设计及资质证明） | M110: 吨 | N110: 9020 | O110: =ROUND(N110*(1+$F$10),2) -> 9831.8 | P110: =ROUND(K110*N110,2) -> 0 | Q110: =ROUND(L110*N110,2) -> 0 | T110: =K110-L110 -> 0 | U110: =P110-Q110 -> 0 | V110: =ABS(U110) -> 0 | W110: =T110/L110 -> #DIV/0! | X110: =ABS(W110) -> #DIV/0!
A111: 51 | B111: 1049 | C111: 1540 | D111: 01 | E111: 5 场地发展费 | F111: 5.8 楼梯结构新建/改造 | G111: 楼梯结构新建/改造 | H111: 楼梯结构新建/改造 | I111: 1000040106 | J111: 新建钢砼楼梯 | M111: 项 | O111: =ROUND(N111*(1+$F$10),2) -> 0 | P111: =ROUND(K111*N111,2) -> 0 | Q111: =ROUND(L111*N111,2) -> 0 | T111: =K111-L111 -> 0 | U111: =P111-Q111 -> 0 | V111: =ABS(U111) -> 0 | W111: =T111/L111 -> #DIV/0! | X111: =ABS(W111) -> #DIV/0!
A112: 51 | B112: 1049 | C112: 1540 | D112: 01 | E112: 5 场地发展费 | F112: 5.8 楼梯结构新建/改造 | G112: 楼梯结构新建/改造 | H112: 楼梯结构新建/改造 | I112: 1000040107 | J112: 改建钢结构楼梯 | M112: 项 | O112: =ROUND(N112*(1+$F$10),2) -> 0 | P112: =ROUND(K112*N112,2) -> 0 | Q112: =ROUND(L112*N112,2) -> 0 | T112: =K112-L112 -> 0 | U112: =P112-Q112 -> 0 | V112: =ABS(U112) -> 0 | W112: =T112/L112 -> #DIV/0! | X112: =ABS(W112) -> #DIV/0!
A113: 51 | B113: 1049 | C113: 1540 | D113: 01 | E113: 5 场地发展费 | F113: 5.8 楼梯结构新建/改造 | G113: 楼梯结构新建/改造 | H113: 楼梯结构新建/改造 | I113: 1000040108 | J113: 改建钢砼楼梯 | M113: 项 | O113: =ROUND(N113*(1+$F$10),2) -> 0 | P113: =ROUND(K113*N113,2) -> 0 | Q113: =ROUND(L113*N113,2) -> 0 | T113: =K113-L113 -> 0 | U113: =P113-Q113 -> 0 | V113: =ABS(U113) -> 0 | W113: =T113/L113 -> #DIV/0! | X113: =ABS(W113) -> #DIV/0!
A114: 56 | B114: 1054 | C114: 1611 | D114: 01 | E114: 6 物业施工费 | F114: 6.1 总承包工程 | G114: 6.1.1 内部装修工程 | H114: 大堂地面（不含卫生间及楼梯） | I114: 1000021456 | J114: 国产同质砖（琛雄，含不超过50mm厚的找平层） | M114: m2 | N114: 180.78 | O114: =ROUND(N114*(1+$F$10),2) -> 197.05 | P114: =ROUND(K114*N114,2) -> 0 | Q114: =ROUND(L114*N114,2) -> 0 | T114: =K114-L114 -> 0 | U114: =P114-Q114 -> 0 | V114: =ABS(U114) -> 0 | W114: =T114/L114 -> #DIV/0! | X114: =ABS(W114) -> #DIV/0!
A115: 56 | B115: 1054 | C115: 1611 | D115: 01 | E115: 6 物业施工费 | F115: 6.1 总承包工程 | G115: 6.1.1 内部装修工程 | H115: 大堂地面（不含卫生间及楼梯） | I115: 1000021457 | J115: 国产同质砖踢脚（琛雄） | M115: 米 | N115: 41.36 | O115: =ROUND(N115*(1+$F$10),2) -> 45.08 | P115: =ROUND(K115*N115,2) -> 0 | Q115: =ROUND(L115*N115,2) -> 0 | T115: =K115-L115 -> 0 | U115: =P115-Q115 -> 0 | V115: =ABS(U115) -> 0 | W115: =T115/L115 -> #DIV/0! | X115: =ABS(W115) -> #DIV/0!
A116: 56 | B116: 1054 | C116: 1611 | D116: 01 | E116: 6 物业施工费 | F116: 6.1 总承包工程 | G116: 6.1.1 内部装修工程 | H116: 大堂地面（不含卫生间及楼梯） | I116: 1000021643 | J116: 国产同质砖（共荣，含不超过50mm厚的找平层） | M116: m2 | N116: 160.21 | O116: =ROUND(N116*(1+$F$10),2) -> 174.63 | P116: =ROUND(K116*N116,2) -> 0 | Q116: =ROUND(L116*N116,2) -> 0 | T116: =K116-L116 -> 0 | U116: =P116-Q116 -> 0 | V116: =ABS(U116) -> 0 | W116: =T116/L116 -> #DIV/0! | X116: =ABS(W116) -> #DIV/0!
A117: 56 | B117: 1054 | C117: 1611 | D117: 01 | E117: 6 物业施工费 | F117: 6.1 总承包工程 | G117: 6.1.1 内部装修工程 | H117: 大堂地面（不含卫生间及楼梯） | I117: 1000021644 | J117: 国产同质砖踢脚（共荣） | M117: 米 | N117: 38.94 | O117: =ROUND(N117*(1+$F$10),2) -> 42.44 | P117: =ROUND(K117*N117,2) -> 0 | Q117: =ROUND(L117*N117,2) -> 0 | T117: =K117-L117 -> 0 | U117: =P117-Q117 -> 0 | V117: =ABS(U117) -> 0 | W117: =T117/L117 -> #DIV/0! | X117: =ABS(W117) -> #DIV/0!
A118: 56 | B118: 1054 | C118: 1611 | D118: 01 | E118: 6 物业施工费 | F118: 6.1 总承包工程 | G118: 6.1.1 内部装修工程 | H118: 大堂地面（不含卫生间及楼梯） | I118: 1000021622 | J118: 国产同质砖（冠军，含不超过50mm厚的找平层） | M118: m2 | N118: 181.99 | O118: =ROUND(N118*(1+$F$10),2) -> 198.37 | P118: =ROUND(K118*N118,2) -> 0 | Q118: =ROUND(L118*N118,2) -> 0 | T118: =K118-L118 -> 0 | U118: =P118-Q118 -> 0 | V118: =ABS(U118) -> 0 | W118: =T118/L118 -> #DIV/0! | X118: =ABS(W118) -> #DIV/0!
A119: 56 | B119: 1054 | C119: 1611 | D119: 01 | E119: 6 物业施工费 | F119: 6.1 总承包工程 | G119: 6.1.1 内部装修工程 | H119: 大堂地面（不含卫生间及楼梯） | I119: 1000021623 | J119: 国产同质砖踢脚（冠军） | M119: 米 | N119: 42.57 | O119: =ROUND(N119*(1+$F$10),2) -> 46.4 | P119: =ROUND(K119*N119,2) -> 0 | Q119: =ROUND(L119*N119,2) -> 0 | T119: =K119-L119 -> 0 | U119: =P119-Q119 -> 0 | V119: =ABS(U119) -> 0 | W119: =T119/L119 -> #DIV/0! | X119: =ABS(W119) -> #DIV/0!
A120: 56 | B120: 1054 | C120: 1611 | D120: 01 | E120: 6 物业施工费 | F120: 6.1 总承包工程 | G120: 6.1.1 内部装修工程 | H120: 大堂地面（不含卫生间及楼梯） | I120: 1000051755 | J120: 600*600mm灰色水泥地砖（琛雄，含不超过50mm厚的找平层） | M120: m2 | N120: 187.98 | O120: =ROUND(N120*(1+$F$10),2) -> 204.9 | P120: =ROUND(K120*N120,2) -> 0 | Q120: =ROUND(L120*N120,2) -> 0 | T120: =K120-L120 -> 0 | U120: =P120-Q120 -> 0 | V120: =ABS(U120) -> 0 | W120: =T120/L120 -> #DIV/0! | X120: =ABS(W120) -> #DIV/0!
A121: 56 | B121: 1054 | C121: 1611 | D121: 01 | E121: 6 物业施工费 | F121: 6.1 总承包工程 | G121: 6.1.1 内部装修工程 | H121: 大堂地面（不含卫生间及楼梯） | I121: 1000051756 | J121: 600*600mm灰色水泥地砖（共荣，含不超过50mm厚的找平层） | M121: m2 | N121: 171.66 | O121: =ROUND(N121*(1+$F$10),2) -> 187.11 | P121: =ROUND(K121*N121,2) -> 0 | Q121: =ROUND(L121*N121,2) -> 0 | T121: =K121-L121 -> 0 | U121: =P121-Q121 -> 0 | V121: =ABS(U121) -> 0 | W121: =T121/L121 -> #DIV/0! | X121: =ABS(W121) -> #DIV/0!
A122: 56 | B122: 1054 | C122: 1611 | D122: 01 | E122: 6 物业施工费 | F122: 6.1 总承包工程 | G122: 6.1.1 内部装修工程 | H122: 大堂地面（不含卫生间及楼梯） | I122: 1000051757 | J122: 600*600mm灰色水泥地砖（冠军，含不超过50mm厚的找平层） | M122: m2 | N122: 189.15 | O122: =ROUND(N122*(1+$F$10),2) -> 206.17 | P122: =ROUND(K122*N122,2) -> 0 | Q122: =ROUND(L122*N122,2) -> 0 | T122: =K122-L122 -> 0 | U122: =P122-Q122 -> 0 | V122: =ABS(U122) -> 0 | W122: =T122/L122 -> #DIV/0! | X122: =ABS(W122) -> #DIV/0!
A123: 56 | B123: 1054 | C123: 1611 | D123: 01 | E123: 6 物业施工费 | F123: 6.1 总承包工程 | G123: 6.1.1 内部装修工程 | H123: 大堂地面（不含卫生间及楼梯） | I123: 1000053612 | J123: 灰色水泥纹踢脚（琛雄） | M123: 米 | N123: 41.36 | O123: =ROUND(N123*(1+$F$10),2) -> 45.08 | P123: =ROUND(K123*N123,2) -> 0 | Q123: =ROUND(L123*N123,2) -> 0 | T123: =K123-L123 -> 0 | U123: =P123-Q123 -> 0 | V123: =ABS(U123) -> 0 | W123: =T123/L123 -> #DIV/0! | X123: =ABS(W123) -> #DIV/0!
A124: 56 | B124: 1054 | C124: 1611 | D124: 01 | E124: 6 物业施工费 | F124: 6.1 总承包工程 | G124: 6.1.1 内部装修工程 | H124: 大堂地面（不含卫生间及楼梯） | I124: 1000053613 | J124: 灰色水泥纹踢脚（共荣） | M124: 米 | N124: 38.94 | O124: =ROUND(N124*(1+$F$10),2) -> 42.44 | P124: =ROUND(K124*N124,2) -> 0 | Q124: =ROUND(L124*N124,2) -> 0 | T124: =K124-L124 -> 0 | U124: =P124-Q124 -> 0 | V124: =ABS(U124) -> 0 | W124: =T124/L124 -> #DIV/0! | X124: =ABS(W124) -> #DIV/0!
A125: 56 | B125: 1054 | C125: 1611 | D125: 01 | E125: 6 物业施工费 | F125: 6.1 总承包工程 | G125: 6.1.1 内部装修工程 | H125: 大堂地面（不含卫生间及楼梯） | I125: 1000053614 | J125: 灰色水泥纹踢脚（冠军） | M125: 米 | N125: 40.15 | O125: =ROUND(N125*(1+$F$10),2) -> 43.76 | P125: =ROUND(K125*N125,2) -> 0 | Q125: =ROUND(L125*N125,2) -> 0 | T125: =K125-L125 -> 0 | U125: =P125-Q125 -> 0 | V125: =ABS(U125) -> 0 | W125: =T125/L125 -> #DIV/0! | X125: =ABS(W125) -> #DIV/0!
... A127: 56 | B127: 1054 | C127: 1611 | D127: 01 | E127: 6 物业施工费 | F127: 6.1 总承包工程 | G127: 6.1.1 内部装修工程 | H127: 大堂地面（不含卫生间及楼梯） | I127: 1000021678 | J127: 混凝土地面砖（共荣，人字形拼接） | M127: m2 | N127: 203.42 | O127: =ROUND(N127*(1+$F$10),2) -> 221.73 | P127: =ROUND(K127*N127,2) -> 0 | Q127: =ROUND(L127*N127,2) -> 0 | T127: =K127-L127 -> 0 | U127: =P127-Q127 -> 0 | V127: =ABS(U127) -> 0 | W127: =T127/L127 -> #DIV/0! | X127: =ABS(W127) -> #DIV/0!
A128: 56 | B128: 1054 | C128: 1611 | D128: 01 | E128: 6 物业施工费 | F128: 6.1 总承包工程 | G128: 6.1.1 内部装修工程 | H128: 大堂地面（不含卫生间及楼梯） | I128: 1000021460 | J128: 混凝土地面砖（冠军，人字形拼接） | K128: 81.33 | L128: 81.12 | M128: m2 | N128: 222.39 | O128: =ROUND(N128*(1+$F$10),2) -> 242.41 | P128: =ROUND(K128*N128,2) -> 18086.98 | Q128: =ROUND(L128*N128,2) -> 18040.28 | T128: =K128-L128 -> 0.21 | U128: =P128-Q128 -> 46.7 | V128: =ABS(U128) -> 46.7 | W128: =T128/L128 -> 0.0025887574 | X128: =ABS(W128) -> 0.0025887574
A129: 56 | B129: 1054 | C129: 1611 | D129: 01 | E129: 6 物业施工费 | F129: 6.1 总承包工程 | G129: 6.1.1 内部装修工程 | H129: 大堂地面（不含卫生间及楼梯） | I129: 1000041810 | J129: 黑色踢脚（琛雄，Geometry） | M129: 米 | N129: 41.36 | O129: =ROUND(N129*(1+$F$10),2) -> 45.08 | P129: =ROUND(K129*N129,2) -> 0 | Q129: =ROUND(L129*N129,2) -> 0 | T129: =K129-L129 -> 0 | U129: =P129-Q129 -> 0 | V129: =ABS(U129) -> 0 | W129: =T129/L129 -> #DIV/0! | X129: =ABS(W129) -> #DIV/0!
A130: 56 | B130: 1054 | C130: 1611 | D130: 01 | E130: 6 物业施工费 | F130: 6.1 总承包工程 | G130: 6.1.1 内部装修工程 | H130: 大堂地面（不含卫生间及楼梯） | I130: 1000041812 | J130: 黑色踢脚（共荣，Geometry） | M130: 米 | N130: 40.15 | O130: =ROUND(N130*(1+$F$10),2) -> 43.76 | P130: =ROUND(K130*N130,2) -> 0 | Q130: =ROUND(L130*N130,2) -> 0 | T130: =K130-L130 -> 0 | U130: =P130-Q130 -> 0 | V130: =ABS(U130) -> 0 | W130: =T130/L130 -> #DIV/0! | X130: =ABS(W130) -> #DIV/0!
A131: 56 | B131: 1054 | C131: 1611 | D131: 01 | E131: 6 物业施工费 | F131: 6.1 总承包工程 | G131: 6.1.1 内部装修工程 | H131: 大堂地面（不含卫生间及楼梯） | I131: 1000041818 | J131: 黑色踢脚（冠军，Geometry） | K131: =72.34+6.49+0.36+8.32 -> 87.51 | L131: =77.15+0.31+10.04 -> 87.5 | M131: 米 | N131: 41.36 | O131: =ROUND(N131*(1+$F$10),2) -> 45.08 | P131: =ROUND(K131*N131,2) -> 3619.41 | Q131: =ROUND(L131*N131,2) -> 3619 | T131: =K131-L131 -> 0.01 | U131: =P131-Q131 -> 0.41 | V131: =ABS(U131) -> 0.41 | W131: =T131/L131 -> 0.00011428571 | X131: =ABS(W131) -> 0.00011428571
A132: 56 | B132: 1054 | C132: 1611 | D132: 01 | E132: 6 物业施工费 | F132: 6.1 总承包工程 | G132: 6.1.1 内部装修工程 | H132: 大堂地面（不含卫生间及楼梯） | I132: 1000021666 | J132: 600*600mm水磨石地砖（琛雄，含不超过50mm厚的找平层） | M132: m2 | N132: 196.14 | O132: =ROUND(N132*(1+$F$10),2) -> 213.79 | P132: =ROUND(K132*N132,2) -> 0 | Q132: =ROUND(L132*N132,2) -> 0 | T132: =K132-L132 -> 0 | U132: =P132-Q132 -> 0 | V132: =ABS(U132) -> 0 | W132: =T132/L132 -> #DIV/0! | X132: =ABS(W132) -> #DIV/0!
A133: 56 | B133: 1054 | C133: 1611 | D133: 01 | E133: 6 物业施工费 | F133: 6.1 总承包工程 | G133: 6.1.1 内部装修工程 | H133: 大堂地面（不含卫生间及楼梯） | I133: 1000021667 | J133: 琛雄水磨石踢脚 | M133: 米 | N133: 41.47 | O133: =ROUND(N133*(1+$F$10),2) -> 45.2 | P133: =ROUND(K133*N133,2) -> 0 | Q133: =ROUND(L133*N133,2) -> 0 | T133: =K133-L133 -> 0 | U133: =P133-Q133 -> 0 | V133: =ABS(U133) -> 0 | W133: =T133/L133 -> #DIV/0! | X133: =ABS(W133) -> #DIV/0!
...

Sheet 其他
A1: 区域 | C1: 麦当劳项目经理
A2: 市场/城市 | C2: 餐厅编号
A3: 餐厅名称 | C3: ppcode
A4: 面积 | C4: 餐厅地址
A5: 座位数 | C5: 税率
A6: 注意：填写Asset Code和PMT Code时，请对照资产分摊表中的Q列Asset Code和BD列的PMT Code对应关系填写，Asset Code和PMT Code必须都为四位编码。填写完毕之后，请校验资产分摊表和FA的汇总金额是否一致，税率必填。
A7: Asset Code | B7: PMT Code | C7: 描述（请参照描述信息参考页将分摊表中的合并描述按规则拆分之后填写在下列表格中） | D7: 单价 | E7: 小计（下列金额和数量都为必填项）
E8: Main Store （不含税金额） | F8: 数量 | G8: Remote Kiosk （不含税金额） | H8: 数量 | I8: Attached Kiosk （不含税金额） | J8: 数量 | K8: McCafe （不含税金额） | L8: 数量 | M8: MDS （不含税金额） | N8: 数量 | O8: Hot Kiosk （不含税金额） | P8: 数量 | Q8: Dessert bar （不含税金额） | R8: 数量
A66: 分项小计： | E66: =SUM(E9:E65) -> 0 | G66: =SUM(G9:G65) -> 0 | I66: =SUM(I9:I65) -> 0 | K66: =SUM(K9:K65) -> 0 | M66: =SUM(M9:M65) -> 0 | O66: =SUM(O9:O65) -> 0 | Q66: =SUM(Q9:Q65) -> 0
A67: 总计： | E67: =SUM(E66:Q66) -> 0
A70: 备注：
A71: 1. 请完整填写以上信息，以免影响付款；
A72: 2. 请根据采购设备或安装服务的归属，准确将小计金额填写在所属的投资分类项中
A73: Main Store--母店，Remote Kiosk--外甜， Attached Kiosk--内甜， McCafe--麦咖啡， MDS--外送，Hot Kiosk--热甜，Dessert bar--甜品吧
A74: 3. 可插入行记录。

Sheet 描述信息参考页
A1: Asset Code | B1: 分摊表描述 | C1: 其他页【描述】字段填写标准
A2: 6002 | B2: 基础 仅适用于DT | C2: 房产建筑DT
A3: 6002 | B3: 主体建筑(仅适用于DT) | C3: 主体建筑DT
A4: 6002 | B4: 外立面(仅适用于DT) | C4: 外立面DT
A5: 1220 | B5: Required test( i.e .water quality)(检测费用)(地质,水质等) | C5: 检测费
A6: 1314 | B6: Construction cost to bright electricity to store 红线电缆接线费 | C6: 电缆工程
A7: 1320 | B7: Sewer and water conneciton fees 给水,排水 接驳费 | C7: 供排水接驳费
A8: 1350 | B8: Telephone services 电话系统 | C8: 电话系统
A9: 1360 | B9: Other permits application fee 其他许可证申请费,含招标费/环评费等 | C9: 许可证申请费
A10: 1410 | B10: Structure demolition 埸地清拆 | C10: 埸地清拆
A11: 1420 | B11: Hoarding 围墙板 | C11: 围墙板
A12: 1510 | B12: Site preparation 埸地准备 | C12: 埸地准备
A13: 1520 | B13: Structure reinforcement 结构加固 | C13: 结构加固
... A36: 1612 | B36: Electrical sub-contract 电承包-不包括灯具 | C36: 电气工程
A37: 1612 | C37: 变压器
A38: 1646 | B38: Dining light fixture only 灯具-顾客就餐区-不包括装饰吊灯具 | C38: 客区照明-各种筒灯及射灯
A39: 1646 | B39: Other light fixture only 其他灯具-包括厨房区及建筑照明 | C39: 厨房照明-各种格栅灯盘
A40: 1613 | B40: Plumbing & sanitation sub-constract 给排水承包 | C40: 排水工程
A41: 1614 | B41: HVAC sub-contract 空调机组安装和管道承包，不含空调设备费用 | C41: 空调管道工程
A42: 1621 | B42: Fire service Design and engineering 消防设计 | C42: 消防设计
A43: 1622 | B43: Sprinkler/hydrant system 喷淋/消防栓系统 | C43: 喷淋消防栓系统
A44: 1623 | B44: Smoke/heat detector system 烟感/温感系统，强排烟系统 | C44: 消防报警系统
A45: 1630 | B45: Environment protection 环保工程：包括化粪池、隔油池、油烟净化器等 | C45: 环保工程-其他
A46: 1630 | C46: 油烟净化器
A47: 3791 | B47: Signage installtion 招牌安装，含杆标基础，立杆等
A48: 8410 | B48: Safe 保险箱 | C48: 保险箱
A49: 8421 | B49: 电视/录像机／相机／影碟机 | C49: 餐厅电视机
A50: 8421 | C50: 麦咖啡电视机
A51: 8421 | C51: 录像机
A52: 8421 | C52: 相机
A53: 8421 | C53: 影碟机
A54: 8422 | B54: 音响 | C54: 音响
A55: 8423 | B55: 电话/传真机 | C55: 电话
A56: 8423 | C56: 传真机
A57: 8424 | B57: Security monitoring System 安保监控系统/ CO2报警器(Cons.) | C57: CO2报警器
C58: 监控设备
A59: 8426 | B59: Electrical Distribution Panel 配电柜 | C59: 配电柜
A60: 8426 | B60: Electrical Distribution Panel 配电柜 | C60: 经理室IT机柜
A61: 8451 | B61: Others kitchen tools 其他厨房工具/烘手机(Cons.) | C61: 倒油车
A62: 8451 | C62: 密码锁
A63: 8451 | C63: MDS外卖箱
A64: 8451 | C64: 食用油检测仪
A65: 8451 | C65: 烫衣板&电熨斗
A66: 8451 | C66: 节能开水机
A67: 8451 | C67: 其他小件工具
A68: 8452 | B68: Others kitchen tools 其他厨房工具 | C68: 高压水枪
A69: 8452 | C69: 感应龙头
A70: 8452 | C70: 其他清洁工具
A71: 8453 | C71: 吸管箱
A72: 8454 | C72: 烘手器
A73: 8455
A74: 8456 | B74: 烘手机、灭蝇灯 | C74: 灭蝇灯
A75: 8425 | B75: Microwave Oven 微波炉 | C75: 微波炉
A76: 8491 | B76: Air Conditioner 空调设备和控制系统/风幕机/新、排风机(Cons.) | C76: 空调+规格编号
A77: 8491 | C77: 风幕机
A78: 8491 | C78: 新风机
A79: 8491 | C79: 排风机
A80: 8492 | B80: Hot Water Heater 热水器 | C80: 热水器
A81: 8485 | B81: Kawneer Door 铝门 | C81: 铝门
A82: 8496 | B82: Kitchen Exhaust Fan 厨房抽油烟机/VFD智能排烟风机 | C82: 排风扇
A83: 8496 | C83: 油烟机
A84: 8496 | C84: 智能排烟风机
A85: 8497 | B85: Other Hardwares 其他五金件 | C85: 其他五金件
A86: 8900 | B86: Others 其他设备/折叠式换尿布平台 | C86: 取消
A87: 8900 | C87: 外送接单机
A88: 8900 | C88: 其他设备
A89: 8900 | C89: 折叠式换尿布平台
A90: 2991 | B90: Seating installtion 座位安装
A91: 4007 | B91: Décor Package 主题装饰（家具供应商提供的屏风、吊灯等装饰品） | C91: 礼品箱+规格编号
A92: 4007 | C92: 挂画+规格编号
A93: 4007 | C93: 屏风+规格编号
A94: 4007 | C94: 主题装饰
A95: 4007 | C95: 圆吊灯+规格编号
A96: 4007 | C96: 长吊灯+规格编号
A97: 4007 | C97: 其他吊灯+规格编号
A98: 4081 | B98: Decor- Others 其他装饰（沟通栏、布告栏等） | C98: 其他装饰
A99: 4991 | B99: Décor - Installation 装饰品- 安装
A100: 1110 | B100: 设计、QS | C100: 设计、QS
A101: 1110 | B101: 设计、QS | C101: 设计、QS
A102: 1120 | B102: 结构加固设计费 | C102: 结构加固设计费
A103: 1130 | B103: 报建费 | C103: 报建费
A104: 1210 | B104: 场地勘察费 | C104: 场地勘察费
A105: 1311 | B105: 付业主供电费
A106: 1312 | B106: 配电房工程费 | C106: =B106 -> 配电房工程费
A107: 1313 | B107: 电增容费 | C107: =B107 -> 电增容费
A108: 1330 | B108: 煤气装置 | C108: =B108 -> 煤气装置
A109: 1340 | B109: 公共暖气装置 | C109: =B109 -> 公共暖气装置
A110: 1430 | B110: 临时安全设置 | C110: =B110 -> 临时安全设置
A111: 1624 | B111: 手动灭火设备 | C111: 灭火器
A112: 1624 | C112: 消防应急包
A113: 2960 | B113: Seating- others 其他座位 - 室外桌椅，室外垃圾桶等/员休室桌椅 | C113: 儿童椅
A114: 2960 | C114: 沙发+规格编号
A115: 2960 | C115: 沙发垫
A116: 2960 | C116: 其他桌椅
A117: 2960 | C117: 太阳伞+规格编号
A118: 2960 | C118: 员休室桌椅
A119: 3718 | B119: 其他招牌 | C119: 防撞条
A120: 3718 | C120: 取餐牌+规格编号
A121: 3718 | C121: 点餐牌+规格编号
A122: 3718 | C122: 24小时贴墙灯箱
...
